Workbook
Name ActualEICharge: [2]Hidden_Calculations!$G$3:$G$219
Name ActualRentCharge: [2]Hidden_Calculations!$E$3:$E$219
Name ActualSubsidyCharge: [2]Hidden_Calculations!$F$3:$F$219
Name Concessions: [2]Hidden_Calculations!$K$3:$K$219
Name CurrentSubsidyUnpaidCharges: [2]Hidden_Calculations!$Q$3:$Q$219
Name CurrentUnpaidCharges: [2]Hidden_Calculations!$P$3:$P$219
Name EconomicVacancy: [2]Hidden_Calculations!$D$3:$D$219
Name LossGainToLease: [2]Hidden_Calculations!$B$3:$B$219
Name MarketRent: [2]Hidden_Calculations!$A$3:$A$219
Name NumberOfProperties: '[2]Summarize By - Unit'!$AL$1
Name PotentialRent: [2]Hidden_Calculations!$C$3:$C$219
Name Prepaid: [2]Hidden_Calculations!$R$3:$R$219
Name PropertyCount: '[2]Summarize By - Unit'!$AL$6:$AL$224
Name ReceiptsCurrent: [2]Hidden_Calculations!$N$3:$N$219
Name ReceiptsPrior: [2]Hidden_Calculations!$O$3:$O$219
Name RentAdjustments: [2]Hidden_Calculations!$I$3:$I$219
Name RentalIncome: #REF!
Name SubsidyAdjustments: [2]Hidden_Calculations!$J$3:$J$219
Name TABLE: '[1]Property Profile (Variables)'!$V$1:$Z$21
Name UtilityReimbursement: [2]Hidden_Calculations!$H$3:$H$219
Name Writeoffs: [2]Hidden_Calculations!$L$3:$L$219

Sheet Payroll
R1: -1 | S1: 1 | T1: 2 | U1: 3 | V1: 4 | W1: 5 | X1: 6 | Y1: 7 | Z1: 8 | AA1: 9 | AB1: 10 | AC1: 11 | AD1: 12
AX2: =COUNTA(AZ3:BZ3) -> 27 | AY2: States | CR2: Pay Period | CS2: 1 | CT2: 2 | CU2: 3 | CV2: 4 | CW2: 5 | CX2: 6 | CY2: 7 | CZ2: 8 | DA2: 9 | DB2: 10 | DC2: 11 | DD2: 12 | DE2: 13 | DF2: 14 | DG2: 15 | DH2: 16 | DI2: 17 | DJ2: 18 | DK2: 19 | DL2: 20 | DM2: 21 | DN2: 22 | DO2: 23 | DP2: 24 | DQ2: 25 | DR2: 26 | DS2: 27 | DT2: 28
B3: ← Click this filter and uncheck "Hide" box to hide unused rows. | L3: ='[1]Property Profile (Variables)'!F5 -> The Bluffs | AX3: 45866 | AY3: Date of Rate | AZ3: AK | BA3: AZ | BB3: CA | BC3: CO | BD3: FL | BE3: GA | BF3: ID | BG3: IL | BH3: LA | BI3: MD | BJ3: MN | BK3: MO | BL3: MT | BM3: NC | BN3: NJ | BO3: NM | BP3: NV | BQ3: OH | BR3: OK | BS3: OR | BT3: PA | BU3: SC | BV3: TN | BW3: TX | BX3: UT | BY3: VA | BZ3: WA | CA3: WA Work comp SAFE plus LM Stop Gap rate | CC3: Disability Surcharge -Excludign CA, WA, OR, CO | CH3: ACTIVITY DIRECTOR PAYROLL | CK3: 6980-010 ACTIVITY DIRECTOR PAYROLL | CR3: Month Pay Period begins | CS3: -1 | CT3: =MONTH(CT4) -> 1 | CU3: =MONTH(CU4) -> 1 | CV3: =MONTH(CV4) -> 2 | CW3: =MONTH(CW4) -> 2 | CX3: =MONTH(CX4) -> 3 | CY3: =MONTH(CY4) -> 3 | CZ3: =MONTH(CZ4) -> 3 | DA3: =MONTH(DA4) -> 4 | ... DT3: =MONTH(DT4) -> 1
F4: New Rate | G4: Month of New Rate | L4: ='[1]Property Profile (Variables)'!AA2 -> January 1, 2026 through December 31, 2026 | AW4: =LOOKUP($E$9,$AZ$3:$BZ$3,$AZ4:$BZ4) -> 0.112714 | AX4: Payroll Tax | AY4: 45838 | AZ4: 0.0925 | BA4: 0.1032 | BB4: 0.1215 | BC4: 0.10805 | BD4: 0.084 | BE4: 0.1063 | BF4: 0.0885 | BG4: 0.154 | BH4: 0.0913 | BI4: 0.09 | BJ4: 0.1263 | BK4: 0.09218 | BL4: 0.0945 | BM4: 0.0947 | BN4: 0.1135 | BO4: 0.1362 | BP4: 0.1005 | BQ4: 0.0985 | BR4: 0.1225 | BS4: 0.1005 | BT4: 0.147468 | BU4: 0.0881 | BV4: 0.1095 | BW4: 0.134 | BX4: 0.0965 | BY4: 0.0968 | BZ4: 0.112714 | CC4: eff. | CH4: AREA SUPERVISOR | CK4: 6390-050 AREA SUPERVISOR | CR4: Start Pay Period | CS4: 46012 | CT4: =CS4+14 -> 46026 | CU4: =CT4+14 -> 46040 | CV4: =CU4+14 -> 46054 | CW4: =CV4+14 -> 46068 | CX4: =CW4+14 -> 46082 | CY4: =CX4+14 -> 46096 | CZ4: =CY4+14 -> 46110 | DA4: =CZ4+14 -> 46124 | ... DT4: =DS4+14 -> 46390
C5: Payroll Tax Multiplier | E5: =AW4 -> 0.112714 | H5: Rate updated | J5: =AY4 -> 45838 | S5: Payroll Billings Periods per Month | AW5: =LOOKUP($E$9,$AZ$3:$BZ$3,$AZ5:$BZ5) -> 1.4499 | AX5: Workman's Comp. Non-Office | AY5: 45839 | AZ5: 0.0222 | BA5: 0.0222 | BB5: 0.0574 | BC5: 0.0222 | BD5: 0.0222 | BE5: 0.0222 | BF5: 0.0222 | BG5: 0.0222 | BH5: 0.0222 | BI5: 0.0222 | BJ5: 0.0222 | BK5: 0.0222 | BL5: 0.0222 | BM5: 0.0222 | BN5: 0.0222 | BO5: 0.0222 | BP5: 0.0222 | BQ5: =0.01876+0.0004 -> 0.01916 | BR5: 0.0222 | BS5: 0.0222 | BT5: 0.0222 | BU5: 0.0222 | BV5: 0.0222 | BW5: 0.0222 | BX5: 0.0222 | BY5: 0.0222 | BZ5: 1.4499 | CA5: 0 | CC5: 45505 | CH5: BUS OPERATOR PAYROLL | CK5: 6980-020 BUS OPERATOR PAYROLL | CR5: End Pay Period | CS5: =CS4+13 -> 46025 | CT5: =CT4+13 -> 46039 | CU5: =CU4+13 -> 46053 | CV5: =CV4+13 -> 46067 | CW5: =CW4+13 -> 46081 | CX5: =CX4+13 -> 46095 | CY5: =CY4+13 -> 46109 | CZ5: =CZ4+13 -> 46123 | ... DT5: =DT4+13 -> 46403
C6: Workman's Comp. Multiplier | E6: =AW5 -> 1.4499 | F6: =E6 -> 1.4499 | G6: 7 | H6: Rate updated | J6: =AY5 -> 45839 | S6: ='[1]Property Profile (Variables)'!B23 -> Jan | T6: ='[1]Property Profile (Variables)'!C23 -> Feb | U6: ='[1]Property Profile (Variables)'!D23 -> Mar | V6: ='[1]Property Profile (Variables)'!E23 -> Apr | W6: ='[1]Property Profile (Variables)'!F23 -> May | X6: ='[1]Property Profile (Variables)'!G23 -> Jun | Y6: ='[1]Property Profile (Variables)'!H23 -> Jul | Z6: ='[1]Property Profile (Variables)'!I23 -> Aug | ... AD6: ='[1]Property Profile (Variables)'!M23 -> Dec | AE6: Total | AW6: =LOOKUP($E$9,$AZ$3:$BZ$3,$AZ6:$BZ6) -> 1.4499 | AX6: Workman's Comp. Mult. Office | AY6: =AY5 -> 45839 | AZ6: 0.0222 | BA6: 0.0222 | BB6: 0.0574 | BC6: 0.0222 | BD6: 0.0222 | BE6: 0.0222 | BF6: 0.0222 | BG6: 0.0222 | BH6: 0.0222 | BI6: 0.0222 | BJ6: 0.0222 | BK6: 0.0222 | BL6: 0.0222 | BM6: 0.0222 | BN6: 0.0222 | BO6: 0.0222 | BP6: 0.0222 | BQ6: =BQ5 -> 0.01916 | BR6: 0.0222 | BS6: 0.0222 | BT6: 0.0222 | BU6: 0.0222 | BV6: 0.0222 | BW6: 0.0222 | BX6: 0.0222 | BY6: 0.0222 | BZ6: =BZ5 -> 1.4499 | CA6: 0 | CC6: 0.0077 | CH6: COOK PAYROLL | CK6: 6930-010 COOK PAYROLL | CR6: Pay Day | CS6: =CS5+6 -> 46031 | CT6: =CT5+6 -> 46045 | CU6: =CU5+6 -> 46059 | CV6: =CV5+6 -> 46073 | CW6: =CW5+6 -> 46087 | CX6: =CX5+6 -> 46101 | CY6: =CY5+6 -> 46115 | CZ6: =CZ5+6 -> 46129 | ... DT6: =DT5+6 -> 46409
C7: Monthly Health Benefit Exp per employee: | E7: 1072.15 | S7: 2 | T7: 2 | U7: 2 | V7: 2 | W7: 2 | X7: 2 | Y7: 3 | Z7: 2 | AA7: 2 | AB7: 2 | AC7: 2 | AD7: 3 | AE7: =SUM(S7:AD7) -> 26 | AF7: verified for 2026 | CH7: FOOD SERVICE PAYROLL | CK7: 6930-000 FOOD SERVICE PAYROLL | CR7: Bill Day | CS7: =CS6-2 -> 46029 | CT7: =CT6-2 -> 46043 | CU7: =CU6-2 -> 46057 | CV7: =CV6-2 -> 46071 | CW7: =CW6-2 -> 46085 | CX7: =CX6-2 -> 46099 | CY7: =CY6-2 -> 46113 | CZ7: =CZ6-2 -> 46127 | ... DT7: =DT6-2 -> 46407
R8: Health Benefit Billings | S8: 1 | T8: 2 | U8: 2 | V8: 2 | W8: 2 | X8: 2 | Y8: 2 | Z8: 2 | AA8: 2 | AB8: 2 | AC8: 2 | AD8: 3 | AE8: =SUM(S8:AD8) -> 24 | AF8: verified for 2026 | CH8: MAINT CONSULT SALARY | CK8: 6500-400 MAINT CONSULT SALARY | CR8: Days to accrue | CS8: =MAX(0,CS5-DAY(CS5)+1-CS4)+IF(CS9=1,IF(MONTH(CS4)=MONTH(CS5),14,0),0) -> 11 | CT8: =MAX(0,CT5-DAY(CT5)+1-CT4)+IF(CT9=1,IF(MONTH(CT4)=MONTH(CT5),14,0),0) -> 0 | CU8: =MAX(0,CU5-DAY(CU5)+1-CU4)+IF(CU9=1,IF(MONTH(CU4)=MONTH(CU5),14,0),0) -> 14 | CV8: =MAX(0,CV5-DAY(CV5)+1-CV4)+IF(CV9=1,IF(MONTH(CV4)=MONTH(CV5),14,0),0) -> 0 | CW8: =MAX(0,CW5-DAY(CW5)+1-CW4)+IF(CW9=1,IF(MONTH(CW4)=MONTH(CW5),14,0),0) -> 14 | CX8: =MAX(0,CX5-DAY(CX5)+1-CX4)+IF(CX9=1,IF(MONTH(CX4)=MONTH(CX5),14,0),0) -> 0 | CY8: =MAX(0,CY5-DAY(CY5)+1-CY4)+IF(CY9=1,IF(MONTH(CY4)=MONTH(CY5),14,0),0) -> 14 | CZ8: =MAX(0,CZ5-DAY(CZ5)+1-CZ4)+IF(CZ9=1,IF(MONTH(CZ4)=MONTH(CZ5),14,0),0) -> 3 | ... DT8: =MAX(0,DT5-DAY(DT5)+1-DT4)+IF(DT9=1,IF(MONTH(DT4)=MONTH(DT5),14,0),0) -> 0
C9: State where the property is located | E9: ='[1]Property Profile (Variables)'!F6 -> WA | S9: =IF(S7=3," "&S6,"") | T9: =IF(T7=3," "&T6,"") | U9: =IF(U7=3," "&U6,"") | V9: =IF(V7=3," "&V6,"") | W9: =IF(W7=3," "&W6,"") | X9: =IF(X7=3," "&X6,"") | Y9: =IF(Y7=3," "&Y6,"") -> Jul | Z9: =IF(Z7=3," "&Z6,"") | ... AD9: =IF(AD7=3," "&AD6,"") -> Dec | AE9: =S9&T9&U9&V9&W9&X9&Y9&Z9&AA9&AB9&AC9&AD9 -> Jul Dec | CH9: OTHER MAINTENANCE PAYROLL | CK9: 6500-210 OTHER MAINTENANCE PAYROLL | CS9: =IF(MONTH(CS4)=MONTH(CS7),0,1) -> 1 | CT9: =IF(MONTH(CT4)=MONTH(CT7),0,1) -> 0 | CU9: =IF(MONTH(CU4)=MONTH(CU7),0,1) -> 1 | CV9: =IF(MONTH(CV4)=MONTH(CV7),0,1) -> 0 | CW9: =IF(MONTH(CW4)=MONTH(CW7),0,1) -> 1 | CX9: =IF(MONTH(CX4)=MONTH(CX7),0,1) -> 0 | CY9: =IF(MONTH(CY4)=MONTH(CY7),0,1) -> 1 | CZ9: =IF(MONTH(CZ4)=MONTH(CZ7),0,1) -> 1 | ... DT9: =IF(MONTH(DT4)=MONTH(DT7),0,1) -> 0
C10: PAYROLL ADMIN | E10: 36.66 | G10: Safe Fund Rate | H10: 0.0325 | N10: Does the Property Accrue payroll Monthly? | O10: N | R10: =IF('[1]Property Profile (Variables)'!G26="Y","Delivery Schedule","") | S10: =IF($R10="","",'[1]Rental Revenue'!H77) | T10: =IF($R10="","",'[1]Rental Revenue'!I77) | U10: =IF($R10="","",'[1]Rental Revenue'!J77) | V10: =IF($R10="","",'[1]Rental Revenue'!K77) | W10: =IF($R10="","",'[1]Rental Revenue'!L77) | X10: =IF($R10="","",'[1]Rental Revenue'!M77) | Y10: =IF($R10="","",'[1]Rental Revenue'!N77) | Z10: =IF($R10="","",'[1]Rental Revenue'!O77) | ... AD10: =IF($R10="","",'[1]Rental Revenue'!S77) | CH10: PATROL SERVICE PAYROLL | CK10: 6531-000 PATROL SERVICE PAYROLL | CT10: Jan | CU10: Feb | CV10: Mar | CW10: Apr | CX10: May | CY10: Jun | CZ10: Jul | DA10: Aug | DB10: Sep | DC10: Oct | DD10: Nov | DE10: Dec
G11: 401K Match | H11: 1000 | N11: =IF(O10="Y","","Does the Property Accrue payroll at year end only?") -> Does the Property Accrue payroll at year end only? | O11: N | R11: # Occupied Units | S11: ='[1]Budget Worksheet (Sch A)'!AK6 -> 208.32 | T11: ='[1]Budget Worksheet (Sch A)'!AL6 -> 208.32 | U11: ='[1]Budget Worksheet (Sch A)'!AM6 -> 208.32 | V11: ='[1]Budget Worksheet (Sch A)'!AN6 -> 208.32 | W11: ='[1]Budget Worksheet (Sch A)'!AO6 -> 208.32 | X11: ='[1]Budget Worksheet (Sch A)'!AP6 -> 208.32 | Y11: ='[1]Budget Worksheet (Sch A)'!AQ6 -> 208.32 | Z11: ='[1]Budget Worksheet (Sch A)'!AR6 -> 208.32 | ... AD11: ='[1]Budget Worksheet (Sch A)'!AV6 -> 208.32 | CH11: REPAIRS PAYROLL | CK11: 6540-000 REPAIRS PAYROLL | CT11: 1 | CU11: 0 | CV11: 0 | CW11: 0 | CX11: 0 | CY11: 0 | CZ11: 0 | DA11: 0 | DB11: 0 | DC11: 0 | DD11: 0 | DE11: 0 | DF11: 1
O12: =IF(AND(O11="Y",O10="Y"),"Do Not enter Y in both cells, O9 and O10. If accruing monthly leave N in cell O10.","") | AF12: x | CH12: WAITRESS PAYROLL | CK12: 6930-020 WAITRESS PAYROLL
C13: Position | D13: Name | E13: Monthly Amount of Free Rent | F13: Home Prop. | G13: Health Ins. Head Count | H13: Instructor Lead Trainings | I13: Cell Phone Re-imbursement | J13: Date Hired at the Property | K13: Current Hourly Rate of Pay | L13: Proposed % Increase | M13: Proposed Rate of Pay | N13: Hours/ Week | O13: Overtime Hours/ Week | P13: varia-tion? | Q13: Annual Salary | R13: Weeks per yr of Vacation (Optional) | S13: =S6 -> Jan | T13: =T6 -> Feb | U13: =U6 -> Mar | V13: =V6 -> Apr | W13: =W6 -> May | X13: =X6 -> Jun | Y13: =Y6 -> Jul | Z13: =Z6 -> Aug | ... AE13: =AE6 -> Total | AH13: Footnote Formulas
A14: =IF(F14+G14+H14+M14=0,"Uncheck to Hide","") | B14: 6330-000 MANAGEMENT SALARIES | C14: Community Director 1 | D14: Karen Bryandt | F14: 1 | G14: 1 | I14: 35 | J14: 45678 | K14: 48.07 | L14: 0 | M14: =ROUND(K14*(1+L14),2) -> 48.07 | N14: 40 | P14: =IF(SUM(S15:AD15)>0,1,0) -> 0 | Q14: =M14*N14*52 -> 99985.6 | S14: =IF(S15="",$M14*$N14*2*S$7+$P16*S$7+$O14*$M14*1.5*2*S$7+IF($O$10="Y",(SUMIF($CS$3:$DT$3,S$1,$CS$8:$DT$8)-SUMIF($CS$3:$DT$3,R$1,$CS$8:$DT$8))*($M14*$N14*2*S$7+$P16*S$7+$O14*$M14*1.5*2*S$7)/(S$7*14),0)+IF($O$11="Y",(SUMIF($CS$3:$DT$3,S$1,$CS$8:$DT$8)*CU$11-SUMIF($CS$3:$DT$3,R$1,$CS$8:$DT$8)*CT$11)*($M14*$N14*2*S$7+$P16*S$7+$O14*$M14*1.5*2*S$7)/(S$7*14),0),S15) -> 7691.2 | T14: =IF(T15="",$M14*$N14*2*T$7+$P16*T$7+$O14*$M14*1.5*2*T$7+IF($O$10="Y",(SUMIF($CS$3:$DT$3,T$1,$CS$8:$DT$8)-SUMIF($CS$3:$DT$3,S$1,$CS$8:$DT$8))*($M14*$N14*2*T$7+$P16*T$7+$O14*$M14*1.5*2*T$7)/(T$7*14),0)+IF($O$11="Y",(SUMIF($CS$3:$DT$3,T$1,$CS$8:$DT$8)*CV$11-SUMIF($CS$3:$DT$3,S$1,$CS$8:$DT$8)*CU$11)*($M14*$N14*2*T$7+$P16*T$7+$O14*$M14*1.5*2*T$7)/(T$7*14),0),T15) -> 7691.2 | U14: =IF(U15="",$M14*$N14*2*U$7+$P16*U$7+$O14*$M14*1.5*2*U$7+IF($O$10="Y",(SUMIF($CS$3:$DT$3,U$1,$CS$8:$DT$8)-SUMIF($CS$3:$DT$3,T$1,$CS$8:$DT$8))*($M14*$N14*2*U$7+$P16*U$7+$O14*$M14*1.5*2*U$7)/(U$7*14),0)+IF($O$11="Y",(SUMIF($CS$3:$DT$3,U$1,$CS$8:$DT$8)*CW$11-SUMIF($CS$3:$DT$3,T$1,$CS$8:$DT$8)*CV$11)*($M14*$N14*2*U$7+$P16*U$7+$O14*$M14*1.5*2*U$7)/(U$7*14),0),U15) -> 7691.2 | V14: =IF(V15="",$M14*$N14*2*V$7+$P16*V$7+$O14*$M14*1.5*2*V$7+IF($O$10="Y",(SUMIF($CS$3:$DT$3,V$1,$CS$8:$DT$8)-SUMIF($CS$3:$DT$3,U$1,$CS$8:$DT$8))*($M14*$N14*2*V$7+$P16*V$7+$O14*$M14*1.5*2*V$7)/(V$7*14),0)+IF($O$11="Y",(SUMIF($CS$3:$DT$3,V$1,$CS$8:$DT$8)*CX$11-SUMIF($CS$3:$DT$3,U$1,$CS$8:$DT$8)*CW$11)*($M14*$N14*2*V$7+$P16*V$7+$O14*$M14*1.5*2*V$7)/(V$7*14),0),V15) -> 7691.2 | W14: =IF(W15="",$M14*$N14*2*W$7+$P16*W$7+$O14*$M14*1.5*2*W$7+IF($O$10="Y",(SUMIF($CS$3:$DT$3,W$1,$CS$8:$DT$8)-SUMIF($CS$3:$DT$3,V$1,$CS$8:$DT$8))*($M14*$N14*2*W$7+$P16*W$7+$O14*$M14*1.5*2*W$7)/(W$7*14),0)+IF($O$11="Y",(SUMIF($CS$3:$DT$3,W$1,$CS$8:$DT$8)*CY$11-SUMIF($CS$3:$DT$3,V$1,$CS$8:$DT$8)*CX$11)*($M14*$N14*2*W$7+$P16*W$7+$O14*$M14*1.5*2*W$7)/(W$7*14),0),W15) -> 7691.2 | X14: =IF(X15="",$M14*$N14*2*X$7+$P16*X$7+$O14*$M14*1.5*2*X$7+IF($O$10="Y",(SUMIF($CS$3:$DT$3,X$1,$CS$8:$DT$8)-SUMIF($CS$3:$DT$3,W$1,$CS$8:$DT$8))*($M14*$N14*2*X$7+$P16*X$7+$O14*$M14*1.5*2*X$7)/(X$7*14),0)+IF($O$11="Y",(SUMIF($CS$3:$DT$3,X$1,$CS$8:$DT$8)*CZ$11-SUMIF($CS$3:$DT$3,W$1,$CS$8:$DT$8)*CY$11)*($M14*$N14*2*X$7+$P16*X$7+$O14*$M14*1.5*2*X$7)/(X$7*14),0),X15) -> 7691.2 | Y14: =IF(Y15="",$M14*$N14*2*Y$7+$P16*Y$7+$O14*$M14*1.5*2*Y$7+IF($O$10="Y",(SUMIF($CS$3:$DT$3,Y$1,$CS$8:$DT$8)-SUMIF($CS$3:$DT$3,X$1,$CS$8:$DT$8))*($M14*$N14*2*Y$7+$P16*Y$7+$O14*$M14*1.5*2*Y$7)/(Y$7*14),0)+IF($O$11="Y",(SUMIF($CS$3:$DT$3,Y$1,$CS$8:$DT$8)*DA$11-SUMIF($CS$3:$DT$3,X$1,$CS$8:$DT$8)*CZ$11)*($M14*$N14*2*Y$7+$P16*Y$7+$O14*$M14*1.5*2*Y$7)/(Y$7*14),0),Y15) -> 11536.8 | Z14: =IF(Z15="",$M14*$N14*2*Z$7+$P16*Z$7+$O14*$M14*1.5*2*Z$7+IF($O$10="Y",(SUMIF($CS$3:$DT$3,Z$1,$CS$8:$DT$8)-SUMIF($CS$3:$DT$3,Y$1,$CS$8:$DT$8))*($M14*$N14*2*Z$7+$P16*Z$7+$O14*$M14*1.5*2*Z$7)/(Z$7*14),0)+IF($O$11="Y",(SUMIF($CS$3:$DT$3,Z$1,$CS$8:$DT$8)*DB$11-SUMIF($CS$3:$DT$3,Y$1,$CS$8:$DT$8)*DA$11)*($M14*$N14*2*Z$7+$P16*Z$7+$O14*$M14*1.5*2*Z$7)/(Z$7*14),0),Z15) -> 7691.2 | ... AD14: =IF(AD15="",$M14*$N14*2*AD$7+$P16*AD$7+$O14*$M14*1.5*2*AD$7+IF($O$10="Y",(SUMIF($CS$3:$DT$3,AD$1,$CS$8:$DT$8)-SUMIF($CS$3:$DT$3,AC$1,$CS$8:$DT$8))*($M14*$N14*2*AD$7+$P16*AD$7+$O14*$M14*1.5*2*AD$7)/(AD$7*14),0)+IF($O$11="Y",(SUMIF($CS$3:$DT$3,AD$1,$CS$8:$DT$8)*DF$11-SUMIF($CS$3:$DT$3,AC$1,$CS$8:$DT$8)*DE$11)*($M14*$N14*2*AD$7+$P16*AD$7+$O14*$M14*1.5*2*AD$7)/(AD$7*14),0),AD15) -> 11536.8 | AE14: =SUM(S14:AD14) -> 99985.6
A15: =A14
A16: Do not check this box | P16: =+M14*N14*R14/AE$7 -> 0 | S16: =IF(S15>0,S15-$P16*S$7,+S14-$P16*S$7) -> 7691.2 | T16: =IF(T15>0,T15-$P16*T$7,+T14-$P16*T$7) -> 7691.2 | U16: =IF(U15>0,U15-$P16*U$7,+U14-$P16*U$7) -> 7691.2 | V16: =IF(V15>0,V15-$P16*V$7,+V14-$P16*V$7) -> 7691.2 | W16: =IF(W15>0,W15-$P16*W$7,+W14-$P16*W$7) -> 7691.2 | X16: =IF(X15>0,X15-$P16*X$7,+X14-$P16*X$7) -> 7691.2 | Y16: =IF(Y15>0,Y15-$P16*Y$7,+Y14-$P16*Y$7) -> 11536.8 | Z16: =IF(Z15>0,Z15-$P16*Z$7,+Z14-$P16*Z$7) -> 7691.2 | ... AD16: =IF(AD15>0,AD15-$P16*AD$7,+AD14-$P16*AD$7) -> 11536.8
A17: Do not check this box | S17: =+S16 -> 7691.2 | T17: =+T16+S17 -> 15382.4 | U17: =+U16+T17 -> 23073.6 | V17: =+V16+U17 -> 30764.8 | W17: =+W16+V17 -> 38456 | X17: =+X16+W17 -> 46147.2 | Y17: =+Y16+X17 -> 57684 | Z17: =+Z16+Y17 -> 65375.2 | AA17: =+AA16+Z17 -> 73066.4 | ... AD17: =+AD16+AC17 -> 99985.6
A18: =A15 | C18: Payroll Tax | S18: =IF($E$9="CA",IF(R17<7000,$E$5*S16,($E$5-0.043)*S16),IF($E$9="IL",IF(R17<12960,$E$5*S16,($E$5-0.04125)*S16),IF($E$9="PA",IF(R17<10000,$E$5*S16,($E$5-0.071)*S16),IF($E$9="TX",IF(R17<9000,$E$5*S16,($E$5-0.0363)*S16),IF($E$9="UT",IF(R17<44800,$E$5*S16,0),$E$5*S16))))) -> 866.90592 | T18: =IF($E$9="CA",IF(S17<7000,$E$5*T16,($E$5-0.043)*T16),IF($E$9="IL",IF(S17<12960,$E$5*T16,($E$5-0.04125)*T16),IF($E$9="PA",IF(S17<10000,$E$5*T16,($E$5-0.071)*T16),IF($E$9="TX",IF(S17<9000,$E$5*T16,($E$5-0.0363)*T16),IF($E$9="UT",IF(S17<44800,$E$5*T16,0),$E$5*T16))))) -> 866.90592 | U18: =IF($E$9="CA",IF(T17<7000,$E$5*U16,($E$5-0.043)*U16),IF($E$9="IL",IF(T17<12960,$E$5*U16,($E$5-0.04125)*U16),IF($E$9="PA",IF(T17<10000,$E$5*U16,($E$5-0.071)*U16),IF($E$9="TX",IF(T17<9000,$E$5*U16,($E$5-0.0363)*U16),IF($E$9="UT",IF(T17<44800,$E$5*U16,0),$E$5*U16))))) -> 866.90592 | V18: =IF($E$9="CA",IF(U17<7000,$E$5*V16,($E$5-0.043)*V16),IF($E$9="IL",IF(U17<12960,$E$5*V16,($E$5-0.04125)*V16),IF($E$9="PA",IF(U17<10000,$E$5*V16,($E$5-0.071)*V16),IF($E$9="TX",IF(U17<9000,$E$5*V16,($E$5-0.0363)*V16),IF($E$9="UT",IF(U17<44800,$E$5*V16,0),$E$5*V16))))) -> 866.90592 | W18: =IF($E$9="CA",IF(V17<7000,$E$5*W16,($E$5-0.043)*W16),IF($E$9="IL",IF(V17<12960,$E$5*W16,($E$5-0.04125)*W16),IF($E$9="PA",IF(V17<10000,$E$5*W16,($E$5-0.071)*W16),IF($E$9="TX",IF(V17<9000,$E$5*W16,($E$5-0.0363)*W16),IF($E$9="UT",IF(V17<44800,$E$5*W16,0),$E$5*W16))))) -> 866.90592 | X18: =IF($E$9="CA",IF(W17<7000,$E$5*X16,($E$5-0.043)*X16),IF($E$9="IL",IF(W17<12960,$E$5*X16,($E$5-0.04125)*X16),IF($E$9="PA",IF(W17<10000,$E$5*X16,($E$5-0.071)*X16),IF($E$9="TX",IF(W17<9000,$E$5*X16,($E$5-0.0363)*X16),IF($E$9="UT",IF(W17<44800,$E$5*X16,0),$E$5*X16))))) -> 866.90592 | Y18: =IF($E$9="CA",IF(X17<7000,$E$5*Y16,($E$5-0.043)*Y16),IF($E$9="IL",IF(X17<12960,$E$5*Y16,($E$5-0.04125)*Y16),IF($E$9="PA",IF(X17<10000,$E$5*Y16,($E$5-0.071)*Y16),IF($E$9="TX",IF(X17<9000,$E$5*Y16,($E$5-0.0363)*Y16),IF($E$9="UT",IF(X17<44800,$E$5*Y16,0),$E$5*Y16))))) -> 1300.3589 | Z18: =IF($E$9="CA",IF(Y17<7000,$E$5*Z16,($E$5-0.043)*Z16),IF($E$9="IL",IF(Y17<12960,$E$5*Z16,($E$5-0.04125)*Z16),IF($E$9="PA",IF(Y17<10000,$E$5*Z16,($E$5-0.071)*Z16),IF($E$9="TX",IF(Y17<9000,$E$5*Z16,($E$5-0.0363)*Z16),IF($E$9="UT",IF(Y17<44800,$E$5*Z16,0),$E$5*Z16))))) -> 866.90592 | ... AD18: =IF($E$9="CA",IF(AC17<7000,$E$5*AD16,($E$5-0.043)*AD16),IF($E$9="IL",IF(AC17<12960,$E$5*AD16,($E$5-0.04125)*AD16),IF($E$9="PA",IF(AC17<10000,$E$5*AD16,($E$5-0.071)*AD16),IF($E$9="TX",IF(AC17<9000,$E$5*AD16,($E$5-0.0363)*AD16),IF($E$9="UT",IF(AC17<44800,$E$5*AD16,0),$E$5*AD16))))) -> 1300.3589
A19: =A18 | C19: Workman's Comp | S19: =IF($E$9="WA",IF(S$1<$G$6,$E$6*$N14*2*S$7+$CA$5*S16,$F$6*$N14*2*S$7+$CA$5*S16),IF($E$9="NV",IF(R17>36000,0,IF(S$1<$G$6,$E$6*S16,$F$6*S16)),IF(S$1<$G$6,$E$6*S16,$F$6*S16))) -> 231.984 | T19: =IF($E$9="WA",IF(T$1<$G$6,$E$6*$N14*2*T$7+$CA$5*T16,$F$6*$N14*2*T$7+$CA$5*T16),IF($E$9="NV",IF(S17>36000,0,IF(T$1<$G$6,$E$6*T16,$F$6*T16)),IF(T$1<$G$6,$E$6*T16,$F$6*T16))) -> 231.984 | U19: =IF($E$9="WA",IF(U$1<$G$6,$E$6*$N14*2*U$7+$CA$5*U16,$F$6*$N14*2*U$7+$CA$5*U16),IF($E$9="NV",IF(T17>36000,0,IF(U$1<$G$6,$E$6*U16,$F$6*U16)),IF(U$1<$G$6,$E$6*U16,$F$6*U16))) -> 231.984 | V19: =IF($E$9="WA",IF(V$1<$G$6,$E$6*$N14*2*V$7+$CA$5*V16,$F$6*$N14*2*V$7+$CA$5*V16),IF($E$9="NV",IF(U17>36000,0,IF(V$1<$G$6,$E$6*V16,$F$6*V16)),IF(V$1<$G$6,$E$6*V16,$F$6*V16))) -> 231.984 | W19: =IF($E$9="WA",IF(W$1<$G$6,$E$6*$N14*2*W$7+$CA$5*W16,$F$6*$N14*2*W$7+$CA$5*W16),IF($E$9="NV",IF(V17>36000,0,IF(W$1<$G$6,$E$6*W16,$F$6*W16)),IF(W$1<$G$6,$E$6*W16,$F$6*W16))) -> 231.984 | X19: =IF($E$9="WA",IF(X$1<$G$6,$E$6*$N14*2*X$7+$CA$5*X16,$F$6*$N14*2*X$7+$CA$5*X16),IF($E$9="NV",IF(W17>36000,0,IF(X$1<$G$6,$E$6*X16,$F$6*X16)),IF(X$1<$G$6,$E$6*X16,$F$6*X16))) -> 231.984 | Y19: =IF($E$9="WA",IF(Y$1<$G$6,$E$6*$N14*2*Y$7+$CA$5*Y16,$F$6*$N14*2*Y$7+$CA$5*Y16),IF($E$9="NV",IF(X17>36000,0,IF(Y$1<$G$6,$E$6*Y16,$F$6*Y16)),IF(Y$1<$G$6,$E$6*Y16,$F$6*Y16))) -> 347.976 | Z19: =IF($E$9="WA",IF(Z$1<$G$6,$E$6*$N14*2*Z$7+$CA$5*Z16,$F$6*$N14*2*Z$7+$CA$5*Z16),IF($E$9="NV",IF(Y17>36000,0,IF(Z$1<$G$6,$E$6*Z16,$F$6*Z16)),IF(Z$1<$G$6,$E$6*Z16,$F$6*Z16))) -> 231.984 | ... AD19: =IF($E$9="WA",IF(AD$1<$G$6,$E$6*$N14*2*AD$7+$CA$5*AD16,$F$6*$N14*2*AD$7+$CA$5*AD16),IF($E$9="NV",IF(AC17>36000,0,IF(AD$1<$G$6,$E$6*AD16,$F$6*AD16)),IF(AD$1<$G$6,$E$6*AD16,$F$6*AD16))) -> 347.976
A20: =A19 | C20: 401K Match | S20: =IF(S14=0,0,$H$11/26*S$7*IF(OR($G14=0,$G14=1),1,$G14)) -> 76.923077 | T20: =IF(T14=0,0,$H$11/26*T$7*IF(OR($G14=0,$G14=1),1,$G14)) -> 76.923077 | U20: =IF(U14=0,0,$H$11/26*U$7*IF(OR($G14=0,$G14=1),1,$G14)) -> 76.923077 | V20: =IF(V14=0,0,$H$11/26*V$7*IF(OR($G14=0,$G14=1),1,$G14)) -> 76.923077 | W20: =IF(W14=0,0,$H$11/26*W$7*IF(OR($G14=0,$G14=1),1,$G14)) -> 76.923077 | X20: =IF(X14=0,0,$H$11/26*X$7*IF(OR($G14=0,$G14=1),1,$G14)) -> 76.923077 | Y20: =IF(Y14=0,0,$H$11/26*Y$7*IF(OR($G14=0,$G14=1),1,$G14)) -> 115.38462 | Z20: =IF(Z14=0,0,$H$11/26*Z$7*IF(OR($G14=0,$G14=1),1,$G14)) -> 76.923077 | ... AD20: =IF(AD14=0,0,$H$11/26*AD$7*IF(OR($G14=0,$G14=1),1,$G14)) -> 115.38462
A21: =A19 | C21: =IF($E$9="CA","",$C$269) -> HEALTH INS. & EMPL. BENEFITS | S21: =IF(OR($E$9="CA",$E$9="CO",$E$9="OR",$E$9="WA"),0,IF($G14=0,0,$G14*$E$7*S$8/2+S16*$CC$6)) -> 0 | T21: =IF(OR($E$9="CA",$E$9="CO",$E$9="OR",$E$9="WA"),0,IF($G14=0,0,$G14*$E$7*T$8/2+T16*$CC$6)) -> 0 | U21: =IF(OR($E$9="CA",$E$9="CO",$E$9="OR",$E$9="WA"),0,IF($G14=0,0,$G14*$E$7*U$8/2+U16*$CC$6)) -> 0 | V21: =IF(OR($E$9="CA",$E$9="CO",$E$9="OR",$E$9="WA"),0,IF($G14=0,0,$G14*$E$7*V$8/2+V16*$CC$6)) -> 0 | W21: =IF(OR($E$9="CA",$E$9="CO",$E$9="OR",$E$9="WA"),0,IF($G14=0,0,$G14*$E$7*W$8/2+W16*$CC$6)) -> 0 | X21: =IF(OR($E$9="CA",$E$9="CO",$E$9="OR",$E$9="WA"),0,IF($G14=0,0,$G14*$E$7*X$8/2+X16*$CC$6)) -> 0 | Y21: =IF(OR($E$9="CA",$E$9="CO",$E$9="OR",$E$9="WA"),0,IF($G14=0,0,$G14*$E$7*Y$8/2+Y16*$CC$6)) -> 0 | Z21: =IF(OR($E$9="CA",$E$9="CO",$E$9="OR",$E$9="WA"),0,IF($G14=0,0,$G14*$E$7*Z$8/2+Z16*$CC$6)) -> 0 | ... AD21: =IF(OR($E$9="CA",$E$9="CO",$E$9="OR",$E$9="WA"),0,IF($G14=0,0,$G14*$E$7*AD$8/2+AD16*$CC$6)) -> 0
A22: =IF(F22+G22+H22+M22=0,"Uncheck to Hide","") -> Uncheck to Hide | B22: =B14 -> 6330-000 MANAGEMENT SALARIES | C22: Community Director 2 | I22: 35 | M22: =ROUND(K22*(1+L22),2) -> 0 | P22: =IF(SUM(S23:AD23)>0,1,0) -> 0 | Q22: =M22*N22*52 -> 0 | S22: =IF(S23="",$M22*$N22*2*S$7+$P24*S$7+$O22*$M22*1.5*2*S$7+IF($O$10="Y",(SUMIF($CS$3:$DT$3,S$1,$CS$8:$DT$8)-SUMIF($CS$3:$DT$3,R$1,$CS$8:$DT$8))*($M22*$N22*2*S$7+$P24*S$7+$O22*$M22*1.5*2*S$7)/(S$7*14),0)+IF($O$11="Y",(SUMIF($CS$3:$DT$3,S$1,$CS$8:$DT$8)*CU$11-SUMIF($CS$3:$DT$3,R$1,$CS$8:$DT$8)*CT$11)*($M22*$N22*2*S$7+$P24*S$7+$O22*$M22*1.5*2*S$7)/(S$7*14),0),S23) -> 0 | T22: =IF(T23="",$M22*$N22*2*T$7+$P24*T$7+$O22*$M22*1.5*2*T$7+IF($O$10="Y",(SUMIF($CS$3:$DT$3,T$1,$CS$8:$DT$8)-SUMIF($CS$3:$DT$3,S$1,$CS$8:$DT$8))*($M22*$N22*2*T$7+$P24*T$7+$O22*$M22*1.5*2*T$7)/(T$7*14),0)+IF($O$11="Y",(SUMIF($CS$3:$DT$3,T$1,$CS$8:$DT$8)*CV$11-SUMIF($CS$3:$DT$3,S$1,$CS$8:$DT$8)*CU$11)*($M22*$N22*2*T$7+$P24*T$7+$O22*$M22*1.5*2*T$7)/(T$7*14),0),T23) -> 0 | U22: =IF(U23="",$M22*$N22*2*U$7+$P24*U$7+$O22*$M22*1.5*2*U$7+IF($O$10="Y",(SUMIF($CS$3:$DT$3,U$1,$CS$8:$DT$8)-SUMIF($CS$3:$DT$3,T$1,$CS$8:$DT$8))*($M22*$N22*2*U$7+$P24*U$7+$O22*$M22*1.5*2*U$7)/(U$7*14),0)+IF($O$11="Y",(SUMIF($CS$3:$DT$3,U$1,$CS$8:$DT$8)*CW$11-SUMIF($CS$3:$DT$3,T$1,$CS$8:$DT$8)*CV$11)*($M22*$N22*2*U$7+$P24*U$7+$O22*$M22*1.5*2*U$7)/(U$7*14),0),U23) -> 0 | V22: =IF(V23="",$M22*$N22*2*V$7+$P24*V$7+$O22*$M22*1.5*2*V$7+IF($O$10="Y",(SUMIF($CS$3:$DT$3,V$1,$CS$8:$DT$8)-SUMIF($CS$3:$DT$3,U$1,$CS$8:$DT$8))*($M22*$N22*2*V$7+$P24*V$7+$O22*$M22*1.5*2*V$7)/(V$7*14),0)+IF($O$11="Y",(SUMIF($CS$3:$DT$3,V$1,$CS$8:$DT$8)*CX$11-SUMIF($CS$3:$DT$3,U$1,$CS$8:$DT$8)*CW$11)*($M22*$N22*2*V$7+$P24*V$7+$O22*$M22*1.5*2*V$7)/(V$7*14),0),V23) -> 0 | W22: =IF(W23="",$M22*$N22*2*W$7+$P24*W$7+$O22*$M22*1.5*2*W$7+IF($O$10="Y",(SUMIF($CS$3:$DT$3,W$1,$CS$8:$DT$8)-SUMIF($CS$3:$DT$3,V$1,$CS$8:$DT$8))*($M22*$N22*2*W$7+$P24*W$7+$O22*$M22*1.5*2*W$7)/(W$7*14),0)+IF($O$11="Y",(SUMIF($CS$3:$DT$3,W$1,$CS$8:$DT$8)*CY$11-SUMIF($CS$3:$DT$3,V$1,$CS$8:$DT$8)*CX$11)*($M22*$N22*2*W$7+$P24*W$7+$O22*$M22*1.5*2*W$7)/(W$7*14),0),W23) -> 0 | X22: =IF(X23="",$M22*$N22*2*X$7+$P24*X$7+$O22*$M22*1.5*2*X$7+IF($O$10="Y",(SUMIF($CS$3:$DT$3,X$1,$CS$8:$DT$8)-SUMIF($CS$3:$DT$3,W$1,$CS$8:$DT$8))*($M22*$N22*2*X$7+$P24*X$7+$O22*$M22*1.5*2*X$7)/(X$7*14),0)+IF($O$11="Y",(SUMIF($CS$3:$DT$3,X$1,$CS$8:$DT$8)*CZ$11-SUMIF($CS$3:$DT$3,W$1,$CS$8:$DT$8)*CY$11)*($M22*$N22*2*X$7+$P24*X$7+$O22*$M22*1.5*2*X$7)/(X$7*14),0),X23) -> 0 | Y22: =IF(Y23="",$M22*$N22*2*Y$7+$P24*Y$7+$O22*$M22*1.5*2*Y$7+IF($O$10="Y",(SUMIF($CS$3:$DT$3,Y$1,$CS$8:$DT$8)-SUMIF($CS$3:$DT$3,X$1,$CS$8:$DT$8))*($M22*$N22*2*Y$7+$P24*Y$7+$O22*$M22*1.5*2*Y$7)/(Y$7*14),0)+IF($O$11="Y",(SUMIF($CS$3:$DT$3,Y$1,$CS$8:$DT$8)*DA$11-SUMIF($CS$3:$DT$3,X$1,$CS$8:$DT$8)*CZ$11)*($M22*$N22*2*Y$7+$P24*Y$7+$O22*$M22*1.5*2*Y$7)/(Y$7*14),0),Y23) -> 0 | Z22: =IF(Z23="",$M22*$N22*2*Z$7+$P24*Z$7+$O22*$M22*1.5*2*Z$7+IF($O$10="Y",(SUMIF($CS$3:$DT$3,Z$1,$CS$8:$DT$8)-SUMIF($CS$3:$DT$3,Y$1,$CS$8:$DT$8))*($M22*$N22*2*Z$7+$P24*Z$7+$O22*$M22*1.5*2*Z$7)/(Z$7*14),0)+IF($O$11="Y",(SUMIF($CS$3:$DT$3,Z$1,$CS$8:$DT$8)*DB$11-SUMIF($CS$3:$DT$3,Y$1,$CS$8:$DT$8)*DA$11)*($M22*$N22*2*Z$7+$P24*Z$7+$O22*$M22*1.5*2*Z$7)/(Z$7*14),0),Z23) -> 0 | ... AD22: =IF(AD23="",$M22*$N22*2*AD$7+$P24*AD$7+$O22*$M22*1.5*2*AD$7+IF($O$10="Y",(SUMIF($CS$3:$DT$3,AD$1,$CS$8:$DT$8)-SUMIF($CS$3:$DT$3,AC$1,$CS$8:$DT$8))*($M22*$N22*2*AD$7+$P24*AD$7+$O22*$M22*1.5*2*AD$7)/(AD$7*14),0)+IF($O$11="Y",(SUMIF($CS$3:$DT$3,AD$1,$CS$8:$DT$8)*DF$11-SUMIF($CS$3:$DT$3,AC$1,$CS$8:$DT$8)*DE$11)*($M22*$N22*2*AD$7+$P24*AD$7+$O22*$M22*1.5*2*AD$7)/(AD$7*14),0),AD23) -> 0 | AE22: =SUM(S22:AD22) -> 0
A23: =A22 -> Uncheck to Hide
A24: Do not check this box | P24: =+M22*N22*R22/AE$7 -> 0 | S24: =IF(S23>0,S23-$P24*S$7,+S22-$P24*S$7) -> 0 | T24: =IF(T23>0,T23-$P24*T$7,+T22-$P24*T$7) -> 0 | U24: =IF(U23>0,U23-$P24*U$7,+U22-$P24*U$7) -> 0 | V24: =IF(V23>0,V23-$P24*V$7,+V22-$P24*V$7) -> 0 | W24: =IF(W23>0,W23-$P24*W$7,+W22-$P24*W$7) -> 0 | X24: =IF(X23>0,X23-$P24*X$7,+X22-$P24*X$7) -> 0 | Y24: =IF(Y23>0,Y23-$P24*Y$7,+Y22-$P24*Y$7) -> 0 | Z24: =IF(Z23>0,Z23-$P24*Z$7,+Z22-$P24*Z$7) -> 0 | ... AD24: =IF(AD23>0,AD23-$P24*AD$7,+AD22-$P24*AD$7) -> 0
A25: Do not check this box | S25: =+S24 -> 0 | T25: =+T24+S25 -> 0 | U25: =+U24+T25 -> 0 | V25: =+V24+U25 -> 0 | W25: =+W24+V25 -> 0 | X25: =+X24+W25 -> 0 | Y25: =+Y24+X25 -> 0 | Z25: =+Z24+Y25 -> 0 | AA25: =+AA24+Z25 -> 0 | ... AD25: =+AD24+AC25 -> 0
A26: =A23 -> Uncheck to Hide | C26: Payroll Tax | S26: =IF($E$9="CA",IF(R25<7000,$E$5*S24,($E$5-0.043)*S24),IF($E$9="IL",IF(R25<12960,$E$5*S24,($E$5-0.04125)*S24),IF($E$9="PA",IF(R25<10000,$E$5*S24,($E$5-0.071)*S24),IF($E$9="TX",IF(R25<9000,$E$5*S24,($E$5-0.0363)*S24),$E$5*S24)))) -> 0 | T26: =IF($E$9="CA",IF(S25<7000,$E$5*T24,($E$5-0.043)*T24),IF($E$9="IL",IF(S25<12960,$E$5*T24,($E$5-0.04125)*T24),IF($E$9="PA",IF(S25<10000,$E$5*T24,($E$5-0.071)*T24),IF($E$9="TX",IF(S25<9000,$E$5*T24,($E$5-0.0363)*T24),$E$5*T24)))) -> 0 | U26: =IF($E$9="CA",IF(T25<7000,$E$5*U24,($E$5-0.043)*U24),IF($E$9="IL",IF(T25<12960,$E$5*U24,($E$5-0.04125)*U24),IF($E$9="PA",IF(T25<10000,$E$5*U24,($E$5-0.071)*U24),IF($E$9="TX",IF(T25<9000,$E$5*U24,($E$5-0.0363)*U24),$E$5*U24)))) -> 0 | V26: =IF($E$9="CA",IF(U25<7000,$E$5*V24,($E$5-0.043)*V24),IF($E$9="IL",IF(U25<12960,$E$5*V24,($E$5-0.04125)*V24),IF($E$9="PA",IF(U25<10000,$E$5*V24,($E$5-0.071)*V24),IF($E$9="TX",IF(U25<9000,$E$5*V24,($E$5-0.0363)*V24),$E$5*V24)))) -> 0 | W26: =IF($E$9="CA",IF(V25<7000,$E$5*W24,($E$5-0.043)*W24),IF($E$9="IL",IF(V25<12960,$E$5*W24,($E$5-0.04125)*W24),IF($E$9="PA",IF(V25<10000,$E$5*W24,($E$5-0.071)*W24),IF($E$9="TX",IF(V25<9000,$E$5*W24,($E$5-0.0363)*W24),$E$5*W24)))) -> 0 | X26: =IF($E$9="CA",IF(W25<7000,$E$5*X24,($E$5-0.043)*X24),IF($E$9="IL",IF(W25<12960,$E$5*X24,($E$5-0.04125)*X24),IF($E$9="PA",IF(W25<10000,$E$5*X24,($E$5-0.071)*X24),IF($E$9="TX",IF(W25<9000,$E$5*X24,($E$5-0.0363)*X24),$E$5*X24)))) -> 0 | Y26: =IF($E$9="CA",IF(X25<7000,$E$5*Y24,($E$5-0.043)*Y24),IF($E$9="IL",IF(X25<12960,$E$5*Y24,($E$5-0.04125)*Y24),IF($E$9="PA",IF(X25<10000,$E$5*Y24,($E$5-0.071)*Y24),IF($E$9="TX",IF(X25<9000,$E$5*Y24,($E$5-0.0363)*Y24),$E$5*Y24)))) -> 0 | Z26: =IF($E$9="CA",IF(Y25<7000,$E$5*Z24,($E$5-0.043)*Z24),IF($E$9="IL",IF(Y25<12960,$E$5*Z24,($E$5-0.04125)*Z24),IF($E$9="PA",IF(Y25<10000,$E$5*Z24,($E$5-0.071)*Z24),IF($E$9="TX",IF(Y25<9000,$E$5*Z24,($E$5-0.0363)*Z24),$E$5*Z24)))) -> 0 | ... AD26: =IF($E$9="CA",IF(AC25<7000,$E$5*AD24,($E$5-0.043)*AD24),IF($E$9="IL",IF(AC25<12960,$E$5*AD24,($E$5-0.04125)*AD24),IF($E$9="PA",IF(AC25<10000,$E$5*AD24,($E$5-0.071)*AD24),IF($E$9="TX",IF(AC25<9000,$E$5*AD24,($E$5-0.0363)*AD24),$E$5*AD24)))) -> 0
A27: =A26 -> Uncheck to Hide | C27: Workman's Comp | S27: =IF($E$9="WA",IF(S$1<$G$6,$E$6*$N22*2*S$7+$CA$5*S24,$F$6*$N22*2*S$7+$CA$5*S24),IF($E$9="NV",IF(R25>36000,0,IF(S$1<$G$6,$E$6*S24,$F$6*S24)),IF(S$1<$G$6,$E$6*S24,$F$6*S24))) -> 0 | T27: =IF($E$9="WA",IF(T$1<$G$6,$E$6*$N22*2*T$7+$CA$5*T24,$F$6*$N22*2*T$7+$CA$5*T24),IF($E$9="NV",IF(S25>36000,0,IF(T$1<$G$6,$E$6*T24,$F$6*T24)),IF(T$1<$G$6,$E$6*T24,$F$6*T24))) -> 0 | U27: =IF($E$9="WA",IF(U$1<$G$6,$E$6*$N22*2*U$7+$CA$5*U24,$F$6*$N22*2*U$7+$CA$5*U24),IF($E$9="NV",IF(T25>36000,0,IF(U$1<$G$6,$E$6*U24,$F$6*U24)),IF(U$1<$G$6,$E$6*U24,$F$6*U24))) -> 0 | V27: =IF($E$9="WA",IF(V$1<$G$6,$E$6*$N22*2*V$7+$CA$5*V24,$F$6*$N22*2*V$7+$CA$5*V24),IF($E$9="NV",IF(U25>36000,0,IF(V$1<$G$6,$E$6*V24,$F$6*V24)),IF(V$1<$G$6,$E$6*V24,$F$6*V24))) -> 0 | W27: =IF($E$9="WA",IF(W$1<$G$6,$E$6*$N22*2*W$7+$CA$5*W24,$F$6*$N22*2*W$7+$CA$5*W24),IF($E$9="NV",IF(V25>36000,0,IF(W$1<$G$6,$E$6*W24,$F$6*W24)),IF(W$1<$G$6,$E$6*W24,$F$6*W24))) -> 0 | X27: =IF($E$9="WA",IF(X$1<$G$6,$E$6*$N22*2*X$7+$CA$5*X24,$F$6*$N22*2*X$7+$CA$5*X24),IF($E$9="NV",IF(W25>36000,0,IF(X$1<$G$6,$E$6*X24,$F$6*X24)),IF(X$1<$G$6,$E$6*X24,$F$6*X24))) -> 0 | Y27: =IF($E$9="WA",IF(Y$1<$G$6,$E$6*$N22*2*Y$7+$CA$5*Y24,$F$6*$N22*2*Y$7+$CA$5*Y24),IF($E$9="NV",IF(X25>36000,0,IF(Y$1<$G$6,$E$6*Y24,$F$6*Y24)),IF(Y$1<$G$6,$E$6*Y24,$F$6*Y24))) -> 0 | Z27: =IF($E$9="WA",IF(Z$1<$G$6,$E$6*$N22*2*Z$7+$CA$5*Z24,$F$6*$N22*2*Z$7+$CA$5*Z24),IF($E$9="NV",IF(Y25>36000,0,IF(Z$1<$G$6,$E$6*Z24,$F$6*Z24)),IF(Z$1<$G$6,$E$6*Z24,$F$6*Z24))) -> 0 | ... AD27: =IF($E$9="WA",IF(AD$1<$G$6,$E$6*$N22*2*AD$7+$CA$5*AD24,$F$6*$N22*2*AD$7+$CA$5*AD24),IF($E$9="NV",IF(AC25>36000,0,IF(AD$1<$G$6,$E$6*AD24,$F$6*AD24)),IF(AD$1<$G$6,$E$6*AD24,$F$6*AD24))) -> 0
A28: =A27 -> Uncheck to Hide | C28: 401K Match | S28: =IF(S22=0,0,$H$11/26*S$7*IF(OR($G22=0,$G22=1),1,$G22)) -> 0 | T28: =IF(T22=0,0,$H$11/26*T$7*IF(OR($G22=0,$G22=1),1,$G22)) -> 0 | U28: =IF(U22=0,0,$H$11/26*U$7*IF(OR($G22=0,$G22=1),1,$G22)) -> 0 | V28: =IF(V22=0,0,$H$11/26*V$7*IF(OR($G22=0,$G22=1),1,$G22)) -> 0 | W28: =IF(W22=0,0,$H$11/26*W$7*IF(OR($G22=0,$G22=1),1,$G22)) -> 0 | X28: =IF(X22=0,0,$H$11/26*X$7*IF(OR($G22=0,$G22=1),1,$G22)) -> 0 | Y28: =IF(Y22=0,0,$H$11/26*Y$7*IF(OR($G22=0,$G22=1),1,$G22)) -> 0 | Z28: =IF(Z22=0,0,$H$11/26*Z$7*IF(OR($G22=0,$G22=1),1,$G22)) -> 0 | ... AD28: =IF(AD22=0,0,$H$11/26*AD$7*IF(OR($G22=0,$G22=1),1,$G22)) -> 0
A29: =A27 -> Uncheck to Hide | C29: =IF($E$9="CA","",$C$269) -> HEALTH INS. & EMPL. BENEFITS | S29: =IF(OR($E$9="CA",$E$9="CO",$E$9="OR",$E$9="WA"),0,IF($G22=0,0,$G22*$E$7*S$8/2+S24*$CC$6)) -> 0 | T29: =IF(OR($E$9="CA",$E$9="CO",$E$9="OR",$E$9="WA"),0,IF($G22=0,0,$G22*$E$7*T$8/2+T24*$CC$6)) -> 0 | U29: =IF(OR($E$9="CA",$E$9="CO",$E$9="OR",$E$9="WA"),0,IF($G22=0,0,$G22*$E$7*U$8/2+U24*$CC$6)) -> 0 | V29: =IF(OR($E$9="CA",$E$9="CO",$E$9="OR",$E$9="WA"),0,IF($G22=0,0,$G22*$E$7*V$8/2+V24*$CC$6)) -> 0 | W29: =IF(OR($E$9="CA",$E$9="CO",$E$9="OR",$E$9="WA"),0,IF($G22=0,0,$G22*$E$7*W$8/2+W24*$CC$6)) -> 0 | X29: =IF(OR($E$9="CA",$E$9="CO",$E$9="OR",$E$9="WA"),0,IF($G22=0,0,$G22*$E$7*X$8/2+X24*$CC$6)) -> 0 | Y29: =IF(OR($E$9="CA",$E$9="CO",$E$9="OR",$E$9="WA"),0,IF($G22=0,0,$G22*$E$7*Y$8/2+Y24*$CC$6)) -> 0 | Z29: =IF(OR($E$9="CA",$E$9="CO",$E$9="OR",$E$9="WA"),0,IF($G22=0,0,$G22*$E$7*Z$8/2+Z24*$CC$6)) -> 0 | ... AD29: =IF(OR($E$9="CA",$E$9="CO",$E$9="OR",$E$9="WA"),0,IF($G22=0,0,$G22*$E$7*AD$8/2+AD24*$CC$6)) -> 0
A30: =IF(F30+G30+H30+M30=0,"Uncheck to Hide","") | B30: 6330-100 ASST MANAGER SALARY | C30: Asst Community Director 1 | D30: Michelle Daub | F30: 1 | G30: 1 | I30: 25 | J30: 45490 | K30: 31.25 | L30: 0.03 | M30: =ROUND(K30*(1+L30),2) -> 32.19 | N30: 40 | P30: =IF(SUM(S31:AD31)>0,1,0) -> 0 | Q30: =M30*N30*52 -> 66955.2 | S30: =IF(S31="",$M30*$N30*2*S$7+$P32*S$7+$O30*$M30*1.5*2*S$7+IF($O$10="Y",(SUMIF($CS$3:$DT$3,S$1,$CS$8:$DT$8)-SUMIF($CS$3:$DT$3,R$1,$CS$8:$DT$8))*($M30*$N30*2*S$7+$P32*S$7+$O30*$M30*1.5*2*S$7)/(S$7*14),0)+IF($O$11="Y",(SUMIF($CS$3:$DT$3,S$1,$CS$8:$DT$8)*CU$11-SUMIF($CS$3:$DT$3,R$1,$CS$8:$DT$8)*CT$11)*($M30*$N30*2*S$7+$P32*S$7+$O30*$M30*1.5*2*S$7)/(S$7*14),0),S31) -> 5150.4 | T30: =IF(T31="",$M30*$N30*2*T$7+$P32*T$7+$O30*$M30*1.5*2*T$7+IF($O$10="Y",(SUMIF($CS$3:$DT$3,T$1,$CS$8:$DT$8)-SUMIF($CS$3:$DT$3,S$1,$CS$8:$DT$8))*($M30*$N30*2*T$7+$P32*T$7+$O30*$M30*1.5*2*T$7)/(T$7*14),0)+IF($O$11="Y",(SUMIF($CS$3:$DT$3,T$1,$CS$8:$DT$8)*CV$11-SUMIF($CS$3:$DT$3,S$1,$CS$8:$DT$8)*CU$11)*($M30*$N30*2*T$7+$P32*T$7+$O30*$M30*1.5*2*T$7)/(T$7*14),0),T31) -> 5150.4 | U30: =IF(U31="",$M30*$N30*2*U$7+$P32*U$7+$O30*$M30*1.5*2*U$7+IF($O$10="Y",(SUMIF($CS$3:$DT$3,U$1,$CS$8:$DT$8)-SUMIF($CS$3:$DT$3,T$1,$CS$8:$DT$8))*($M30*$N30*2*U$7+$P32*U$7+$O30*$M30*1.5*2*U$7)/(U$7*14),0)+IF($O$11="Y",(SUMIF($CS$3:$DT$3,U$1,$CS$8:$DT$8)*CW$11-SUMIF($CS$3:$DT$3,T$1,$CS$8:$DT$8)*CV$11)*($M30*$N30*2*U$7+$P32*U$7+$O30*$M30*1.5*2*U$7)/(U$7*14),0),U31) -> 5150.4 | V30: =IF(V31="",$M30*$N30*2*V$7+$P32*V$7+$O30*$M30*1.5*2*V$7+IF($O$10="Y",(SUMIF($CS$3:$DT$3,V$1,$CS$8:$DT$8)-SUMIF($CS$3:$DT$3,U$1,$CS$8:$DT$8))*($M30*$N30*2*V$7+$P32*V$7+$O30*$M30*1.5*2*V$7)/(V$7*14),0)+IF($O$11="Y",(SUMIF($CS$3:$DT$3,V$1,$CS$8:$DT$8)*CX$11-SUMIF($CS$3:$DT$3,U$1,$CS$8:$DT$8)*CW$11)*($M30*$N30*2*V$7+$P32*V$7+$O30*$M30*1.5*2*V$7)/(V$7*14),0),V31) -> 5150.4 | W30: =IF(W31="",$M30*$N30*2*W$7+$P32*W$7+$O30*$M30*1.5*2*W$7+IF($O$10="Y",(SUMIF($CS$3:$DT$3,W$1,$CS$8:$DT$8)-SUMIF($CS$3:$DT$3,V$1,$CS$8:$DT$8))*($M30*$N30*2*W$7+$P32*W$7+$O30*$M30*1.5*2*W$7)/(W$7*14),0)+IF($O$11="Y",(SUMIF($CS$3:$DT$3,W$1,$CS$8:$DT$8)*CY$11-SUMIF($CS$3:$DT$3,V$1,$CS$8:$DT$8)*CX$11)*($M30*$N30*2*W$7+$P32*W$7+$O30*$M30*1.5*2*W$7)/(W$7*14),0),W31) -> 5150.4 | X30: =IF(X31="",$M30*$N30*2*X$7+$P32*X$7+$O30*$M30*1.5*2*X$7+IF($O$10="Y",(SUMIF($CS$3:$DT$3,X$1,$CS$8:$DT$8)-SUMIF($CS$3:$DT$3,W$1,$CS$8:$DT$8))*($M30*$N30*2*X$7+$P32*X$7+$O30*$M30*1.5*2*X$7)/(X$7*14),0)+IF($O$11="Y",(SUMIF($CS$3:$DT$3,X$1,$CS$8:$DT$8)*CZ$11-SUMIF($CS$3:$DT$3,W$1,$CS$8:$DT$8)*CY$11)*($M30*$N30*2*X$7+$P32*X$7+$O30*$M30*1.5*2*X$7)/(X$7*14),0),X31) -> 5150.4 | Y30: =IF(Y31="",$M30*$N30*2*Y$7+$P32*Y$7+$O30*$M30*1.5*2*Y$7+IF($O$10="Y",(SUMIF($CS$3:$DT$3,Y$1,$CS$8:$DT$8)-SUMIF($CS$3:$DT$3,X$1,$CS$8:$DT$8))*($M30*$N30*2*Y$7+$P32*Y$7+$O30*$M30*1.5*2*Y$7)/(Y$7*14),0)+IF($O$11="Y",(SUMIF($CS$3:$DT$3,Y$1,$CS$8:$DT$8)*DA$11-SUMIF($CS$3:$DT$3,X$1,$CS$8:$DT$8)*CZ$11)*($M30*$N30*2*Y$7+$P32*Y$7+$O30*$M30*1.5*2*Y$7)/(Y$7*14),0),Y31) -> 7725.6 | Z30: =IF(Z31="",$M30*$N30*2*Z$7+$P32*Z$7+$O30*$M30*1.5*2*Z$7+IF($O$10="Y",(SUMIF($CS$3:$DT$3,Z$1,$CS$8:$DT$8)-SUMIF($CS$3:$DT$3,Y$1,$CS$8:$DT$8))*($M30*$N30*2*Z$7+$P32*Z$7+$O30*$M30*1.5*2*Z$7)/(Z$7*14),0)+IF($O$11="Y",(SUMIF($CS$3:$DT$3,Z$1,$CS$8:$DT$8)*DB$11-SUMIF($CS$3:$DT$3,Y$1,$CS$8:$DT$8)*DA$11)*($M30*$N30*2*Z$7+$P32*Z$7+$O30*$M30*1.5*2*Z$7)/(Z$7*14),0),Z31) -> 5150.4 | ... AD30: =IF(AD31="",$M30*$N30*2*AD$7+$P32*AD$7+$O30*$M30*1.5*2*AD$7+IF($O$10="Y",(SUMIF($CS$3:$DT$3,AD$1,$CS$8:$DT$8)-SUMIF($CS$3:$DT$3,AC$1,$CS$8:$DT$8))*($M30*$N30*2*AD$7+$P32*AD$7+$O30*$M30*1.5*2*AD$7)/(AD$7*14),0)+IF($O$11="Y",(SUMIF($CS$3:$DT$3,AD$1,$CS$8:$DT$8)*DF$11-SUMIF($CS$3:$DT$3,AC$1,$CS$8:$DT$8)*DE$11)*($M30*$N30*2*AD$7+$P32*AD$7+$O30*$M30*1.5*2*AD$7)/(AD$7*14),0),AD31) -> 7725.6 | AE30: =SUM(S30:AD30) -> 66955.2
A31: =A30
A32: Do not check this box | P32: =+M30*N30*R30/AE$7 -> 0 | S32: =IF(S31>0,S31-$P32*S$7,+S30-$P32*S$7) -> 5150.4 | T32: =IF(T31>0,T31-$P32*T$7,+T30-$P32*T$7) -> 5150.4 | U32: =IF(U31>0,U31-$P32*U$7,+U30-$P32*U$7) -> 5150.4 | V32: =IF(V31>0,V31-$P32*V$7,+V30-$P32*V$7) -> 5150.4 | W32: =IF(W31>0,W31-$P32*W$7,+W30-$P32*W$7) -> 5150.4 | X32: =IF(X31>0,X31-$P32*X$7,+X30-$P32*X$7) -> 5150.4 | Y32: =IF(Y31>0,Y31-$P32*Y$7,+Y30-$P32*Y$7) -> 7725.6 | Z32: =IF(Z31>0,Z31-$P32*Z$7,+Z30-$P32*Z$7) -> 5150.4 | ... AD32: =IF(AD31>0,AD31-$P32*AD$7,+AD30-$P32*AD$7) -> 7725.6
A33: Do not check this box | S33: =+S32 -> 5150.4 | T33: =+T32+S33 -> 10300.8 | U33: =+U32+T33 -> 15451.2 | V33: =+V32+U33 -> 20601.6 | W33: =+W32+V33 -> 25752 | X33: =+X32+W33 -> 30902.4 | Y33: =+Y32+X33 -> 38628 | Z33: =+Z32+Y33 -> 43778.4 | AA33: =+AA32+Z33 -> 48928.8 | ... AD33: =+AD32+AC33 -> 66955.2
A34: =A31 | C34: Payroll Tax | S34: =IF($E$9="CA",IF(R33<7000,$E$5*S32,($E$5-0.043)*S32),IF($E$9="IL",IF(R33<12960,$E$5*S32,($E$5-0.04125)*S32),IF($E$9="PA",IF(R33<10000,$E$5*S32,($E$5-0.071)*S32),IF($E$9="TX",IF(R33<9000,$E$5*S32,($E$5-0.0363)*S32),$E$5*S32)))) -> 580.52219 | T34: =IF($E$9="CA",IF(S33<7000,$E$5*T32,($E$5-0.043)*T32),IF($E$9="IL",IF(S33<12960,$E$5*T32,($E$5-0.04125)*T32),IF($E$9="PA",IF(S33<10000,$E$5*T32,($E$5-0.071)*T32),IF($E$9="TX",IF(S33<9000,$E$5*T32,($E$5-0.0363)*T32),$E$5*T32)))) -> 580.52219 | U34: =IF($E$9="CA",IF(T33<7000,$E$5*U32,($E$5-0.043)*U32),IF($E$9="IL",IF(T33<12960,$E$5*U32,($E$5-0.04125)*U32),IF($E$9="PA",IF(T33<10000,$E$5*U32,($E$5-0.071)*U32),IF($E$9="TX",IF(T33<9000,$E$5*U32,($E$5-0.0363)*U32),$E$5*U32)))) -> 580.52219 | V34: =IF($E$9="CA",IF(U33<7000,$E$5*V32,($E$5-0.043)*V32),IF($E$9="IL",IF(U33<12960,$E$5*V32,($E$5-0.04125)*V32),IF($E$9="PA",IF(U33<10000,$E$5*V32,($E$5-0.071)*V32),IF($E$9="TX",IF(U33<9000,$E$5*V32,($E$5-0.0363)*V32),$E$5*V32)))) -> 580.52219 | W34: =IF($E$9="CA",IF(V33<7000,$E$5*W32,($E$5-0.043)*W32),IF($E$9="IL",IF(V33<12960,$E$5*W32,($E$5-0.04125)*W32),IF($E$9="PA",IF(V33<10000,$E$5*W32,($E$5-0.071)*W32),IF($E$9="TX",IF(V33<9000,$E$5*W32,($E$5-0.0363)*W32),$E$5*W32)))) -> 580.52219 | X34: =IF($E$9="CA",IF(W33<7000,$E$5*X32,($E$5-0.043)*X32),IF($E$9="IL",IF(W33<12960,$E$5*X32,($E$5-0.04125)*X32),IF($E$9="PA",IF(W33<10000,$E$5*X32,($E$5-0.071)*X32),IF($E$9="TX",IF(W33<9000,$E$5*X32,($E$5-0.0363)*X32),$E$5*X32)))) -> 580.52219 | Y34: =IF($E$9="CA",IF(X33<7000,$E$5*Y32,($E$5-0.043)*Y32),IF($E$9="IL",IF(X33<12960,$E$5*Y32,($E$5-0.04125)*Y32),IF($E$9="PA",IF(X33<10000,$E$5*Y32,($E$5-0.071)*Y32),IF($E$9="TX",IF(X33<9000,$E$5*Y32,($E$5-0.0363)*Y32),$E$5*Y32)))) -> 870.78328 | Z34: =IF($E$9="CA",IF(Y33<7000,$E$5*Z32,($E$5-0.043)*Z32),IF($E$9="IL",IF(Y33<12960,$E$5*Z32,($E$5-0.04125)*Z32),IF($E$9="PA",IF(Y33<10000,$E$5*Z32,($E$5-0.071)*Z32),IF($E$9="TX",IF(Y33<9000,$E$5*Z32,($E$5-0.0363)*Z32),$E$5*Z32)))) -> 580.52219 | ... AD34: =IF($E$9="CA",IF(AC33<7000,$E$5*AD32,($E$5-0.043)*AD32),IF($E$9="IL",IF(AC33<12960,$E$5*AD32,($E$5-0.04125)*AD32),IF($E$9="PA",IF(AC33<10000,$E$5*AD32,($E$5-0.071)*AD32),IF($E$9="TX",IF(AC33<9000,$E$5*AD32,($E$5-0.0363)*AD32),$E$5*AD32)))) -> 870.78328
A35: =A34 | C35: Workman's Comp | S35: =IF($E$9="WA",IF(S$1<$G$6,$E$6*$N30*2*S$7+$CA$5*S32,$F$6*$N30*2*S$7+$CA$5*S32),IF($E$9="NV",IF(R33>36000,0,IF(S$1<$G$6,$E$6*S32,$F$6*S32)),IF(S$1<$G$6,$E$6*S32,$F$6*S32))) -> 231.984 | T35: =IF($E$9="WA",IF(T$1<$G$6,$E$6*$N30*2*T$7+$CA$5*T32,$F$6*$N30*2*T$7+$CA$5*T32),IF($E$9="NV",IF(S33>36000,0,IF(T$1<$G$6,$E$6*T32,$F$6*T32)),IF(T$1<$G$6,$E$6*T32,$F$6*T32))) -> 231.984 | U35: =IF($E$9="WA",IF(U$1<$G$6,$E$6*$N30*2*U$7+$CA$5*U32,$F$6*$N30*2*U$7+$CA$5*U32),IF($E$9="NV",IF(T33>36000,0,IF(U$1<$G$6,$E$6*U32,$F$6*U32)),IF(U$1<$G$6,$E$6*U32,$F$6*U32))) -> 231.984 | V35: =IF($E$9="WA",IF(V$1<$G$6,$E$6*$N30*2*V$7+$CA$5*V32,$F$6*$N30*2*V$7+$CA$5*V32),IF($E$9="NV",IF(U33>36000,0,IF(V$1<$G$6,$E$6*V32,$F$6*V32)),IF(V$1<$G$6,$E$6*V32,$F$6*V32))) -> 231.984 | W35: =IF($E$9="WA",IF(W$1<$G$6,$E$6*$N30*2*W$7+$CA$5*W32,$F$6*$N30*2*W$7+$CA$5*W32),IF($E$9="NV",IF(V33>36000,0,IF(W$1<$G$6,$E$6*W32,$F$6*W32)),IF(W$1<$G$6,$E$6*W32,$F$6*W32))) -> 231.984 | X35: =IF($E$9="WA",IF(X$1<$G$6,$E$6*$N30*2*X$7+$CA$5*X32,$F$6*$N30*2*X$7+$CA$5*X32),IF($E$9="NV",IF(W33>36000,0,IF(X$1<$G$6,$E$6*X32,$F$6*X32)),IF(X$1<$G$6,$E$6*X32,$F$6*X32))) -> 231.984 | Y35: =IF($E$9="WA",IF(Y$1<$G$6,$E$6*$N30*2*Y$7+$CA$5*Y32,$F$6*$N30*2*Y$7+$CA$5*Y32),IF($E$9="NV",IF(X33>36000,0,IF(Y$1<$G$6,$E$6*Y32,$F$6*Y32)),IF(Y$1<$G$6,$E$6*Y32,$F$6*Y32))) -> 347.976 | Z35: =IF($E$9="WA",IF(Z$1<$G$6,$E$6*$N30*2*Z$7+$CA$5*Z32,$F$6*$N30*2*Z$7+$CA$5*Z32),IF($E$9="NV",IF(Y33>36000,0,IF(Z$1<$G$6,$E$6*Z32,$F$6*Z32)),IF(Z$1<$G$6,$E$6*Z32,$F$6*Z32))) -> 231.984 | ... AD35: =IF($E$9="WA",IF(AD$1<$G$6,$E$6*$N30*2*AD$7+$CA$5*AD32,$F$6*$N30*2*AD$7+$CA$5*AD32),IF($E$9="NV",IF(AC33>36000,0,IF(AD$1<$G$6,$E$6*AD32,$F$6*AD32)),IF(AD$1<$G$6,$E$6*AD32,$F$6*AD32))) -> 347.976
A36: =A35 | C36: 401K Match | S36: =IF(S30=0,0,$H$11/26*S$7*IF(OR($G30=0,$G30=1),1,$G30)) -> 76.923077 | T36: =IF(T30=0,0,$H$11/26*T$7*IF(OR($G30=0,$G30=1),1,$G30)) -> 76.923077 | U36: =IF(U30=0,0,$H$11/26*U$7*IF(OR($G30=0,$G30=1),1,$G30)) -> 76.923077 | V36: =IF(V30=0,0,$H$11/26*V$7*IF(OR($G30=0,$G30=1),1,$G30)) -> 76.923077 | W36: =IF(W30=0,0,$H$11/26*W$7*IF(OR($G30=0,$G30=1),1,$G30)) -> 76.923077 | X36: =IF(X30=0,0,$H$11/26*X$7*IF(OR($G30=0,$G30=1),1,$G30)) -> 76.923077 | Y36: =IF(Y30=0,0,$H$11/26*Y$7*IF(OR($G30=0,$G30=1),1,$G30)) -> 115.38462 | Z36: =IF(Z30=0,0,$H$11/26*Z$7*IF(OR($G30=0,$G30=1),1,$G30)) -> 76.923077 | ... AD36: =IF(AD30=0,0,$H$11/26*AD$7*IF(OR($G30=0,$G30=1),1,$G30)) -> 115.38462
A37: =A35 | C37: =IF($E$9="CA","",$C$269) -> HEALTH INS. & EMPL. BENEFITS | S37: =IF(OR($E$9="CA",$E$9="CO",$E$9="OR",$E$9="WA"),0,IF($G30=0,0,$G30*$E$7*S$8/2+S32*$CC$6)) -> 0 | T37: =IF(OR($E$9="CA",$E$9="CO",$E$9="OR",$E$9="WA"),0,IF($G30=0,0,$G30*$E$7*T$8/2+T32*$CC$6)) -> 0 | U37: =IF(OR($E$9="CA",$E$9="CO",$E$9="OR",$E$9="WA"),0,IF($G30=0,0,$G30*$E$7*U$8/2+U32*$CC$6)) -> 0 | V37: =IF(OR($E$9="CA",$E$9="CO",$E$9="OR",$E$9="WA"),0,IF($G30=0,0,$G30*$E$7*V$8/2+V32*$CC$6)) -> 0 | W37: =IF(OR($E$9="CA",$E$9="CO",$E$9="OR",$E$9="WA"),0,IF($G30=0,0,$G30*$E$7*W$8/2+W32*$CC$6)) -> 0 | X37: =IF(OR($E$9="CA",$E$9="CO",$E$9="OR",$E$9="WA"),0,IF($G30=0,0,$G30*$E$7*X$8/2+X32*$CC$6)) -> 0 | Y37: =IF(OR($E$9="CA",$E$9="CO",$E$9="OR",$E$9="WA"),0,IF($G30=0,0,$G30*$E$7*Y$8/2+Y32*$CC$6)) -> 0 | Z37: =IF(OR($E$9="CA",$E$9="CO",$E$9="OR",$E$9="WA"),0,IF($G30=0,0,$G30*$E$7*Z$8/2+Z32*$CC$6)) -> 0 | ... AD37: =IF(OR($E$9="CA",$E$9="CO",$E$9="OR",$E$9="WA"),0,IF($G30=0,0,$G30*$E$7*AD$8/2+AD32*$CC$6)) -> 0
A38: =IF(F38+G38+H38+M38=0,"Uncheck to Hide","") -> Uncheck to Hide | B38: =B30 -> 6330-100 ASST MANAGER SALARY | C38: Asst Community Director 2 | I38: 25 | M38: =ROUND(K38*(1+L38),2) -> 0 | P38: =IF(SUM(S39:AD39)>0,1,0) -> 0 | Q38: =M38*N38*52 -> 0 | S38: =IF(S39="",$M38*$N38*2*S$7+$P40*S$7+$O38*$M38*1.5*2*S$7+IF($O$10="Y",(SUMIF($CS$3:$DT$3,S$1,$CS$8:$DT$8)-SUMIF($CS$3:$DT$3,R$1,$CS$8:$DT$8))*($M38*$N38*2*S$7+$P40*S$7+$O38*$M38*1.5*2*S$7)/(S$7*14),0)+IF($O$11="Y",(SUMIF($CS$3:$DT$3,S$1,$CS$8:$DT$8)*CU$11-SUMIF($CS$3:$DT$3,R$1,$CS$8:$DT$8)*CT$11)*($M38*$N38*2*S$7+$P40*S$7+$O38*$M38*1.5*2*S$7)/(S$7*14),0),S39) -> 0 | T38: =IF(T39="",$M38*$N38*2*T$7+$P40*T$7+$O38*$M38*1.5*2*T$7+IF($O$10="Y",(SUMIF($CS$3:$DT$3,T$1,$CS$8:$DT$8)-SUMIF($CS$3:$DT$3,S$1,$CS$8:$DT$8))*($M38*$N38*2*T$7+$P40*T$7+$O38*$M38*1.5*2*T$7)/(T$7*14),0)+IF($O$11="Y",(SUMIF($CS$3:$DT$3,T$1,$CS$8:$DT$8)*CV$11-SUMIF($CS$3:$DT$3,S$1,$CS$8:$DT$8)*CU$11)*($M38*$N38*2*T$7+$P40*T$7+$O38*$M38*1.5*2*T$7)/(T$7*14),0),T39) -> 0 | U38: =IF(U39="",$M38*$N38*2*U$7+$P40*U$7+$O38*$M38*1.5*2*U$7+IF($O$10="Y",(SUMIF($CS$3:$DT$3,U$1,$CS$8:$DT$8)-SUMIF($CS$3:$DT$3,T$1,$CS$8:$DT$8))*($M38*$N38*2*U$7+$P40*U$7+$O38*$M38*1.5*2*U$7)/(U$7*14),0)+IF($O$11="Y",(SUMIF($CS$3:$DT$3,U$1,$CS$8:$DT$8)*CW$11-SUMIF($CS$3:$DT$3,T$1,$CS$8:$DT$8)*CV$11)*($M38*$N38*2*U$7+$P40*U$7+$O38*$M38*1.5*2*U$7)/(U$7*14),0),U39) -> 0 | V38: =IF(V39="",$M38*$N38*2*V$7+$P40*V$7+$O38*$M38*1.5*2*V$7+IF($O$10="Y",(SUMIF($CS$3:$DT$3,V$1,$CS$8:$DT$8)-SUMIF($CS$3:$DT$3,U$1,$CS$8:$DT$8))*($M38*$N38*2*V$7+$P40*V$7+$O38*$M38*1.5*2*V$7)/(V$7*14),0)+IF($O$11="Y",(SUMIF($CS$3:$DT$3,V$1,$CS$8:$DT$8)*CX$11-SUMIF($CS$3:$DT$3,U$1,$CS$8:$DT$8)*CW$11)*($M38*$N38*2*V$7+$P40*V$7+$O38*$M38*1.5*2*V$7)/(V$7*14),0),V39) -> 0 | W38: =IF(W39="",$M38*$N38*2*W$7+$P40*W$7+$O38*$M38*1.5*2*W$7+IF($O$10="Y",(SUMIF($CS$3:$DT$3,W$1,$CS$8:$DT$8)-SUMIF($CS$3:$DT$3,V$1,$CS$8:$DT$8))*($M38*$N38*2*W$7+$P40*W$7+$O38*$M38*1.5*2*W$7)/(W$7*14),0)+IF($O$11="Y",(SUMIF($CS$3:$DT$3,W$1,$CS$8:$DT$8)*CY$11-SUMIF($CS$3:$DT$3,V$1,$CS$8:$DT$8)*CX$11)*($M38*$N38*2*W$7+$P40*W$7+$O38*$M38*1.5*2*W$7)/(W$7*14),0),W39) -> 0 | X38: =IF(X39="",$M38*$N38*2*X$7+$P40*X$7+$O38*$M38*1.5*2*X$7+IF($O$10="Y",(SUMIF($CS$3:$DT$3,X$1,$CS$8:$DT$8)-SUMIF($CS$3:$DT$3,W$1,$CS$8:$DT$8))*($M38*$N38*2*X$7+$P40*X$7+$O38*$M38*1.5*2*X$7)/(X$7*14),0)+IF($O$11="Y",(SUMIF($CS$3:$DT$3,X$1,$CS$8:$DT$8)*CZ$11-SUMIF($CS$3:$DT$3,W$1,$CS$8:$DT$8)*CY$11)*($M38*$N38*2*X$7+$P40*X$7+$O38*$M38*1.5*2*X$7)/(X$7*14),0),X39) -> 0 | Y38: =IF(Y39="",$M38*$N38*2*Y$7+$P40*Y$7+$O38*$M38*1.5*2*Y$7+IF($O$10="Y",(SUMIF($CS$3:$DT$3,Y$1,$CS$8:$DT$8)-SUMIF($CS$3:$DT$3,X$1,$CS$8:$DT$8))*($M38*$N38*2*Y$7+$P40*Y$7+$O38*$M38*1.5*2*Y$7)/(Y$7*14),0)+IF($O$11="Y",(SUMIF($CS$3:$DT$3,Y$1,$CS$8:$DT$8)*DA$11-SUMIF($CS$3:$DT$3,X$1,$CS$8:$DT$8)*CZ$11)*($M38*$N38*2*Y$7+$P40*Y$7+$O38*$M38*1.5*2*Y$7)/(Y$7*14),0),Y39) -> 0 | Z38: =IF(Z39="",$M38*$N38*2*Z$7+$P40*Z$7+$O38*$M38*1.5*2*Z$7+IF($O$10="Y",(SUMIF($CS$3:$DT$3,Z$1,$CS$8:$DT$8)-SUMIF($CS$3:$DT$3,Y$1,$CS$8:$DT$8))*($M38*$N38*2*Z$7+$P40*Z$7+$O38*$M38*1.5*2*Z$7)/(Z$7*14),0)+IF($O$11="Y",(SUMIF($CS$3:$DT$3,Z$1,$CS$8:$DT$8)*DB$11-SUMIF($CS$3:$DT$3,Y$1,$CS$8:$DT$8)*DA$11)*($M38*$N38*2*Z$7+$P40*Z$7+$O38*$M38*1.5*2*Z$7)/(Z$7*14),0),Z39) -> 0 | ... AD38: =IF(AD39="",$M38*$N38*2*AD$7+$P40*AD$7+$O38*$M38*1.5*2*AD$7+IF($O$10="Y",(SUMIF($CS$3:$DT$3,AD$1,$CS$8:$DT$8)-SUMIF($CS$3:$DT$3,AC$1,$CS$8:$DT$8))*($M38*$N38*2*AD$7+$P40*AD$7+$O38*$M38*1.5*2*AD$7)/(AD$7*14),0)+IF($O$11="Y",(SUMIF($CS$3:$DT$3,AD$1,$CS$8:$DT$8)*DF$11-SUMIF($CS$3:$DT$3,AC$1,$CS$8:$DT$8)*DE$11)*($M38*$N38*2*AD$7+$P40*AD$7+$O38*$M38*1.5*2*AD$7)/(AD$7*14),0),AD39) -> 0 | AE38: =SUM(S38:AD38) -> 0
A39: =A38 -> Uncheck to Hide
A40: Do not check this box | P40: =+M38*N38*R38/AE$7 -> 0 | S40: =IF(S39>0,S39-$P40*S$7,+S38-$P40*S$7) -> 0 | T40: =IF(T39>0,T39-$P40*T$7,+T38-$P40*T$7) -> 0 | U40: =IF(U39>0,U39-$P40*U$7,+U38-$P40*U$7) -> 0 | V40: =IF(V39>0,V39-$P40*V$7,+V38-$P40*V$7) -> 0 | W40: =IF(W39>0,W39-$P40*W$7,+W38-$P40*W$7) -> 0 | X40: =IF(X39>0,X39-$P40*X$7,+X38-$P40*X$7) -> 0 | Y40: =IF(Y39>0,Y39-$P40*Y$7,+Y38-$P40*Y$7) -> 0 | Z40: =IF(Z39>0,Z39-$P40*Z$7,+Z38-$P40*Z$7) -> 0 | ... AD40: =IF(AD39>0,AD39-$P40*AD$7,+AD38-$P40*AD$7) -> 0
A41: Do not check this box | S41: =+S40 -> 0 | T41: =+T40+S41 -> 0 | U41: =+U40+T41 -> 0 | V41: =+V40+U41 -> 0 | W41: =+W40+V41 -> 0 | X41: =+X40+W41 -> 0 | Y41: =+Y40+X41 -> 0 | Z41: =+Z40+Y41 -> 0 | AA41: =+AA40+Z41 -> 0 | ... AD41: =+AD40+AC41 -> 0
A42: =A39 -> Uncheck to Hide | C42: Payroll Tax | S42: =IF($E$9="CA",IF(R41<7000,$E$5*S40,($E$5-0.043)*S40),IF($E$9="IL",IF(R41<12960,$E$5*S40,($E$5-0.04125)*S40),IF($E$9="PA",IF(R41<10000,$E$5*S40,($E$5-0.071)*S40),IF($E$9="TX",IF(R41<9000,$E$5*S40,($E$5-0.0363)*S40),$E$5*S40)))) -> 0 | T42: =IF($E$9="CA",IF(S41<7000,$E$5*T40,($E$5-0.043)*T40),IF($E$9="IL",IF(S41<12960,$E$5*T40,($E$5-0.04125)*T40),IF($E$9="PA",IF(S41<10000,$E$5*T40,($E$5-0.071)*T40),IF($E$9="TX",IF(S41<9000,$E$5*T40,($E$5-0.0363)*T40),$E$5*T40)))) -> 0 | U42: =IF($E$9="CA",IF(T41<7000,$E$5*U40,($E$5-0.043)*U40),IF($E$9="IL",IF(T41<12960,$E$5*U40,($E$5-0.04125)*U40),IF($E$9="PA",IF(T41<10000,$E$5*U40,($E$5-0.071)*U40),IF($E$9="TX",IF(T41<9000,$E$5*U40,($E$5-0.0363)*U40),$E$5*U40)))) -> 0 | V42: =IF($E$9="CA",IF(U41<7000,$E$5*V40,($E$5-0.043)*V40),IF($E$9="IL",IF(U41<12960,$E$5*V40,($E$5-0.04125)*V40),IF($E$9="PA",IF(U41<10000,$E$5*V40,($E$5-0.071)*V40),IF($E$9="TX",IF(U41<9000,$E$5*V40,($E$5-0.0363)*V40),$E$5*V40)))) -> 0 | W42: =IF($E$9="CA",IF(V41<7000,$E$5*W40,($E$5-0.043)*W40),IF($E$9="IL",IF(V41<12960,$E$5*W40,($E$5-0.04125)*W40),IF($E$9="PA",IF(V41<10000,$E$5*W40,($E$5-0.071)*W40),IF($E$9="TX",IF(V41<9000,$E$5*W40,($E$5-0.0363)*W40),$E$5*W40)))) -> 0 | X42: =IF($E$9="CA",IF(W41<7000,$E$5*X40,($E$5-0.043)*X40),IF($E$9="IL",IF(W41<12960,$E$5*X40,($E$5-0.04125)*X40),IF($E$9="PA",IF(W41<10000,$E$5*X40,($E$5-0.071)*X40),IF($E$9="TX",IF(W41<9000,$E$5*X40,($E$5-0.0363)*X40),$E$5*X40)))) -> 0 | Y42: =IF($E$9="CA",IF(X41<7000,$E$5*Y40,($E$5-0.043)*Y40),IF($E$9="IL",IF(X41<12960,$E$5*Y40,($E$5-0.04125)*Y40),IF($E$9="PA",IF(X41<10000,$E$5*Y40,($E$5-0.071)*Y40),IF($E$9="TX",IF(X41<9000,$E$5*Y40,($E$5-0.0363)*Y40),$E$5*Y40)))) -> 0 | Z42: =IF($E$9="CA",IF(Y41<7000,$E$5*Z40,($E$5-0.043)*Z40),IF($E$9="IL",IF(Y41<12960,$E$5*Z40,($E$5-0.04125)*Z40),IF($E$9="PA",IF(Y41<10000,$E$5*Z40,($E$5-0.071)*Z40),IF($E$9="TX",IF(Y41<9000,$E$5*Z40,($E$5-0.0363)*Z40),$E$5*Z40)))) -> 0 | ... AD42: =IF($E$9="CA",IF(AC41<7000,$E$5*AD40,($E$5-0.043)*AD40),IF($E$9="IL",IF(AC41<12960,$E$5*AD40,($E$5-0.04125)*AD40),IF($E$9="PA",IF(AC41<10000,$E$5*AD40,($E$5-0.071)*AD40),IF($E$9="TX",IF(AC41<9000,$E$5*AD40,($E$5-0.0363)*AD40),$E$5*AD40)))) -> 0
A43: =A42 -> Uncheck to Hide | C43: Workman's Comp | S43: =IF($E$9="WA",IF(S$1<$G$6,$E$6*$N38*2*S$7+$CA$5*S40,$F$6*$N38*2*S$7+$CA$5*S40),IF($E$9="NV",IF(R41>36000,0,IF(S$1<$G$6,$E$6*S40,$F$6*S40)),IF(S$1<$G$6,$E$6*S40,$F$6*S40))) -> 0 | T43: =IF($E$9="WA",IF(T$1<$G$6,$E$6*$N38*2*T$7+$CA$5*T40,$F$6*$N38*2*T$7+$CA$5*T40),IF($E$9="NV",IF(S41>36000,0,IF(T$1<$G$6,$E$6*T40,$F$6*T40)),IF(T$1<$G$6,$E$6*T40,$F$6*T40))) -> 0 | U43: =IF($E$9="WA",IF(U$1<$G$6,$E$6*$N38*2*U$7+$CA$5*U40,$F$6*$N38*2*U$7+$CA$5*U40),IF($E$9="NV",IF(T41>36000,0,IF(U$1<$G$6,$E$6*U40,$F$6*U40)),IF(U$1<$G$6,$E$6*U40,$F$6*U40))) -> 0 | V43: =IF($E$9="WA",IF(V$1<$G$6,$E$6*$N38*2*V$7+$CA$5*V40,$F$6*$N38*2*V$7+$CA$5*V40),IF($E$9="NV",IF(U41>36000,0,IF(V$1<$G$6,$E$6*V40,$F$6*V40)),IF(V$1<$G$6,$E$6*V40,$F$6*V40))) -> 0 | W43: =IF($E$9="WA",IF(W$1<$G$6,$E$6*$N38*2*W$7+$CA$5*W40,$F$6*$N38*2*W$7+$CA$5*W40),IF($E$9="NV",IF(V41>36000,0,IF(W$1<$G$6,$E$6*W40,$F$6*W40)),IF(W$1<$G$6,$E$6*W40,$F$6*W40))) -> 0 | X43: =IF($E$9="WA",IF(X$1<$G$6,$E$6*$N38*2*X$7+$CA$5*X40,$F$6*$N38*2*X$7+$CA$5*X40),IF($E$9="NV",IF(W41>36000,0,IF(X$1<$G$6,$E$6*X40,$F$6*X40)),IF(X$1<$G$6,$E$6*X40,$F$6*X40))) -> 0 | Y43: =IF($E$9="WA",IF(Y$1<$G$6,$E$6*$N38*2*Y$7+$CA$5*Y40,$F$6*$N38*2*Y$7+$CA$5*Y40),IF($E$9="NV",IF(X41>36000,0,IF(Y$1<$G$6,$E$6*Y40,$F$6*Y40)),IF(Y$1<$G$6,$E$6*Y40,$F$6*Y40))) -> 0 | Z43: =IF($E$9="WA",IF(Z$1<$G$6,$E$6*$N38*2*Z$7+$CA$5*Z40,$F$6*$N38*2*Z$7+$CA$5*Z40),IF($E$9="NV",IF(Y41>36000,0,IF(Z$1<$G$6,$E$6*Z40,$F$6*Z40)),IF(Z$1<$G$6,$E$6*Z40,$F$6*Z40))) -> 0 | ... AD43: =IF($E$9="WA",IF(AD$1<$G$6,$E$6*$N38*2*AD$7+$CA$5*AD40,$F$6*$N38*2*AD$7+$CA$5*AD40),IF($E$9="NV",IF(AC41>36000,0,IF(AD$1<$G$6,$E$6*AD40,$F$6*AD40)),IF(AD$1<$G$6,$E$6*AD40,$F$6*AD40))) -> 0
A44: =A43 -> Uncheck to Hide | C44: 401K Match | S44: =IF(S38=0,0,$H$11/26*S$7*IF(OR($G38=0,$G38=1),1,$G38)) -> 0 | T44: =IF(T38=0,0,$H$11/26*T$7*IF(OR($G38=0,$G38=1),1,$G38)) -> 0 | U44: =IF(U38=0,0,$H$11/26*U$7*IF(OR($G38=0,$G38=1),1,$G38)) -> 0 | V44: =IF(V38=0,0,$H$11/26*V$7*IF(OR($G38=0,$G38=1),1,$G38)) -> 0 | W44: =IF(W38=0,0,$H$11/26*W$7*IF(OR($G38=0,$G38=1),1,$G38)) -> 0 | X44: =IF(X38=0,0,$H$11/26*X$7*IF(OR($G38=0,$G38=1),1,$G38)) -> 0 | Y44: =IF(Y38=0,0,$H$11/26*Y$7*IF(OR($G38=0,$G38=1),1,$G38)) -> 0 | Z44: =IF(Z38=0,0,$H$11/26*Z$7*IF(OR($G38=0,$G38=1),1,$G38)) -> 0 | ... AD44: =IF(AD38=0,0,$H$11/26*AD$7*IF(OR($G38=0,$G38=1),1,$G38)) -> 0
A45: =A43 -> Uncheck to Hide | C45: =IF($E$9="CA","",$C$269) -> HEALTH INS. & EMPL. BENEFITS | S45: =IF(OR($E$9="CA",$E$9="CO",$E$9="OR",$E$9="WA"),0,IF($G38=0,0,$G38*$E$7*S$8/2+S40*$CC$6)) -> 0 | T45: =IF(OR($E$9="CA",$E$9="CO",$E$9="OR",$E$9="WA"),0,IF($G38=0,0,$G38*$E$7*T$8/2+T40*$CC$6)) -> 0 | U45: =IF(OR($E$9="CA",$E$9="CO",$E$9="OR",$E$9="WA"),0,IF($G38=0,0,$G38*$E$7*U$8/2+U40*$CC$6)) -> 0 | V45: =IF(OR($E$9="CA",$E$9="CO",$E$9="OR",$E$9="WA"),0,IF($G38=0,0,$G38*$E$7*V$8/2+V40*$CC$6)) -> 0 | W45: =IF(OR($E$9="CA",$E$9="CO",$E$9="OR",$E$9="WA"),0,IF($G38=0,0,$G38*$E$7*W$8/2+W40*$CC$6)) -> 0 | X45: =IF(OR($E$9="CA",$E$9="CO",$E$9="OR",$E$9="WA"),0,IF($G38=0,0,$G38*$E$7*X$8/2+X40*$CC$6)) -> 0 | Y45: =IF(OR($E$9="CA",$E$9="CO",$E$9="OR",$E$9="WA"),0,IF($G38=0,0,$G38*$E$7*Y$8/2+Y40*$CC$6)) -> 0 | Z45: =IF(OR($E$9="CA",$E$9="CO",$E$9="OR",$E$9="WA"),0,IF($G38=0,0,$G38*$E$7*Z$8/2+Z40*$CC$6)) -> 0 | ... AD45: =IF(OR($E$9="CA",$E$9="CO",$E$9="OR",$E$9="WA"),0,IF($G38=0,0,$G38*$E$7*AD$8/2+AD40*$CC$6)) -> 0
A46: =IF(F46+G46+H46+M46=0,"Uncheck to Hide","") | B46: 6330-200 LEASING SALARY | C46: Leasing Consultant 1 | D46: Olivia Montes | F46: 1 | G46: 1 | I46: 15 | J46: 45715 | K46: 24 | M46: =ROUND(K46*(1+L46),2) -> 24 | N46: 40 | P46: =IF(SUM(S47:AD47)>0,1,0) -> 0 | Q46: =M46*N46*52 -> 49920 | S46: =IF(S47="",$M46*$N46*2*S$7+$P48*S$7+$O46*$M46*1.5*2*S$7+IF($O$10="Y",(SUMIF($CS$3:$DT$3,S$1,$CS$8:$DT$8)-SUMIF($CS$3:$DT$3,R$1,$CS$8:$DT$8))*($M46*$N46*2*S$7+$P48*S$7+$O46*$M46*1.5*2*S$7)/(S$7*14),0)+IF($O$11="Y",(SUMIF($CS$3:$DT$3,S$1,$CS$8:$DT$8)*CU$11-SUMIF($CS$3:$DT$3,R$1,$CS$8:$DT$8)*CT$11)*($M46*$N46*2*S$7+$P48*S$7+$O46*$M46*1.5*2*S$7)/(S$7*14),0),S47) -> 3840 | T46: =IF(T47="",$M46*$N46*2*T$7+$P48*T$7+$O46*$M46*1.5*2*T$7+IF($O$10="Y",(SUMIF($CS$3:$DT$3,T$1,$CS$8:$DT$8)-SUMIF($CS$3:$DT$3,S$1,$CS$8:$DT$8))*($M46*$N46*2*T$7+$P48*T$7+$O46*$M46*1.5*2*T$7)/(T$7*14),0)+IF($O$11="Y",(SUMIF($CS$3:$DT$3,T$1,$CS$8:$DT$8)*CV$11-SUMIF($CS$3:$DT$3,S$1,$CS$8:$DT$8)*CU$11)*($M46*$N46*2*T$7+$P48*T$7+$O46*$M46*1.5*2*T$7)/(T$7*14),0),T47) -> 3840 | U46: =IF(U47="",$M46*$N46*2*U$7+$P48*U$7+$O46*$M46*1.5*2*U$7+IF($O$10="Y",(SUMIF($CS$3:$DT$3,U$1,$CS$8:$DT$8)-SUMIF($CS$3:$DT$3,T$1,$CS$8:$DT$8))*($M46*$N46*2*U$7+$P48*U$7+$O46*$M46*1.5*2*U$7)/(U$7*14),0)+IF($O$11="Y",(SUMIF($CS$3:$DT$3,U$1,$CS$8:$DT$8)*CW$11-SUMIF($CS$3:$DT$3,T$1,$CS$8:$DT$8)*CV$11)*($M46*$N46*2*U$7+$P48*U$7+$O46*$M46*1.5*2*U$7)/(U$7*14),0),U47) -> 3840 | V46: =IF(V47="",$M46*$N46*2*V$7+$P48*V$7+$O46*$M46*1.5*2*V$7+IF($O$10="Y",(SUMIF($CS$3:$DT$3,V$1,$CS$8:$DT$8)-SUMIF($CS$3:$DT$3,U$1,$CS$8:$DT$8))*($M46*$N46*2*V$7+$P48*V$7+$O46*$M46*1.5*2*V$7)/(V$7*14),0)+IF($O$11="Y",(SUMIF($CS$3:$DT$3,V$1,$CS$8:$DT$8)*CX$11-SUMIF($CS$3:$DT$3,U$1,$CS$8:$DT$8)*CW$11)*($M46*$N46*2*V$7+$P48*V$7+$O46*$M46*1.5*2*V$7)/(V$7*14),0),V47) -> 3840 | W46: =IF(W47="",$M46*$N46*2*W$7+$P48*W$7+$O46*$M46*1.5*2*W$7+IF($O$10="Y",(SUMIF($CS$3:$DT$3,W$1,$CS$8:$DT$8)-SUMIF($CS$3:$DT$3,V$1,$CS$8:$DT$8))*($M46*$N46*2*W$7+$P48*W$7+$O46*$M46*1.5*2*W$7)/(W$7*14),0)+IF($O$11="Y",(SUMIF($CS$3:$DT$3,W$1,$CS$8:$DT$8)*CY$11-SUMIF($CS$3:$DT$3,V$1,$CS$8:$DT$8)*CX$11)*($M46*$N46*2*W$7+$P48*W$7+$O46*$M46*1.5*2*W$7)/(W$7*14),0),W47) -> 3840 | X46: =IF(X47="",$M46*$N46*2*X$7+$P48*X$7+$O46*$M46*1.5*2*X$7+IF($O$10="Y",(SUMIF($CS$3:$DT$3,X$1,$CS$8:$DT$8)-SUMIF($CS$3:$DT$3,W$1,$CS$8:$DT$8))*($M46*$N46*2*X$7+$P48*X$7+$O46*$M46*1.5*2*X$7)/(X$7*14),0)+IF($O$11="Y",(SUMIF($CS$3:$DT$3,X$1,$CS$8:$DT$8)*CZ$11-SUMIF($CS$3:$DT$3,W$1,$CS$8:$DT$8)*CY$11)*($M46*$N46*2*X$7+$P48*X$7+$O46*$M46*1.5*2*X$7)/(X$7*14),0),X47) -> 3840 | Y46: =IF(Y47="",$M46*$N46*2*Y$7+$P48*Y$7+$O46*$M46*1.5*2*Y$7+IF($O$10="Y",(SUMIF($CS$3:$DT$3,Y$1,$CS$8:$DT$8)-SUMIF($CS$3:$DT$3,X$1,$CS$8:$DT$8))*($M46*$N46*2*Y$7+$P48*Y$7+$O46*$M46*1.5*2*Y$7)/(Y$7*14),0)+IF($O$11="Y",(SUMIF($CS$3:$DT$3,Y$1,$CS$8:$DT$8)*DA$11-SUMIF($CS$3:$DT$3,X$1,$CS$8:$DT$8)*CZ$11)*($M46*$N46*2*Y$7+$P48*Y$7+$O46*$M46*1.5*2*Y$7)/(Y$7*14),0),Y47) -> 5760 | Z46: =IF(Z47="",$M46*$N46*2*Z$7+$P48*Z$7+$O46*$M46*1.5*2*Z$7+IF($O$10="Y",(SUMIF($CS$3:$DT$3,Z$1,$CS$8:$DT$8)-SUMIF($CS$3:$DT$3,Y$1,$CS$8:$DT$8))*($M46*$N46*2*Z$7+$P48*Z$7+$O46*$M46*1.5*2*Z$7)/(Z$7*14),0)+IF($O$11="Y",(SUMIF($CS$3:$DT$3,Z$1,$CS$8:$DT$8)*DB$11-SUMIF($CS$3:$DT$3,Y$1,$CS$8:$DT$8)*DA$11)*($M46*$N46*2*Z$7+$P48*Z$7+$O46*$M46*1.5*2*Z$7)/(Z$7*14),0),Z47) -> 3840 | ... AD46: =IF(AD47="",$M46*$N46*2*AD$7+$P48*AD$7+$O46*$M46*1.5*2*AD$7+IF($O$10="Y",(SUMIF($CS$3:$DT$3,AD$1,$CS$8:$DT$8)-SUMIF($CS$3:$DT$3,AC$1,$CS$8:$DT$8))*($M46*$N46*2*AD$7+$P48*AD$7+$O46*$M46*1.5*2*AD$7)/(AD$7*14),0)+IF($O$11="Y",(SUMIF($CS$3:$DT$3,AD$1,$CS$8:$DT$8)*DF$11-SUMIF($CS$3:$DT$3,AC$1,$CS$8:$DT$8)*DE$11)*($M46*$N46*2*AD$7+$P48*AD$7+$O46*$M46*1.5*2*AD$7)/(AD$7*14),0),AD47) -> 5760 | AE46: =SUM(S46:AD46) -> 49920 | AG46: =SUBTOTAL(9,AG47:AG95) -> 1 | AH46: =Payroll!AG46&" Leasing consultant"&IF(Payroll!AG46>1,"s","")&Payroll!AH47&Payroll!AH55&Payroll!AH63&Payroll!AH71&Payroll!AH79&Payroll!AH87&Payroll!AH95 -> 1 Leasing consultant at $24/hour, working 40 hours per week without housing.
A47: =A46 | AG47: =IF(AE46=0,0,1) -> 1 | AH47: =IF(AG47=0,"",IF($AG$46>1,", 1 at "," at ")&"$"&ROUND(M46,2)&"/hour, working "&N46&" hours per week with"&IF(E46>0," housing","out housing")) -> at $24/hour, working 40 hours per week without housing
A48: Do not check this box | P48: =+M46*N46*R46/AE$7 -> 0 | S48: =IF(S47>0,S47-$P48*S$7,+S46-$P48*S$7) -> 3840 | T48: =IF(T47>0,T47-$P48*T$7,+T46-$P48*T$7) -> 3840 | U48: =IF(U47>0,U47-$P48*U$7,+U46-$P48*U$7) -> 3840 | V48: =IF(V47>0,V47-$P48*V$7,+V46-$P48*V$7) -> 3840 | W48: =IF(W47>0,W47-$P48*W$7,+W46-$P48*W$7) -> 3840 | X48: =IF(X47>0,X47-$P48*X$7,+X46-$P48*X$7) -> 3840 | Y48: =IF(Y47>0,Y47-$P48*Y$7,+Y46-$P48*Y$7) -> 5760 | Z48: =IF(Z47>0,Z47-$P48*Z$7,+Z46-$P48*Z$7) -> 3840 | ... AD48: =IF(AD47>0,AD47-$P48*AD$7,+AD46-$P48*AD$7) -> 5760
A49: Do not check this box | S49: =+S48 -> 3840 | T49: =+T48+S49 -> 7680 | U49: =+U48+T49 -> 11520 | V49: =+V48+U49 -> 15360 | W49: =+W48+V49 -> 19200 | X49: =+X48+W49 -> 23040 | Y49: =+Y48+X49 -> 28800 | Z49: =+Z48+Y49 -> 32640 | AA49: =+AA48+Z49 -> 36480 | ... AD49: =+AD48+AC49 -> 49920
A50: =A47 | C50: Payroll Tax | S50: =IF($E$9="CA",IF(R49<7000,$E$5*S48,($E$5-0.043)*S48),IF($E$9="IL",IF(R49<12960,$E$5*S48,($E$5-0.04125)*S48),IF($E$9="PA",IF(R49<10000,$E$5*S48,($E$5-0.071)*S48),IF($E$9="TX",IF(R49<9000,$E$5*S48,($E$5-0.0363)*S48),$E$5*S48)))) -> 432.82176 | T50: =IF($E$9="CA",IF(S49<7000,$E$5*T48,($E$5-0.043)*T48),IF($E$9="IL",IF(S49<12960,$E$5*T48,($E$5-0.04125)*T48),IF($E$9="PA",IF(S49<10000,$E$5*T48,($E$5-0.071)*T48),IF($E$9="TX",IF(S49<9000,$E$5*T48,($E$5-0.0363)*T48),$E$5*T48)))) -> 432.82176 | U50: =IF($E$9="CA",IF(T49<7000,$E$5*U48,($E$5-0.043)*U48),IF($E$9="IL",IF(T49<12960,$E$5*U48,($E$5-0.04125)*U48),IF($E$9="PA",IF(T49<10000,$E$5*U48,($E$5-0.071)*U48),IF($E$9="TX",IF(T49<9000,$E$5*U48,($E$5-0.0363)*U48),$E$5*U48)))) -> 432.82176 | V50: =IF($E$9="CA",IF(U49<7000,$E$5*V48,($E$5-0.043)*V48),IF($E$9="IL",IF(U49<12960,$E$5*V48,($E$5-0.04125)*V48),IF($E$9="PA",IF(U49<10000,$E$5*V48,($E$5-0.071)*V48),IF($E$9="TX",IF(U49<9000,$E$5*V48,($E$5-0.0363)*V48),$E$5*V48)))) -> 432.82176 | W50: =IF($E$9="CA",IF(V49<7000,$E$5*W48,($E$5-0.043)*W48),IF($E$9="IL",IF(V49<12960,$E$5*W48,($E$5-0.04125)*W48),IF($E$9="PA",IF(V49<10000,$E$5*W48,($E$5-0.071)*W48),IF($E$9="TX",IF(V49<9000,$E$5*W48,($E$5-0.0363)*W48),$E$5*W48)))) -> 432.82176 | X50: =IF($E$9="CA",IF(W49<7000,$E$5*X48,($E$5-0.043)*X48),IF($E$9="IL",IF(W49<12960,$E$5*X48,($E$5-0.04125)*X48),IF($E$9="PA",IF(W49<10000,$E$5*X48,($E$5-0.071)*X48),IF($E$9="TX",IF(W49<9000,$E$5*X48,($E$5-0.0363)*X48),$E$5*X48)))) -> 432.82176 | Y50: =IF($E$9="CA",IF(X49<7000,$E$5*Y48,($E$5-0.043)*Y48),IF($E$9="IL",IF(X49<12960,$E$5*Y48,($E$5-0.04125)*Y48),IF($E$9="PA",IF(X49<10000,$E$5*Y48,($E$5-0.071)*Y48),IF($E$9="TX",IF(X49<9000,$E$5*Y48,($E$5-0.0363)*Y48),$E$5*Y48)))) -> 649.23264 | Z50: =IF($E$9="CA",IF(Y49<7000,$E$5*Z48,($E$5-0.043)*Z48),IF($E$9="IL",IF(Y49<12960,$E$5*Z48,($E$5-0.04125)*Z48),IF($E$9="PA",IF(Y49<10000,$E$5*Z48,($E$5-0.071)*Z48),IF($E$9="TX",IF(Y49<9000,$E$5*Z48,($E$5-0.0363)*Z48),$E$5*Z48)))) -> 432.82176 | ... AD50: =IF($E$9="CA",IF(AC49<7000,$E$5*AD48,($E$5-0.043)*AD48),IF($E$9="IL",IF(AC49<12960,$E$5*AD48,($E$5-0.04125)*AD48),IF($E$9="PA",IF(AC49<10000,$E$5*AD48,($E$5-0.071)*AD48),IF($E$9="TX",IF(AC49<9000,$E$5*AD48,($E$5-0.0363)*AD48),$E$5*AD48)))) -> 649.23264
A51: =A50 | C51: Workman's Comp | S51: =IF($E$9="WA",IF(S$1<$G$6,$E$6*$N46*2*S$7+$CA$5*S48,$F$6*$N46*2*S$7+$CA$5*S48),IF($E$9="NV",IF(R49>36000,0,IF(S$1<$G$6,$E$6*S48,$F$6*S48)),IF(S$1<$G$6,$E$6*S48,$F$6*S48))) -> 231.984 | T51: =IF($E$9="WA",IF(T$1<$G$6,$E$6*$N46*2*T$7+$CA$5*T48,$F$6*$N46*2*T$7+$CA$5*T48),IF($E$9="NV",IF(S49>36000,0,IF(T$1<$G$6,$E$6*T48,$F$6*T48)),IF(T$1<$G$6,$E$6*T48,$F$6*T48))) -> 231.984 | U51: =IF($E$9="WA",IF(U$1<$G$6,$E$6*$N46*2*U$7+$CA$5*U48,$F$6*$N46*2*U$7+$CA$5*U48),IF($E$9="NV",IF(T49>36000,0,IF(U$1<$G$6,$E$6*U48,$F$6*U48)),IF(U$1<$G$6,$E$6*U48,$F$6*U48))) -> 231.984 | V51: =IF($E$9="WA",IF(V$1<$G$6,$E$6*$N46*2*V$7+$CA$5*V48,$F$6*$N46*2*V$7+$CA$5*V48),IF($E$9="NV",IF(U49>36000,0,IF(V$1<$G$6,$E$6*V48,$F$6*V48)),IF(V$1<$G$6,$E$6*V48,$F$6*V48))) -> 231.984 | W51: =IF($E$9="WA",IF(W$1<$G$6,$E$6*$N46*2*W$7+$CA$5*W48,$F$6*$N46*2*W$7+$CA$5*W48),IF($E$9="NV",IF(V49>36000,0,IF(W$1<$G$6,$E$6*W48,$F$6*W48)),IF(W$1<$G$6,$E$6*W48,$F$6*W48))) -> 231.984 | X51: =IF($E$9="WA",IF(X$1<$G$6,$E$6*$N46*2*X$7+$CA$5*X48,$F$6*$N46*2*X$7+$CA$5*X48),IF($E$9="NV",IF(W49>36000,0,IF(X$1<$G$6,$E$6*X48,$F$6*X48)),IF(X$1<$G$6,$E$6*X48,$F$6*X48))) -> 231.984 | Y51: =IF($E$9="WA",IF(Y$1<$G$6,$E$6*$N46*2*Y$7+$CA$5*Y48,$F$6*$N46*2*Y$7+$CA$5*Y48),IF($E$9="NV",IF(X49>36000,0,IF(Y$1<$G$6,$E$6*Y48,$F$6*Y48)),IF(Y$1<$G$6,$E$6*Y48,$F$6*Y48))) -> 347.976 | Z51: =IF($E$9="WA",IF(Z$1<$G$6,$E$6*$N46*2*Z$7+$CA$5*Z48,$F$6*$N46*2*Z$7+$CA$5*Z48),IF($E$9="NV",IF(Y49>36000,0,IF(Z$1<$G$6,$E$6*Z48,$F$6*Z48)),IF(Z$1<$G$6,$E$6*Z48,$F$6*Z48))) -> 231.984 | ... AD51: =IF($E$9="WA",IF(AD$1<$G$6,$E$6*$N46*2*AD$7+$CA$5*AD48,$F$6*$N46*2*AD$7+$CA$5*AD48),IF($E$9="NV",IF(AC49>36000,0,IF(AD$1<$G$6,$E$6*AD48,$F$6*AD48)),IF(AD$1<$G$6,$E$6*AD48,$F$6*AD48))) -> 347.976
A52: =A51 | C52: 401K Match | S52: =IF(S46=0,0,$H$11/26*S$7*IF(OR($G46=0,$G46=1),1,$G46)) -> 76.923077 | T52: =IF(T46=0,0,$H$11/26*T$7*IF(OR($G46=0,$G46=1),1,$G46)) -> 76.923077 | U52: =IF(U46=0,0,$H$11/26*U$7*IF(OR($G46=0,$G46=1),1,$G46)) -> 76.923077 | V52: =IF(V46=0,0,$H$11/26*V$7*IF(OR($G46=0,$G46=1),1,$G46)) -> 76.923077 | W52: =IF(W46=0,0,$H$11/26*W$7*IF(OR($G46=0,$G46=1),1,$G46)) -> 76.923077 | X52: =IF(X46=0,0,$H$11/26*X$7*IF(OR($G46=0,$G46=1),1,$G46)) -> 76.923077 | Y52: =IF(Y46=0,0,$H$11/26*Y$7*IF(OR($G46=0,$G46=1),1,$G46)) -> 115.38462 | Z52: =IF(Z46=0,0,$H$11/26*Z$7*IF(OR($G46=0,$G46=1),1,$G46)) -> 76.923077 | ... AD52: =IF(AD46=0,0,$H$11/26*AD$7*IF(OR($G46=0,$G46=1),1,$G46)) -> 115.38462
A53: =A51 | C53: =IF($E$9="CA","",$C$269) -> HEALTH INS. & EMPL. BENEFITS | S53: =IF(OR($E$9="CA",$E$9="CO",$E$9="OR",$E$9="WA"),0,IF($G46=0,0,$G46*$E$7*S$8/2+S48*$CC$6)) -> 0 | T53: =IF(OR($E$9="CA",$E$9="CO",$E$9="OR",$E$9="WA"),0,IF($G46=0,0,$G46*$E$7*T$8/2+T48*$CC$6)) -> 0 | U53: =IF(OR($E$9="CA",$E$9="CO",$E$9="OR",$E$9="WA"),0,IF($G46=0,0,$G46*$E$7*U$8/2+U48*$CC$6)) -> 0 | V53: =IF(OR($E$9="CA",$E$9="CO",$E$9="OR",$E$9="WA"),0,IF($G46=0,0,$G46*$E$7*V$8/2+V48*$CC$6)) -> 0 | W53: =IF(OR($E$9="CA",$E$9="CO",$E$9="OR",$E$9="WA"),0,IF($G46=0,0,$G46*$E$7*W$8/2+W48*$CC$6)) -> 0 | X53: =IF(OR($E$9="CA",$E$9="CO",$E$9="OR",$E$9="WA"),0,IF($G46=0,0,$G46*$E$7*X$8/2+X48*$CC$6)) -> 0 | Y53: =IF(OR($E$9="CA",$E$9="CO",$E$9="OR",$E$9="WA"),0,IF($G46=0,0,$G46*$E$7*Y$8/2+Y48*$CC$6)) -> 0 | Z53: =IF(OR($E$9="CA",$E$9="CO",$E$9="OR",$E$9="WA"),0,IF($G46=0,0,$G46*$E$7*Z$8/2+Z48*$CC$6)) -> 0 | ... AD53: =IF(OR($E$9="CA",$E$9="CO",$E$9="OR",$E$9="WA"),0,IF($G46=0,0,$G46*$E$7*AD$8/2+AD48*$CC$6)) -> 0
A54: =IF(F54+G54+H54+M54=0,"Uncheck to Hide","") -> Uncheck to Hide | B54: =B46 -> 6330-200 LEASING SALARY | C54: Leasing Consultant 2 | I54: 15 | M54: =ROUND(K54*(1+L54),2) -> 0 | P54: =IF(SUM(S55:AD55)>0,1,0) -> 0 | Q54: =M54*N54*52 -> 0 | S54: =IF(S55="",$M54*$N54*2*S$7+$P56*S$7+$O54*$M54*1.5*2*S$7+IF($O$10="Y",(SUMIF($CS$3:$DT$3,S$1,$CS$8:$DT$8)-SUMIF($CS$3:$DT$3,R$1,$CS$8:$DT$8))*($M54*$N54*2*S$7+$P56*S$7+$O54*$M54*1.5*2*S$7)/(S$7*14),0)+IF($O$11="Y",(SUMIF($CS$3:$DT$3,S$1,$CS$8:$DT$8)*CU$11-SUMIF($CS$3:$DT$3,R$1,$CS$8:$DT$8)*CT$11)*($M54*$N54*2*S$7+$P56*S$7+$O54*$M54*1.5*2*S$7)/(S$7*14),0),S55) -> 0 | T54: =IF(T55="",$M54*$N54*2*T$7+$P56*T$7+$O54*$M54*1.5*2*T$7+IF($O$10="Y",(SUMIF($CS$3:$DT$3,T$1,$CS$8:$DT$8)-SUMIF($CS$3:$DT$3,S$1,$CS$8:$DT$8))*($M54*$N54*2*T$7+$P56*T$7+$O54*$M54*1.5*2*T$7)/(T$7*14),0)+IF($O$11="Y",(SUMIF($CS$3:$DT$3,T$1,$CS$8:$DT$8)*CV$11-SUMIF($CS$3:$DT$3,S$1,$CS$8:$DT$8)*CU$11)*($M54*$N54*2*T$7+$P56*T$7+$O54*$M54*1.5*2*T$7)/(T$7*14),0),T55) -> 0 | U54: =IF(U55="",$M54*$N54*2*U$7+$P56*U$7+$O54*$M54*1.5*2*U$7+IF($O$10="Y",(SUMIF($CS$3:$DT$3,U$1,$CS$8:$DT$8)-SUMIF($CS$3:$DT$3,T$1,$CS$8:$DT$8))*($M54*$N54*2*U$7+$P56*U$7+$O54*$M54*1.5*2*U$7)/(U$7*14),0)+IF($O$11="Y",(SUMIF($CS$3:$DT$3,U$1,$CS$8:$DT$8)*CW$11-SUMIF($CS$3:$DT$3,T$1,$CS$8:$DT$8)*CV$11)*($M54*$N54*2*U$7+$P56*U$7+$O54*$M54*1.5*2*U$7)/(U$7*14),0),U55) -> 0 | V54: =IF(V55="",$M54*$N54*2*V$7+$P56*V$7+$O54*$M54*1.5*2*V$7+IF($O$10="Y",(SUMIF($CS$3:$DT$3,V$1,$CS$8:$DT$8)-SUMIF($CS$3:$DT$3,U$1,$CS$8:$DT$8))*($M54*$N54*2*V$7+$P56*V$7+$O54*$M54*1.5*2*V$7)/(V$7*14),0)+IF($O$11="Y",(SUMIF($CS$3:$DT$3,V$1,$CS$8:$DT$8)*CX$11-SUMIF($CS$3:$DT$3,U$1,$CS$8:$DT$8)*CW$11)*($M54*$N54*2*V$7+$P56*V$7+$O54*$M54*1.5*2*V$7)/(V$7*14),0),V55) -> 0 | W54: =IF(W55="",$M54*$N54*2*W$7+$P56*W$7+$O54*$M54*1.5*2*W$7+IF($O$10="Y",(SUMIF($CS$3:$DT$3,W$1,$CS$8:$DT$8)-SUMIF($CS$3:$DT$3,V$1,$CS$8:$DT$8))*($M54*$N54*2*W$7+$P56*W$7+$O54*$M54*1.5*2*W$7)/(W$7*14),0)+IF($O$11="Y",(SUMIF($CS$3:$DT$3,W$1,$CS$8:$DT$8)*CY$11-SUMIF($CS$3:$DT$3,V$1,$CS$8:$DT$8)*CX$11)*($M54*$N54*2*W$7+$P56*W$7+$O54*$M54*1.5*2*W$7)/(W$7*14),0),W55) -> 0 | X54: =IF(X55="",$M54*$N54*2*X$7+$P56*X$7+$O54*$M54*1.5*2*X$7+IF($O$10="Y",(SUMIF($CS$3:$DT$3,X$1,$CS$8:$DT$8)-SUMIF($CS$3:$DT$3,W$1,$CS$8:$DT$8))*($M54*$N54*2*X$7+$P56*X$7+$O54*$M54*1.5*2*X$7)/(X$7*14),0)+IF($O$11="Y",(SUMIF($CS$3:$DT$3,X$1,$CS$8:$DT$8)*CZ$11-SUMIF($CS$3:$DT$3,W$1,$CS$8:$DT$8)*CY$11)*($M54*$N54*2*X$7+$P56*X$7+$O54*$M54*1.5*2*X$7)/(X$7*14),0),X55) -> 0 | Y54: =IF(Y55="",$M54*$N54*2*Y$7+$P56*Y$7+$O54*$M54*1.5*2*Y$7+IF($O$10="Y",(SUMIF($CS$3:$DT$3,Y$1,$CS$8:$DT$8)-SUMIF($CS$3:$DT$3,X$1,$CS$8:$DT$8))*($M54*$N54*2*Y$7+$P56*Y$7+$O54*$M54*1.5*2*Y$7)/(Y$7*14),0)+IF($O$11="Y",(SUMIF($CS$3:$DT$3,Y$1,$CS$8:$DT$8)*DA$11-SUMIF($CS$3:$DT$3,X$1,$CS$8:$DT$8)*CZ$11)*($M54*$N54*2*Y$7+$P56*Y$7+$O54*$M54*1.5*2*Y$7)/(Y$7*14),0),Y55) -> 0 | Z54: =IF(Z55="",$M54*$N54*2*Z$7+$P56*Z$7+$O54*$M54*1.5*2*Z$7+IF($O$10="Y",(SUMIF($CS$3:$DT$3,Z$1,$CS$8:$DT$8)-SUMIF($CS$3:$DT$3,Y$1,$CS$8:$DT$8))*($M54*$N54*2*Z$7+$P56*Z$7+$O54*$M54*1.5*2*Z$7)/(Z$7*14),0)+IF($O$11="Y",(SUMIF($CS$3:$DT$3,Z$1,$CS$8:$DT$8)*DB$11-SUMIF($CS$3:$DT$3,Y$1,$CS$8:$DT$8)*DA$11)*($M54*$N54*2*Z$7+$P56*Z$7+$O54*$M54*1.5*2*Z$7)/(Z$7*14),0),Z55) -> 0 | ... AD54: =IF(AD55="",$M54*$N54*2*AD$7+$P56*AD$7+$O54*$M54*1.5*2*AD$7+IF($O$10="Y",(SUMIF($CS$3:$DT$3,AD$1,$CS$8:$DT$8)-SUMIF($CS$3:$DT$3,AC$1,$CS$8:$DT$8))*($M54*$N54*2*AD$7+$P56*AD$7+$O54*$M54*1.5*2*AD$7)/(AD$7*14),0)+IF($O$11="Y",(SUMIF($CS$3:$DT$3,AD$1,$CS$8:$DT$8)*DF$11-SUMIF($CS$3:$DT$3,AC$1,$CS$8:$DT$8)*DE$11)*($M54*$N54*2*AD$7+$P56*AD$7+$O54*$M54*1.5*2*AD$7)/(AD$7*14),0),AD55) -> 0 | AE54: =SUM(S54:AD54) -> 0
A55: =A54 -> Uncheck to Hide | AG55: =IF(AE54=0,0,1) -> 0 | AH55: =IF(AG55=0,"",IF($AG$46>1,", 1 at "," at ")&"$"&ROUND(M54,2)&"/hour, working "&N54&" hours per week with"&IF(E54>0," housing","out housing"))
A56: Do not check this box | P56: =+M54*N54*R54/AE$7 -> 0 | S56: =IF(S55>0,S55-$P56*S$7,+S54-$P56*S$7) -> 0 | T56: =IF(T55>0,T55-$P56*T$7,+T54-$P56*T$7) -> 0 | U56: =IF(U55>0,U55-$P56*U$7,+U54-$P56*U$7) -> 0 | V56: =IF(V55>0,V55-$P56*V$7,+V54-$P56*V$7) -> 0 | W56: =IF(W55>0,W55-$P56*W$7,+W54-$P56*W$7) -> 0 | X56: =IF(X55>0,X55-$P56*X$7,+X54-$P56*X$7) -> 0 | Y56: =IF(Y55>0,Y55-$P56*Y$7,+Y54-$P56*Y$7) -> 0 | Z56: =IF(Z55>0,Z55-$P56*Z$7,+Z54-$P56*Z$7) -> 0 | ... AD56: =IF(AD55>0,AD55-$P56*AD$7,+AD54-$P56*AD$7) -> 0
A57: Do not check this box | S57: =+S56 -> 0 | T57: =+T56+S57 -> 0 | U57: =+U56+T57 -> 0 | V57: =+V56+U57 -> 0 | W57: =+W56+V57 -> 0 | X57: =+X56+W57 -> 0 | Y57: =+Y56+X57 -> 0 | Z57: =+Z56+Y57 -> 0 | AA57: =+AA56+Z57 -> 0 | ... AD57: =+AD56+AC57 -> 0
A58: =A55 -> Uncheck to Hide | C58: Payroll Tax | S58: =IF($E$9="CA",IF(R57<7000,$E$5*S56,($E$5-0.043)*S56),IF($E$9="IL",IF(R57<12960,$E$5*S56,($E$5-0.04125)*S56),IF($E$9="PA",IF(R57<10000,$E$5*S56,($E$5-0.071)*S56),IF($E$9="TX",IF(R57<9000,$E$5*S56,($E$5-0.0363)*S56),$E$5*S56)))) -> 0 | T58: =IF($E$9="CA",IF(S57<7000,$E$5*T56,($E$5-0.043)*T56),IF($E$9="IL",IF(S57<12960,$E$5*T56,($E$5-0.04125)*T56),IF($E$9="PA",IF(S57<10000,$E$5*T56,($E$5-0.071)*T56),IF($E$9="TX",IF(S57<9000,$E$5*T56,($E$5-0.0363)*T56),$E$5*T56)))) -> 0 | U58: =IF($E$9="CA",IF(T57<7000,$E$5*U56,($E$5-0.043)*U56),IF($E$9="IL",IF(T57<12960,$E$5*U56,($E$5-0.04125)*U56),IF($E$9="PA",IF(T57<10000,$E$5*U56,($E$5-0.071)*U56),IF($E$9="TX",IF(T57<9000,$E$5*U56,($E$5-0.0363)*U56),$E$5*U56)))) -> 0 | V58: =IF($E$9="CA",IF(U57<7000,$E$5*V56,($E$5-0.043)*V56),IF($E$9="IL",IF(U57<12960,$E$5*V56,($E$5-0.04125)*V56),IF($E$9="PA",IF(U57<10000,$E$5*V56,($E$5-0.071)*V56),IF($E$9="TX",IF(U57<9000,$E$5*V56,($E$5-0.0363)*V56),$E$5*V56)))) -> 0 | W58: =IF($E$9="CA",IF(V57<7000,$E$5*W56,($E$5-0.043)*W56),IF($E$9="IL",IF(V57<12960,$E$5*W56,($E$5-0.04125)*W56),IF($E$9="PA",IF(V57<10000,$E$5*W56,($E$5-0.071)*W56),IF($E$9="TX",IF(V57<9000,$E$5*W56,($E$5-0.0363)*W56),$E$5*W56)))) -> 0 | X58: =IF($E$9="CA",IF(W57<7000,$E$5*X56,($E$5-0.043)*X56),IF($E$9="IL",IF(W57<12960,$E$5*X56,($E$5-0.04125)*X56),IF($E$9="PA",IF(W57<10000,$E$5*X56,($E$5-0.071)*X56),IF($E$9="TX",IF(W57<9000,$E$5*X56,($E$5-0.0363)*X56),$E$5*X56)))) -> 0 | Y58: =IF($E$9="CA",IF(X57<7000,$E$5*Y56,($E$5-0.043)*Y56),IF($E$9="IL",IF(X57<12960,$E$5*Y56,($E$5-0.04125)*Y56),IF($E$9="PA",IF(X57<10000,$E$5*Y56,($E$5-0.071)*Y56),IF($E$9="TX",IF(X57<9000,$E$5*Y56,($E$5-0.0363)*Y56),$E$5*Y56)))) -> 0 | Z58: =IF($E$9="CA",IF(Y57<7000,$E$5*Z56,($E$5-0.043)*Z56),IF($E$9="IL",IF(Y57<12960,$E$5*Z56,($E$5-0.04125)*Z56),IF($E$9="PA",IF(Y57<10000,$E$5*Z56,($E$5-0.071)*Z56),IF($E$9="TX",IF(Y57<9000,$E$5*Z56,($E$5-0.0363)*Z56),$E$5*Z56)))) -> 0 | ... AD58: =IF($E$9="CA",IF(AC57<7000,$E$5*AD56,($E$5-0.043)*AD56),IF($E$9="IL",IF(AC57<12960,$E$5*AD56,($E$5-0.04125)*AD56),IF($E$9="PA",IF(AC57<10000,$E$5*AD56,($E$5-0.071)*AD56),IF($E$9="TX",IF(AC57<9000,$E$5*AD56,($E$5-0.0363)*AD56),$E$5*AD56)))) -> 0
A59: =A58 -> Uncheck to Hide | C59: Workman's Comp | S59: =IF($E$9="WA",IF(S$1<$G$6,$E$6*$N54*2*S$7+$CA$5*S56,$F$6*$N54*2*S$7+$CA$5*S56),IF($E$9="NV",IF(R57>36000,0,IF(S$1<$G$6,$E$6*S56,$F$6*S56)),IF(S$1<$G$6,$E$6*S56,$F$6*S56))) -> 0 | T59: =IF($E$9="WA",IF(T$1<$G$6,$E$6*$N54*2*T$7+$CA$5*T56,$F$6*$N54*2*T$7+$CA$5*T56),IF($E$9="NV",IF(S57>36000,0,IF(T$1<$G$6,$E$6*T56,$F$6*T56)),IF(T$1<$G$6,$E$6*T56,$F$6*T56))) -> 0 | U59: =IF($E$9="WA",IF(U$1<$G$6,$E$6*$N54*2*U$7+$CA$5*U56,$F$6*$N54*2*U$7+$CA$5*U56),IF($E$9="NV",IF(T57>36000,0,IF(U$1<$G$6,$E$6*U56,$F$6*U56)),IF(U$1<$G$6,$E$6*U56,$F$6*U56))) -> 0 | V59: =IF($E$9="WA",IF(V$1<$G$6,$E$6*$N54*2*V$7+$CA$5*V56,$F$6*$N54*2*V$7+$CA$5*V56),IF($E$9="NV",IF(U57>36000,0,IF(V$1<$G$6,$E$6*V56,$F$6*V56)),IF(V$1<$G$6,$E$6*V56,$F$6*V56))) -> 0 | W59: =IF($E$9="WA",IF(W$1<$G$6,$E$6*$N54*2*W$7+$CA$5*W56,$F$6*$N54*2*W$7+$CA$5*W56),IF($E$9="NV",IF(V57>36000,0,IF(W$1<$G$6,$E$6*W56,$F$6*W56)),IF(W$1<$G$6,$E$6*W56,$F$6*W56))) -> 0 | X59: =IF($E$9="WA",IF(X$1<$G$6,$E$6*$N54*2*X$7+$CA$5*X56,$F$6*$N54*2*X$7+$CA$5*X56),IF($E$9="NV",IF(W57>36000,0,IF(X$1<$G$6,$E$6*X56,$F$6*X56)),IF(X$1<$G$6,$E$6*X56,$F$6*X56))) -> 0 | Y59: =IF($E$9="WA",IF(Y$1<$G$6,$E$6*$N54*2*Y$7+$CA$5*Y56,$F$6*$N54*2*Y$7+$CA$5*Y56),IF($E$9="NV",IF(X57>36000,0,IF(Y$1<$G$6,$E$6*Y56,$F$6*Y56)),IF(Y$1<$G$6,$E$6*Y56,$F$6*Y56))) -> 0 | Z59: =IF($E$9="WA",IF(Z$1<$G$6,$E$6*$N54*2*Z$7+$CA$5*Z56,$F$6*$N54*2*Z$7+$CA$5*Z56),IF($E$9="NV",IF(Y57>36000,0,IF(Z$1<$G$6,$E$6*Z56,$F$6*Z56)),IF(Z$1<$G$6,$E$6*Z56,$F$6*Z56))) -> 0 | ... AD59: =IF($E$9="WA",IF(AD$1<$G$6,$E$6*$N54*2*AD$7+$CA$5*AD56,$F$6*$N54*2*AD$7+$CA$5*AD56),IF($E$9="NV",IF(AC57>36000,0,IF(AD$1<$G$6,$E$6*AD56,$F$6*AD56)),IF(AD$1<$G$6,$E$6*AD56,$F$6*AD56))) -> 0
A60: =A59 -> Uncheck to Hide | C60: 401K Match | S60: =IF(S54=0,0,$H$11/26*S$7*IF(OR($G54=0,$G54=1),1,$G54)) -> 0 | T60: =IF(T54=0,0,$H$11/26*T$7*IF(OR($G54=0,$G54=1),1,$G54)) -> 0 | U60: =IF(U54=0,0,$H$11/26*U$7*IF(OR($G54=0,$G54=1),1,$G54)) -> 0 | V60: =IF(V54=0,0,$H$11/26*V$7*IF(OR($G54=0,$G54=1),1,$G54)) -> 0 | W60: =IF(W54=0,0,$H$11/26*W$7*IF(OR($G54=0,$G54=1),1,$G54)) -> 0 | X60: =IF(X54=0,0,$H$11/26*X$7*IF(OR($G54=0,$G54=1),1,$G54)) -> 0 | Y60: =IF(Y54=0,0,$H$11/26*Y$7*IF(OR($G54=0,$G54=1),1,$G54)) -> 0 | Z60: =IF(Z54=0,0,$H$11/26*Z$7*IF(OR($G54=0,$G54=1),1,$G54)) -> 0 | ... AD60: =IF(AD54=0,0,$H$11/26*AD$7*IF(OR($G54=0,$G54=1),1,$G54)) -> 0
A61: =A59 -> Uncheck to Hide | C61: =IF($E$9="CA","",$C$269) -> HEALTH INS. & EMPL. BENEFITS | S61: =IF(OR($E$9="CA",$E$9="CO",$E$9="OR",$E$9="WA"),0,IF($G54=0,0,$G54*$E$7*S$8/2+S56*$CC$6)) -> 0 | T61: =IF(OR($E$9="CA",$E$9="CO",$E$9="OR",$E$9="WA"),0,IF($G54=0,0,$G54*$E$7*T$8/2+T56*$CC$6)) -> 0 | U61: =IF(OR($E$9="CA",$E$9="CO",$E$9="OR",$E$9="WA"),0,IF($G54=0,0,$G54*$E$7*U$8/2+U56*$CC$6)) -> 0 | V61: =IF(OR($E$9="CA",$E$9="CO",$E$9="OR",$E$9="WA"),0,IF($G54=0,0,$G54*$E$7*V$8/2+V56*$CC$6)) -> 0 | W61: =IF(OR($E$9="CA",$E$9="CO",$E$9="OR",$E$9="WA"),0,IF($G54=0,0,$G54*$E$7*W$8/2+W56*$CC$6)) -> 0 | X61: =IF(OR($E$9="CA",$E$9="CO",$E$9="OR",$E$9="WA"),0,IF($G54=0,0,$G54*$E$7*X$8/2+X56*$CC$6)) -> 0 | Y61: =IF(OR($E$9="CA",$E$9="CO",$E$9="OR",$E$9="WA"),0,IF($G54=0,0,$G54*$E$7*Y$8/2+Y56*$CC$6)) -> 0 | Z61: =IF(OR($E$9="CA",$E$9="CO",$E$9="OR",$E$9="WA"),0,IF($G54=0,0,$G54*$E$7*Z$8/2+Z56*$CC$6)) -> 0 | ... AD61: =IF(OR($E$9="CA",$E$9="CO",$E$9="OR",$E$9="WA"),0,IF($G54=0,0,$G54*$E$7*AD$8/2+AD56*$CC$6)) -> 0
A62: =IF(F62+G62+H62+M62=0,"Uncheck to Hide","") -> Uncheck to Hide | B62: =B54 -> 6330-200 LEASING SALARY | C62: Leasing Consultant 3 | I62: 15 | M62: =ROUND(K62*(1+L62),2) -> 0 | P62: =IF(SUM(S63:AD63)>0,1,0) -> 0 | Q62: =M62*N62*52 -> 0 | S62: =IF(S63="",$M62*$N62*2*S$7+$P64*S$7+$O62*$M62*1.5*2*S$7+IF($O$10="Y",(SUMIF($CS$3:$DT$3,S$1,$CS$8:$DT$8)-SUMIF($CS$3:$DT$3,R$1,$CS$8:$DT$8))*($M62*$N62*2*S$7+$P64*S$7+$O62*$M62*1.5*2*S$7)/(S$7*14),0)+IF($O$11="Y",(SUMIF($CS$3:$DT$3,S$1,$CS$8:$DT$8)*CU$11-SUMIF($CS$3:$DT$3,R$1,$CS$8:$DT$8)*CT$11)*($M62*$N62*2*S$7+$P64*S$7+$O62*$M62*1.5*2*S$7)/(S$7*14),0),S63) -> 0 | T62: =IF(T63="",$M62*$N62*2*T$7+$P64*T$7+$O62*$M62*1.5*2*T$7+IF($O$10="Y",(SUMIF($CS$3:$DT$3,T$1,$CS$8:$DT$8)-SUMIF($CS$3:$DT$3,S$1,$CS$8:$DT$8))*($M62*$N62*2*T$7+$P64*T$7+$O62*$M62*1.5*2*T$7)/(T$7*14),0)+IF($O$11="Y",(SUMIF($CS$3:$DT$3,T$1,$CS$8:$DT$8)*CV$11-SUMIF($CS$3:$DT$3,S$1,$CS$8:$DT$8)*CU$11)*($M62*$N62*2*T$7+$P64*T$7+$O62*$M62*1.5*2*T$7)/(T$7*14),0),T63) -> 0 | U62: =IF(U63="",$M62*$N62*2*U$7+$P64*U$7+$O62*$M62*1.5*2*U$7+IF($O$10="Y",(SUMIF($CS$3:$DT$3,U$1,$CS$8:$DT$8)-SUMIF($CS$3:$DT$3,T$1,$CS$8:$DT$8))*($M62*$N62*2*U$7+$P64*U$7+$O62*$M62*1.5*2*U$7)/(U$7*14),0)+IF($O$11="Y",(SUMIF($CS$3:$DT$3,U$1,$CS$8:$DT$8)*CW$11-SUMIF($CS$3:$DT$3,T$1,$CS$8:$DT$8)*CV$11)*($M62*$N62*2*U$7+$P64*U$7+$O62*$M62*1.5*2*U$7)/(U$7*14),0),U63) -> 0 | V62: =IF(V63="",$M62*$N62*2*V$7+$P64*V$7+$O62*$M62*1.5*2*V$7+IF($O$10="Y",(SUMIF($CS$3:$DT$3,V$1,$CS$8:$DT$8)-SUMIF($CS$3:$DT$3,U$1,$CS$8:$DT$8))*($M62*$N62*2*V$7+$P64*V$7+$O62*$M62*1.5*2*V$7)/(V$7*14),0)+IF($O$11="Y",(SUMIF($CS$3:$DT$3,V$1,$CS$8:$DT$8)*CX$11-SUMIF($CS$3:$DT$3,U$1,$CS$8:$DT$8)*CW$11)*($M62*$N62*2*V$7+$P64*V$7+$O62*$M62*1.5*2*V$7)/(V$7*14),0),V63) -> 0 | W62: =IF(W63="",$M62*$N62*2*W$7+$P64*W$7+$O62*$M62*1.5*2*W$7+IF($O$10="Y",(SUMIF($CS$3:$DT$3,W$1,$CS$8:$DT$8)-SUMIF($CS$3:$DT$3,V$1,$CS$8:$DT$8))*($M62*$N62*2*W$7+$P64*W$7+$O62*$M62*1.5*2*W$7)/(W$7*14),0)+IF($O$11="Y",(SUMIF($CS$3:$DT$3,W$1,$CS$8:$DT$8)*CY$11-SUMIF($CS$3:$DT$3,V$1,$CS$8:$DT$8)*CX$11)*($M62*$N62*2*W$7+$P64*W$7+$O62*$M62*1.5*2*W$7)/(W$7*14),0),W63) -> 0 | X62: =IF(X63="",$M62*$N62*2*X$7+$P64*X$7+$O62*$M62*1.5*2*X$7+IF($O$10="Y",(SUMIF($CS$3:$DT$3,X$1,$CS$8:$DT$8)-SUMIF($CS$3:$DT$3,W$1,$CS$8:$DT$8))*($M62*$N62*2*X$7+$P64*X$7+$O62*$M62*1.5*2*X$7)/(X$7*14),0)+IF($O$11="Y",(SUMIF($CS$3:$DT$3,X$1,$CS$8:$DT$8)*CZ$11-SUMIF($CS$3:$DT$3,W$1,$CS$8:$DT$8)*CY$11)*($M62*$N62*2*X$7+$P64*X$7+$O62*$M62*1.5*2*X$7)/(X$7*14),0),X63) -> 0 | Y62: =IF(Y63="",$M62*$N62*2*Y$7+$P64*Y$7+$O62*$M62*1.5*2*Y$7+IF($O$10="Y",(SUMIF($CS$3:$DT$3,Y$1,$CS$8:$DT$8)-SUMIF($CS$3:$DT$3,X$1,$CS$8:$DT$8))*($M62*$N62*2*Y$7+$P64*Y$7+$O62*$M62*1.5*2*Y$7)/(Y$7*14),0)+IF($O$11="Y",(SUMIF($CS$3:$DT$3,Y$1,$CS$8:$DT$8)*DA$11-SUMIF($CS$3:$DT$3,X$1,$CS$8:$DT$8)*CZ$11)*($M62*$N62*2*Y$7+$P64*Y$7+$O62*$M62*1.5*2*Y$7)/(Y$7*14),0),Y63) -> 0 | Z62: =IF(Z63="",$M62*$N62*2*Z$7+$P64*Z$7+$O62*$M62*1.5*2*Z$7+IF($O$10="Y",(SUMIF($CS$3:$DT$3,Z$1,$CS$8:$DT$8)-SUMIF($CS$3:$DT$3,Y$1,$CS$8:$DT$8))*($M62*$N62*2*Z$7+$P64*Z$7+$O62*$M62*1.5*2*Z$7)/(Z$7*14),0)+IF($O$11="Y",(SUMIF($CS$3:$DT$3,Z$1,$CS$8:$DT$8)*DB$11-SUMIF($CS$3:$DT$3,Y$1,$CS$8:$DT$8)*DA$11)*($M62*$N62*2*Z$7+$P64*Z$7+$O62*$M62*1.5*2*Z$7)/(Z$7*14),0),Z63) -> 0 | ... AD62: =IF(AD63="",$M62*$N62*2*AD$7+$P64*AD$7+$O62*$M62*1.5*2*AD$7+IF($O$10="Y",(SUMIF($CS$3:$DT$3,AD$1,$CS$8:$DT$8)-SUMIF($CS$3:$DT$3,AC$1,$CS$8:$DT$8))*($M62*$N62*2*AD$7+$P64*AD$7+$O62*$M62*1.5*2*AD$7)/(AD$7*14),0)+IF($O$11="Y",(SUMIF($CS$3:$DT$3,AD$1,$CS$8:$DT$8)*DF$11-SUMIF($CS$3:$DT$3,AC$1,$CS$8:$DT$8)*DE$11)*($M62*$N62*2*AD$7+$P64*AD$7+$O62*$M62*1.5*2*AD$7)/(AD$7*14),0),AD63) -> 0 | AE62: =SUM(S62:AD62) -> 0
A63: =A62 -> Uncheck to Hide | AG63: =IF(AE62=0,0,1) -> 0 | AH63: =IF(AG63=0,"",IF($AG$46>1,", 1 at "," at ")&"$"&ROUND(M62,2)&"/hour, working "&N62&" hours per week with"&IF(E62>0," housing","out housing"))
A64: Do not check this box | P64: =+M62*N62*R62/AE$7 -> 0 | S64: =IF(S63>0,S63-$P64*S$7,+S62-$P64*S$7) -> 0 | T64: =IF(T63>0,T63-$P64*T$7,+T62-$P64*T$7) -> 0 | U64: =IF(U63>0,U63-$P64*U$7,+U62-$P64*U$7) -> 0 | V64: =IF(V63>0,V63-$P64*V$7,+V62-$P64*V$7) -> 0 | W64: =IF(W63>0,W63-$P64*W$7,+W62-$P64*W$7) -> 0 | X64: =IF(X63>0,X63-$P64*X$7,+X62-$P64*X$7) -> 0 | Y64: =IF(Y63>0,Y63-$P64*Y$7,+Y62-$P64*Y$7) -> 0 | Z64: =IF(Z63>0,Z63-$P64*Z$7,+Z62-$P64*Z$7) -> 0 | ... AD64: =IF(AD63>0,AD63-$P64*AD$7,+AD62-$P64*AD$7) -> 0
A65: Do not check this box | S65: =+S64 -> 0 | T65: =+T64+S65 -> 0 | U65: =+U64+T65 -> 0 | V65: =+V64+U65 -> 0 | W65: =+W64+V65 -> 0 | X65: =+X64+W65 -> 0 | Y65: =+Y64+X65 -> 0 | Z65: =+Z64+Y65 -> 0 | AA65: =+AA64+Z65 -> 0 | ... AD65: =+AD64+AC65 -> 0
A66: =A63 -> Uncheck to Hide | C66: Payroll Tax | S66: =IF($E$9="CA",IF(R65<7000,$E$5*S64,($E$5-0.043)*S64),IF($E$9="IL",IF(R65<12960,$E$5*S64,($E$5-0.04125)*S64),IF($E$9="PA",IF(R65<10000,$E$5*S64,($E$5-0.071)*S64),IF($E$9="TX",IF(R65<9000,$E$5*S64,($E$5-0.0363)*S64),$E$5*S64)))) -> 0 | T66: =IF($E$9="CA",IF(S65<7000,$E$5*T64,($E$5-0.043)*T64),IF($E$9="IL",IF(S65<12960,$E$5*T64,($E$5-0.04125)*T64),IF($E$9="PA",IF(S65<10000,$E$5*T64,($E$5-0.071)*T64),IF($E$9="TX",IF(S65<9000,$E$5*T64,($E$5-0.0363)*T64),$E$5*T64)))) -> 0 | U66: =IF($E$9="CA",IF(T65<7000,$E$5*U64,($E$5-0.043)*U64),IF($E$9="IL",IF(T65<12960,$E$5*U64,($E$5-0.04125)*U64),IF($E$9="PA",IF(T65<10000,$E$5*U64,($E$5-0.071)*U64),IF($E$9="TX",IF(T65<9000,$E$5*U64,($E$5-0.0363)*U64),$E$5*U64)))) -> 0 | V66: =IF($E$9="CA",IF(U65<7000,$E$5*V64,($E$5-0.043)*V64),IF($E$9="IL",IF(U65<12960,$E$5*V64,($E$5-0.04125)*V64),IF($E$9="PA",IF(U65<10000,$E$5*V64,($E$5-0.071)*V64),IF($E$9="TX",IF(U65<9000,$E$5*V64,($E$5-0.0363)*V64),$E$5*V64)))) -> 0 | W66: =IF($E$9="CA",IF(V65<7000,$E$5*W64,($E$5-0.043)*W64),IF($E$9="IL",IF(V65<12960,$E$5*W64,($E$5-0.04125)*W64),IF($E$9="PA",IF(V65<10000,$E$5*W64,($E$5-0.071)*W64),IF($E$9="TX",IF(V65<9000,$E$5*W64,($E$5-0.0363)*W64),$E$5*W64)))) -> 0 | X66: =IF($E$9="CA",IF(W65<7000,$E$5*X64,($E$5-0.043)*X64),IF($E$9="IL",IF(W65<12960,$E$5*X64,($E$5-0.04125)*X64),IF($E$9="PA",IF(W65<10000,$E$5*X64,($E$5-0.071)*X64),IF($E$9="TX",IF(W65<9000,$E$5*X64,($E$5-0.0363)*X64),$E$5*X64)))) -> 0 | Y66: =IF($E$9="CA",IF(X65<7000,$E$5*Y64,($E$5-0.043)*Y64),IF($E$9="IL",IF(X65<12960,$E$5*Y64,($E$5-0.04125)*Y64),IF($E$9="PA",IF(X65<10000,$E$5*Y64,($E$5-0.071)*Y64),IF($E$9="TX",IF(X65<9000,$E$5*Y64,($E$5-0.0363)*Y64),$E$5*Y64)))) -> 0 | Z66: =IF($E$9="CA",IF(Y65<7000,$E$5*Z64,($E$5-0.043)*Z64),IF($E$9="IL",IF(Y65<12960,$E$5*Z64,($E$5-0.04125)*Z64),IF($E$9="PA",IF(Y65<10000,$E$5*Z64,($E$5-0.071)*Z64),IF($E$9="TX",IF(Y65<9000,$E$5*Z64,($E$5-0.0363)*Z64),$E$5*Z64)))) -> 0 | ... AD66: =IF($E$9="CA",IF(AC65<7000,$E$5*AD64,($E$5-0.043)*AD64),IF($E$9="IL",IF(AC65<12960,$E$5*AD64,($E$5-0.04125)*AD64),IF($E$9="PA",IF(AC65<10000,$E$5*AD64,($E$5-0.071)*AD64),IF($E$9="TX",IF(AC65<9000,$E$5*AD64,($E$5-0.0363)*AD64),$E$5*AD64)))) -> 0
A67: =A66 -> Uncheck to Hide | C67: Workman's Comp | S67: =IF($E$9="WA",IF(S$1<$G$6,$E$6*$N62*2*S$7+$CA$5*S64,$F$6*$N62*2*S$7+$CA$5*S64),IF($E$9="NV",IF(R65>36000,0,IF(S$1<$G$6,$E$6*S64,$F$6*S64)),IF(S$1<$G$6,$E$6*S64,$F$6*S64))) -> 0 | T67: =IF($E$9="WA",IF(T$1<$G$6,$E$6*$N62*2*T$7+$CA$5*T64,$F$6*$N62*2*T$7+$CA$5*T64),IF($E$9="NV",IF(S65>36000,0,IF(T$1<$G$6,$E$6*T64,$F$6*T64)),IF(T$1<$G$6,$E$6*T64,$F$6*T64))) -> 0 | U67: =IF($E$9="WA",IF(U$1<$G$6,$E$6*$N62*2*U$7+$CA$5*U64,$F$6*$N62*2*U$7+$CA$5*U64),IF($E$9="NV",IF(T65>36000,0,IF(U$1<$G$6,$E$6*U64,$F$6*U64)),IF(U$1<$G$6,$E$6*U64,$F$6*U64))) -> 0 | V67: =IF($E$9="WA",IF(V$1<$G$6,$E$6*$N62*2*V$7+$CA$5*V64,$F$6*$N62*2*V$7+$CA$5*V64),IF($E$9="NV",IF(U65>36000,0,IF(V$1<$G$6,$E$6*V64,$F$6*V64)),IF(V$1<$G$6,$E$6*V64,$F$6*V64))) -> 0 | W67: =IF($E$9="WA",IF(W$1<$G$6,$E$6*$N62*2*W$7+$CA$5*W64,$F$6*$N62*2*W$7+$CA$5*W64),IF($E$9="NV",IF(V65>36000,0,IF(W$1<$G$6,$E$6*W64,$F$6*W64)),IF(W$1<$G$6,$E$6*W64,$F$6*W64))) -> 0 | X67: =IF($E$9="WA",IF(X$1<$G$6,$E$6*$N62*2*X$7+$CA$5*X64,$F$6*$N62*2*X$7+$CA$5*X64),IF($E$9="NV",IF(W65>36000,0,IF(X$1<$G$6,$E$6*X64,$F$6*X64)),IF(X$1<$G$6,$E$6*X64,$F$6*X64))) -> 0 | Y67: =IF($E$9="WA",IF(Y$1<$G$6,$E$6*$N62*2*Y$7+$CA$5*Y64,$F$6*$N62*2*Y$7+$CA$5*Y64),IF($E$9="NV",IF(X65>36000,0,IF(Y$1<$G$6,$E$6*Y64,$F$6*Y64)),IF(Y$1<$G$6,$E$6*Y64,$F$6*Y64))) -> 0 | Z67: =IF($E$9="WA",IF(Z$1<$G$6,$E$6*$N62*2*Z$7+$CA$5*Z64,$F$6*$N62*2*Z$7+$CA$5*Z64),IF($E$9="NV",IF(Y65>36000,0,IF(Z$1<$G$6,$E$6*Z64,$F$6*Z64)),IF(Z$1<$G$6,$E$6*Z64,$F$6*Z64))) -> 0 | ... AD67: =IF($E$9="WA",IF(AD$1<$G$6,$E$6*$N62*2*AD$7+$CA$5*AD64,$F$6*$N62*2*AD$7+$CA$5*AD64),IF($E$9="NV",IF(AC65>36000,0,IF(AD$1<$G$6,$E$6*AD64,$F$6*AD64)),IF(AD$1<$G$6,$E$6*AD64,$F$6*AD64))) -> 0
A68: =A67 -> Uncheck to Hide | C68: 401K Match | S68: =IF(S62=0,0,$H$11/26*S$7*IF(OR($G62=0,$G62=1),1,$G62)) -> 0 | T68: =IF(T62=0,0,$H$11/26*T$7*IF(OR($G62=0,$G62=1),1,$G62)) -> 0 | U68: =IF(U62=0,0,$H$11/26*U$7*IF(OR($G62=0,$G62=1),1,$G62)) -> 0 | V68: =IF(V62=0,0,$H$11/26*V$7*IF(OR($G62=0,$G62=1),1,$G62)) -> 0 | W68: =IF(W62=0,0,$H$11/26*W$7*IF(OR($G62=0,$G62=1),1,$G62)) -> 0 | X68: =IF(X62=0,0,$H$11/26*X$7*IF(OR($G62=0,$G62=1),1,$G62)) -> 0 | Y68: =IF(Y62=0,0,$H$11/26*Y$7*IF(OR($G62=0,$G62=1),1,$G62)) -> 0 | Z68: =IF(Z62=0,0,$H$11/26*Z$7*IF(OR($G62=0,$G62=1),1,$G62)) -> 0 | ... AD68: =IF(AD62=0,0,$H$11/26*AD$7*IF(OR($G62=0,$G62=1),1,$G62)) -> 0
A69: =A67 -> Uncheck to Hide | C69: =IF($E$9="CA","",$C$269) -> HEALTH INS. & EMPL. BENEFITS | S69: =IF(OR($E$9="CA",$E$9="CO",$E$9="OR",$E$9="WA"),0,IF($G62=0,0,$G62*$E$7*S$8/2+S64*$CC$6)) -> 0 | T69: =IF(OR($E$9="CA",$E$9="CO",$E$9="OR",$E$9="WA"),0,IF($G62=0,0,$G62*$E$7*T$8/2+T64*$CC$6)) -> 0 | U69: =IF(OR($E$9="CA",$E$9="CO",$E$9="OR",$E$9="WA"),0,IF($G62=0,0,$G62*$E$7*U$8/2+U64*$CC$6)) -> 0 | V69: =IF(OR($E$9="CA",$E$9="CO",$E$9="OR",$E$9="WA"),0,IF($G62=0,0,$G62*$E$7*V$8/2+V64*$CC$6)) -> 0 | W69: =IF(OR($E$9="CA",$E$9="CO",$E$9="OR",$E$9="WA"),0,IF($G62=0,0,$G62*$E$7*W$8/2+W64*$CC$6)) -> 0 | X69: =IF(OR($E$9="CA",$E$9="CO",$E$9="OR",$E$9="WA"),0,IF($G62=0,0,$G62*$E$7*X$8/2+X64*$CC$6)) -> 0 | Y69: =IF(OR($E$9="CA",$E$9="CO",$E$9="OR",$E$9="WA"),0,IF($G62=0,0,$G62*$E$7*Y$8/2+Y64*$CC$6)) -> 0 | Z69: =IF(OR($E$9="CA",$E$9="CO",$E$9="OR",$E$9="WA"),0,IF($G62=0,0,$G62*$E$7*Z$8/2+Z64*$CC$6)) -> 0 | ... AD69: =IF(OR($E$9="CA",$E$9="CO",$E$9="OR",$E$9="WA"),0,IF($G62=0,0,$G62*$E$7*AD$8/2+AD64*$CC$6)) -> 0
A70: =IF(F70+G70+H70+M70=0,"Uncheck to Hide","") -> Uncheck to Hide | B70: =B62 -> 6330-200 LEASING SALARY | C70: Leasing Consultant 4 | I70: 15 | M70: =ROUND(K70*(1+L70),2) -> 0 | P70: =IF(SUM(S71:AD71)>0,1,0) -> 0 | Q70: =M70*N70*52 -> 0 | S70: =IF(S71="",$M70*$N70*2*S$7+$P72*S$7+$O70*$M70*1.5*2*S$7+IF($O$10="Y",(SUMIF($CS$3:$DT$3,S$1,$CS$8:$DT$8)-SUMIF($CS$3:$DT$3,R$1,$CS$8:$DT$8))*($M70*$N70*2*S$7+$P72*S$7+$O70*$M70*1.5*2*S$7)/(S$7*14),0)+IF($O$11="Y",(SUMIF($CS$3:$DT$3,S$1,$CS$8:$DT$8)*CU$11-SUMIF($CS$3:$DT$3,R$1,$CS$8:$DT$8)*CT$11)*($M70*$N70*2*S$7+$P72*S$7+$O70*$M70*1.5*2*S$7)/(S$7*14),0),S71) -> 0 | T70: =IF(T71="",$M70*$N70*2*T$7+$P72*T$7+$O70*$M70*1.5*2*T$7+IF($O$10="Y",(SUMIF($CS$3:$DT$3,T$1,$CS$8:$DT$8)-SUMIF($CS$3:$DT$3,S$1,$CS$8:$DT$8))*($M70*$N70*2*T$7+$P72*T$7+$O70*$M70*1.5*2*T$7)/(T$7*14),0)+IF($O$11="Y",(SUMIF($CS$3:$DT$3,T$1,$CS$8:$DT$8)*CV$11-SUMIF($CS$3:$DT$3,S$1,$CS$8:$DT$8)*CU$11)*($M70*$N70*2*T$7+$P72*T$7+$O70*$M70*1.5*2*T$7)/(T$7*14),0),T71) -> 0 | U70: =IF(U71="",$M70*$N70*2*U$7+$P72*U$7+$O70*$M70*1.5*2*U$7+IF($O$10="Y",(SUMIF($CS$3:$DT$3,U$1,$CS$8:$DT$8)-SUMIF($CS$3:$DT$3,T$1,$CS$8:$DT$8))*($M70*$N70*2*U$7+$P72*U$7+$O70*$M70*1.5*2*U$7)/(U$7*14),0)+IF($O$11="Y",(SUMIF($CS$3:$DT$3,U$1,$CS$8:$DT$8)*CW$11-SUMIF($CS$3:$DT$3,T$1,$CS$8:$DT$8)*CV$11)*($M70*$N70*2*U$7+$P72*U$7+$O70*$M70*1.5*2*U$7)/(U$7*14),0),U71) -> 0 | V70: =IF(V71="",$M70*$N70*2*V$7+$P72*V$7+$O70*$M70*1.5*2*V$7+IF($O$10="Y",(SUMIF($CS$3:$DT$3,V$1,$CS$8:$DT$8)-SUMIF($CS$3:$DT$3,U$1,$CS$8:$DT$8))*($M70*$N70*2*V$7+$P72*V$7+$O70*$M70*1.5*2*V$7)/(V$7*14),0)+IF($O$11="Y",(SUMIF($CS$3:$DT$3,V$1,$CS$8:$DT$8)*CX$11-SUMIF($CS$3:$DT$3,U$1,$CS$8:$DT$8)*CW$11)*($M70*$N70*2*V$7+$P72*V$7+$O70*$M70*1.5*2*V$7)/(V$7*14),0),V71) -> 0 | W70: =IF(W71="",$M70*$N70*2*W$7+$P72*W$7+$O70*$M70*1.5*2*W$7+IF($O$10="Y",(SUMIF($CS$3:$DT$3,W$1,$CS$8:$DT$8)-SUMIF($CS$3:$DT$3,V$1,$CS$8:$DT$8))*($M70*$N70*2*W$7+$P72*W$7+$O70*$M70*1.5*2*W$7)/(W$7*14),0)+IF($O$11="Y",(SUMIF($CS$3:$DT$3,W$1,$CS$8:$DT$8)*CY$11-SUMIF($CS$3:$DT$3,V$1,$CS$8:$DT$8)*CX$11)*($M70*$N70*2*W$7+$P72*W$7+$O70*$M70*1.5*2*W$7)/(W$7*14),0),W71) -> 0 | X70: =IF(X71="",$M70*$N70*2*X$7+$P72*X$7+$O70*$M70*1.5*2*X$7+IF($O$10="Y",(SUMIF($CS$3:$DT$3,X$1,$CS$8:$DT$8)-SUMIF($CS$3:$DT$3,W$1,$CS$8:$DT$8))*($M70*$N70*2*X$7+$P72*X$7+$O70*$M70*1.5*2*X$7)/(X$7*14),0)+IF($O$11="Y",(SUMIF($CS$3:$DT$3,X$1,$CS$8:$DT$8)*CZ$11-SUMIF($CS$3:$DT$3,W$1,$CS$8:$DT$8)*CY$11)*($M70*$N70*2*X$7+$P72*X$7+$O70*$M70*1.5*2*X$7)/(X$7*14),0),X71) -> 0 | Y70: =IF(Y71="",$M70*$N70*2*Y$7+$P72*Y$7+$O70*$M70*1.5*2*Y$7+IF($O$10="Y",(SUMIF($CS$3:$DT$3,Y$1,$CS$8:$DT$8)-SUMIF($CS$3:$DT$3,X$1,$CS$8:$DT$8))*($M70*$N70*2*Y$7+$P72*Y$7+$O70*$M70*1.5*2*Y$7)/(Y$7*14),0)+IF($O$11="Y",(SUMIF($CS$3:$DT$3,Y$1,$CS$8:$DT$8)*DA$11-SUMIF($CS$3:$DT$3,X$1,$CS$8:$DT$8)*CZ$11)*($M70*$N70*2*Y$7+$P72*Y$7+$O70*$M70*1.5*2*Y$7)/(Y$7*14),0),Y71) -> 0 | Z70: =IF(Z71="",$M70*$N70*2*Z$7+$P72*Z$7+$O70*$M70*1.5*2*Z$7+IF($O$10="Y",(SUMIF($CS$3:$DT$3,Z$1,$CS$8:$DT$8)-SUMIF($CS$3:$DT$3,Y$1,$CS$8:$DT$8))*($M70*$N70*2*Z$7+$P72*Z$7+$O70*$M70*1.5*2*Z$7)/(Z$7*14),0)+IF($O$11="Y",(SUMIF($CS$3:$DT$3,Z$1,$CS$8:$DT$8)*DB$11-SUMIF($CS$3:$DT$3,Y$1,$CS$8:$DT$8)*DA$11)*($M70*$N70*2*Z$7+$P72*Z$7+$O70*$M70*1.5*2*Z$7)/(Z$7*14),0),Z71) -> 0 | ... AD70: =IF(AD71="",$M70*$N70*2*AD$7+$P72*AD$7+$O70*$M70*1.5*2*AD$7+IF($O$10="Y",(SUMIF($CS$3:$DT$3,AD$1,$CS$8:$DT$8)-SUMIF($CS$3:$DT$3,AC$1,$CS$8:$DT$8))*($M70*$N70*2*AD$7+$P72*AD$7+$O70*$M70*1.5*2*AD$7)/(AD$7*14),0)+IF($O$11="Y",(SUMIF($CS$3:$DT$3,AD$1,$CS$8:$DT$8)*DF$11-SUMIF($CS$3:$DT$3,AC$1,$CS$8:$DT$8)*DE$11)*($M70*$N70*2*AD$7+$P72*AD$7+$O70*$M70*1.5*2*AD$7)/(AD$7*14),0),AD71) -> 0 | AE70: =SUM(S70:AD70) -> 0
A71: =A70 -> Uncheck to Hide | AG71: =IF(AE70=0,0,1) -> 0 | AH71: =IF(AG71=0,"",IF($AG$46>1,", 1 at "," at ")&"$"&ROUND(M70,2)&"/hour, working "&N70&" hours per week with"&IF(E70>0," housing","out housing"))
A72: Do not check this box | P72: =+M70*N70*R70/AE$7 -> 0 | S72: =IF(S71>0,S71-$P72*S$7,+S70-$P72*S$7) -> 0 | T72: =IF(T71>0,T71-$P72*T$7,+T70-$P72*T$7) -> 0 | U72: =IF(U71>0,U71-$P72*U$7,+U70-$P72*U$7) -> 0 | V72: =IF(V71>0,V71-$P72*V$7,+V70-$P72*V$7) -> 0 | W72: =IF(W71>0,W71-$P72*W$7,+W70-$P72*W$7) -> 0 | X72: =IF(X71>0,X71-$P72*X$7,+X70-$P72*X$7) -> 0 | Y72: =IF(Y71>0,Y71-$P72*Y$7,+Y70-$P72*Y$7) -> 0 | Z72: =IF(Z71>0,Z71-$P72*Z$7,+Z70-$P72*Z$7) -> 0 | ... AD72: =IF(AD71>0,AD71-$P72*AD$7,+AD70-$P72*AD$7) -> 0
A73: Do not check this box | S73: =+S72 -> 0 | T73: =+T72+S73 -> 0 | U73: =+U72+T73 -> 0 | V73: =+V72+U73 -> 0 | W73: =+W72+V73 -> 0 | X73: =+X72+W73 -> 0 | Y73: =+Y72+X73 -> 0 | Z73: =+Z72+Y73 -> 0 | AA73: =+AA72+Z73 -> 0 | ... AD73: =+AD72+AC73 -> 0
A74: =A71 -> Uncheck to Hide | C74: Payroll Tax | S74: =IF($E$9="CA",IF(R73<7000,$E$5*S72,($E$5-0.043)*S72),IF($E$9="IL",IF(R73<12960,$E$5*S72,($E$5-0.04125)*S72),IF($E$9="PA",IF(R73<10000,$E$5*S72,($E$5-0.071)*S72),IF($E$9="TX",IF(R73<9000,$E$5*S72,($E$5-0.0363)*S72),$E$5*S72)))) -> 0 | T74: =IF($E$9="CA",IF(S73<7000,$E$5*T72,($E$5-0.043)*T72),IF($E$9="IL",IF(S73<12960,$E$5*T72,($E$5-0.04125)*T72),IF($E$9="PA",IF(S73<10000,$E$5*T72,($E$5-0.071)*T72),IF($E$9="TX",IF(S73<9000,$E$5*T72,($E$5-0.0363)*T72),$E$5*T72)))) -> 0 | U74: =IF($E$9="CA",IF(T73<7000,$E$5*U72,($E$5-0.043)*U72),IF($E$9="IL",IF(T73<12960,$E$5*U72,($E$5-0.04125)*U72),IF($E$9="PA",IF(T73<10000,$E$5*U72,($E$5-0.071)*U72),IF($E$9="TX",IF(T73<9000,$E$5*U72,($E$5-0.0363)*U72),$E$5*U72)))) -> 0 | V74: =IF($E$9="CA",IF(U73<7000,$E$5*V72,($E$5-0.043)*V72),IF($E$9="IL",IF(U73<12960,$E$5*V72,($E$5-0.04125)*V72),IF($E$9="PA",IF(U73<10000,$E$5*V72,($E$5-0.071)*V72),IF($E$9="TX",IF(U73<9000,$E$5*V72,($E$5-0.0363)*V72),$E$5*V72)))) -> 0 | W74: =IF($E$9="CA",IF(V73<7000,$E$5*W72,($E$5-0.043)*W72),IF($E$9="IL",IF(V73<12960,$E$5*W72,($E$5-0.04125)*W72),IF($E$9="PA",IF(V73<10000,$E$5*W72,($E$5-0.071)*W72),IF($E$9="TX",IF(V73<9000,$E$5*W72,($E$5-0.0363)*W72),$E$5*W72)))) -> 0 | X74: =IF($E$9="CA",IF(W73<7000,$E$5*X72,($E$5-0.043)*X72),IF($E$9="IL",IF(W73<12960,$E$5*X72,($E$5-0.04125)*X72),IF($E$9="PA",IF(W73<10000,$E$5*X72,($E$5-0.071)*X72),IF($E$9="TX",IF(W73<9000,$E$5*X72,($E$5-0.0363)*X72),$E$5*X72)))) -> 0 | Y74: =IF($E$9="CA",IF(X73<7000,$E$5*Y72,($E$5-0.043)*Y72),IF($E$9="IL",IF(X73<12960,$E$5*Y72,($E$5-0.04125)*Y72),IF($E$9="PA",IF(X73<10000,$E$5*Y72,($E$5-0.071)*Y72),IF($E$9="TX",IF(X73<9000,$E$5*Y72,($E$5-0.0363)*Y72),$E$5*Y72)))) -> 0 | Z74: =IF($E$9="CA",IF(Y73<7000,$E$5*Z72,($E$5-0.043)*Z72),IF($E$9="IL",IF(Y73<12960,$E$5*Z72,($E$5-0.04125)*Z72),IF($E$9="PA",IF(Y73<10000,$E$5*Z72,($E$5-0.071)*Z72),IF($E$9="TX",IF(Y73<9000,$E$5*Z72,($E$5-0.0363)*Z72),$E$5*Z72)))) -> 0 | ... AD74: =IF($E$9="CA",IF(AC73<7000,$E$5*AD72,($E$5-0.043)*AD72),IF($E$9="IL",IF(AC73<12960,$E$5*AD72,($E$5-0.04125)*AD72),IF($E$9="PA",IF(AC73<10000,$E$5*AD72,($E$5-0.071)*AD72),IF($E$9="TX",IF(AC73<9000,$E$5*AD72,($E$5-0.0363)*AD72),$E$5*AD72)))) -> 0
A75: =A74 -> Uncheck to Hide | C75: Workman's Comp | S75: =IF($E$9="WA",IF(S$1<$G$6,$E$6*$N70*2*S$7+$CA$5*S72,$F$6*$N70*2*S$7+$CA$5*S72),IF($E$9="NV",IF(R73>36000,0,IF(S$1<$G$6,$E$6*S72,$F$6*S72)),IF(S$1<$G$6,$E$6*S72,$F$6*S72))) -> 0 | T75: =IF($E$9="WA",IF(T$1<$G$6,$E$6*$N70*2*T$7+$CA$5*T72,$F$6*$N70*2*T$7+$CA$5*T72),IF($E$9="NV",IF(S73>36000,0,IF(T$1<$G$6,$E$6*T72,$F$6*T72)),IF(T$1<$G$6,$E$6*T72,$F$6*T72))) -> 0 | U75: =IF($E$9="WA",IF(U$1<$G$6,$E$6*$N70*2*U$7+$CA$5*U72,$F$6*$N70*2*U$7+$CA$5*U72),IF($E$9="NV",IF(T73>36000,0,IF(U$1<$G$6,$E$6*U72,$F$6*U72)),IF(U$1<$G$6,$E$6*U72,$F$6*U72))) -> 0 | V75: =IF($E$9="WA",IF(V$1<$G$6,$E$6*$N70*2*V$7+$CA$5*V72,$F$6*$N70*2*V$7+$CA$5*V72),IF($E$9="NV",IF(U73>36000,0,IF(V$1<$G$6,$E$6*V72,$F$6*V72)),IF(V$1<$G$6,$E$6*V72,$F$6*V72))) -> 0 | W75: =IF($E$9="WA",IF(W$1<$G$6,$E$6*$N70*2*W$7+$CA$5*W72,$F$6*$N70*2*W$7+$CA$5*W72),IF($E$9="NV",IF(V73>36000,0,IF(W$1<$G$6,$E$6*W72,$F$6*W72)),IF(W$1<$G$6,$E$6*W72,$F$6*W72))) -> 0 | X75: =IF($E$9="WA",IF(X$1<$G$6,$E$6*$N70*2*X$7+$CA$5*X72,$F$6*$N70*2*X$7+$CA$5*X72),IF($E$9="NV",IF(W73>36000,0,IF(X$1<$G$6,$E$6*X72,$F$6*X72)),IF(X$1<$G$6,$E$6*X72,$F$6*X72))) -> 0 | Y75: =IF($E$9="WA",IF(Y$1<$G$6,$E$6*$N70*2*Y$7+$CA$5*Y72,$F$6*$N70*2*Y$7+$CA$5*Y72),IF($E$9="NV",IF(X73>36000,0,IF(Y$1<$G$6,$E$6*Y72,$F$6*Y72)),IF(Y$1<$G$6,$E$6*Y72,$F$6*Y72))) -> 0 | Z75: =IF($E$9="WA",IF(Z$1<$G$6,$E$6*$N70*2*Z$7+$CA$5*Z72,$F$6*$N70*2*Z$7+$CA$5*Z72),IF($E$9="NV",IF(Y73>36000,0,IF(Z$1<$G$6,$E$6*Z72,$F$6*Z72)),IF(Z$1<$G$6,$E$6*Z72,$F$6*Z72))) -> 0 | ... AD75: =IF($E$9="WA",IF(AD$1<$G$6,$E$6*$N70*2*AD$7+$CA$5*AD72,$F$6*$N70*2*AD$7+$CA$5*AD72),IF($E$9="NV",IF(AC73>36000,0,IF(AD$1<$G$6,$E$6*AD72,$F$6*AD72)),IF(AD$1<$G$6,$E$6*AD72,$F$6*AD72))) -> 0
A76: =A75 -> Uncheck to Hide | C76: 401K Match | S76: =IF(S70=0,0,$H$11/26*S$7*IF(OR($G70=0,$G70=1),1,$G70)) -> 0 | T76: =IF(T70=0,0,$H$11/26*T$7*IF(OR($G70=0,$G70=1),1,$G70)) -> 0 | U76: =IF(U70=0,0,$H$11/26*U$7*IF(OR($G70=0,$G70=1),1,$G70)) -> 0 | V76: =IF(V70=0,0,$H$11/26*V$7*IF(OR($G70=0,$G70=1),1,$G70)) -> 0 | W76: =IF(W70=0,0,$H$11/26*W$7*IF(OR($G70=0,$G70=1),1,$G70)) -> 0 | X76: =IF(X70=0,0,$H$11/26*X$7*IF(OR($G70=0,$G70=1),1,$G70)) -> 0 | Y76: =IF(Y70=0,0,$H$11/26*Y$7*IF(OR($G70=0,$G70=1),1,$G70)) -> 0 | Z76: =IF(Z70=0,0,$H$11/26*Z$7*IF(OR($G70=0,$G70=1),1,$G70)) -> 0 | ... AD76: =IF(AD70=0,0,$H$11/26*AD$7*IF(OR($G70=0,$G70=1),1,$G70)) -> 0
A77: =A75 -> Uncheck to Hide | C77: =IF($E$9="CA","",$C$269) -> HEALTH INS. & EMPL. BENEFITS | S77: =IF(OR($E$9="CA",$E$9="CO",$E$9="OR",$E$9="WA"),0,IF($G70=0,0,$G70*$E$7*S$8/2+S72*$CC$6)) -> 0 | T77: =IF(OR($E$9="CA",$E$9="CO",$E$9="OR",$E$9="WA"),0,IF($G70=0,0,$G70*$E$7*T$8/2+T72*$CC$6)) -> 0 | U77: =IF(OR($E$9="CA",$E$9="CO",$E$9="OR",$E$9="WA"),0,IF($G70=0,0,$G70*$E$7*U$8/2+U72*$CC$6)) -> 0 | V77: =IF(OR($E$9="CA",$E$9="CO",$E$9="OR",$E$9="WA"),0,IF($G70=0,0,$G70*$E$7*V$8/2+V72*$CC$6)) -> 0 | W77: =IF(OR($E$9="CA",$E$9="CO",$E$9="OR",$E$9="WA"),0,IF($G70=0,0,$G70*$E$7*W$8/2+W72*$CC$6)) -> 0 | X77: =IF(OR($E$9="CA",$E$9="CO",$E$9="OR",$E$9="WA"),0,IF($G70=0,0,$G70*$E$7*X$8/2+X72*$CC$6)) -> 0 | Y77: =IF(OR($E$9="CA",$E$9="CO",$E$9="OR",$E$9="WA"),0,IF($G70=0,0,$G70*$E$7*Y$8/2+Y72*$CC$6)) -> 0 | Z77: =IF(OR($E$9="CA",$E$9="CO",$E$9="OR",$E$9="WA"),0,IF($G70=0,0,$G70*$E$7*Z$8/2+Z72*$CC$6)) -> 0 | ... AD77: =IF(OR($E$9="CA",$E$9="CO",$E$9="OR",$E$9="WA"),0,IF($G70=0,0,$G70*$E$7*AD$8/2+AD72*$CC$6)) -> 0
A78: =IF(F78+G78+H78+M78=0,"Uncheck to Hide","") -> Uncheck to Hide | B78: =B70 -> 6330-200 LEASING SALARY | C78: Leasing Consultant 5 | I78: 15 | M78: =ROUND(K78*(1+L78),2) -> 0 | P78: =IF(SUM(S79:AD79)>0,1,0) -> 0 | Q78: =M78*N78*52 -> 0 | S78: =IF(S79="",$M78*$N78*2*S$7+$P80*S$7+$O78*$M78*1.5*2*S$7+IF($O$10="Y",(SUMIF($CS$3:$DT$3,S$1,$CS$8:$DT$8)-SUMIF($CS$3:$DT$3,R$1,$CS$8:$DT$8))*($M78*$N78*2*S$7+$P80*S$7+$O78*$M78*1.5*2*S$7)/(S$7*14),0)+IF($O$11="Y",(SUMIF($CS$3:$DT$3,S$1,$CS$8:$DT$8)*CU$11-SUMIF($CS$3:$DT$3,R$1,$CS$8:$DT$8)*CT$11)*($M78*$N78*2*S$7+$P80*S$7+$O78*$M78*1.5*2*S$7)/(S$7*14),0),S79) -> 0 | T78: =IF(T79="",$M78*$N78*2*T$7+$P80*T$7+$O78*$M78*1.5*2*T$7+IF($O$10="Y",(SUMIF($CS$3:$DT$3,T$1,$CS$8:$DT$8)-SUMIF($CS$3:$DT$3,S$1,$CS$8:$DT$8))*($M78*$N78*2*T$7+$P80*T$7+$O78*$M78*1.5*2*T$7)/(T$7*14),0)+IF($O$11="Y",(SUMIF($CS$3:$DT$3,T$1,$CS$8:$DT$8)*CV$11-SUMIF($CS$3:$DT$3,S$1,$CS$8:$DT$8)*CU$11)*($M78*$N78*2*T$7+$P80*T$7+$O78*$M78*1.5*2*T$7)/(T$7*14),0),T79) -> 0 | U78: =IF(U79="",$M78*$N78*2*U$7+$P80*U$7+$O78*$M78*1.5*2*U$7+IF($O$10="Y",(SUMIF($CS$3:$DT$3,U$1,$CS$8:$DT$8)-SUMIF($CS$3:$DT$3,T$1,$CS$8:$DT$8))*($M78*$N78*2*U$7+$P80*U$7+$O78*$M78*1.5*2*U$7)/(U$7*14),0)+IF($O$11="Y",(SUMIF($CS$3:$DT$3,U$1,$CS$8:$DT$8)*CW$11-SUMIF($CS$3:$DT$3,T$1,$CS$8:$DT$8)*CV$11)*($M78*$N78*2*U$7+$P80*U$7+$O78*$M78*1.5*2*U$7)/(U$7*14),0),U79) -> 0 | V78: =IF(V79="",$M78*$N78*2*V$7+$P80*V$7+$O78*$M78*1.5*2*V$7+IF($O$10="Y",(SUMIF($CS$3:$DT$3,V$1,$CS$8:$DT$8)-SUMIF($CS$3:$DT$3,U$1,$CS$8:$DT$8))*($M78*$N78*2*V$7+$P80*V$7+$O78*$M78*1.5*2*V$7)/(V$7*14),0)+IF($O$11="Y",(SUMIF($CS$3:$DT$3,V$1,$CS$8:$DT$8)*CX$11-SUMIF($CS$3:$DT$3,U$1,$CS$8:$DT$8)*CW$11)*($M78*$N78*2*V$7+$P80*V$7+$O78*$M78*1.5*2*V$7)/(V$7*14),0),V79) -> 0 | W78: =IF(W79="",$M78*$N78*2*W$7+$P80*W$7+$O78*$M78*1.5*2*W$7+IF($O$10="Y",(SUMIF($CS$3:$DT$3,W$1,$CS$8:$DT$8)-SUMIF($CS$3:$DT$3,V$1,$CS$8:$DT$8))*($M78*$N78*2*W$7+$P80*W$7+$O78*$M78*1.5*2*W$7)/(W$7*14),0)+IF($O$11="Y",(SUMIF($CS$3:$DT$3,W$1,$CS$8:$DT$8)*CY$11-SUMIF($CS$3:$DT$3,V$1,$CS$8:$DT$8)*CX$11)*($M78*$N78*2*W$7+$P80*W$7+$O78*$M78*1.5*2*W$7)/(W$7*14),0),W79) -> 0 | X78: =IF(X79="",$M78*$N78*2*X$7+$P80*X$7+$O78*$M78*1.5*2*X$7+IF($O$10="Y",(SUMIF($CS$3:$DT$3,X$1,$CS$8:$DT$8)-SUMIF($CS$3:$DT$3,W$1,$CS$8:$DT$8))*($M78*$N78*2*X$7+$P80*X$7+$O78*$M78*1.5*2*X$7)/(X$7*14),0)+IF($O$11="Y",(SUMIF($CS$3:$DT$3,X$1,$CS$8:$DT$8)*CZ$11-SUMIF($CS$3:$DT$3,W$1,$CS$8:$DT$8)*CY$11)*($M78*$N78*2*X$7+$P80*X$7+$O78*$M78*1.5*2*X$7)/(X$7*14),0),X79) -> 0 | Y78: =IF(Y79="",$M78*$N78*2*Y$7+$P80*Y$7+$O78*$M78*1.5*2*Y$7+IF($O$10="Y",(SUMIF($CS$3:$DT$3,Y$1,$CS$8:$DT$8)-SUMIF($CS$3:$DT$3,X$1,$CS$8:$DT$8))*($M78*$N78*2*Y$7+$P80*Y$7+$O78*$M78*1.5*2*Y$7)/(Y$7*14),0)+IF($O$11="Y",(SUMIF($CS$3:$DT$3,Y$1,$CS$8:$DT$8)*DA$11-SUMIF($CS$3:$DT$3,X$1,$CS$8:$DT$8)*CZ$11)*($M78*$N78*2*Y$7+$P80*Y$7+$O78*$M78*1.5*2*Y$7)/(Y$7*14),0),Y79) -> 0 | Z78: =IF(Z79="",$M78*$N78*2*Z$7+$P80*Z$7+$O78*$M78*1.5*2*Z$7+IF($O$10="Y",(SUMIF($CS$3:$DT$3,Z$1,$CS$8:$DT$8)-SUMIF($CS$3:$DT$3,Y$1,$CS$8:$DT$8))*($M78*$N78*2*Z$7+$P80*Z$7+$O78*$M78*1.5*2*Z$7)/(Z$7*14),0)+IF($O$11="Y",(SUMIF($CS$3:$DT$3,Z$1,$CS$8:$DT$8)*DB$11-SUMIF($CS$3:$DT$3,Y$1,$CS$8:$DT$8)*DA$11)*($M78*$N78*2*Z$7+$P80*Z$7+$O78*$M78*1.5*2*Z$7)/(Z$7*14),0),Z79) -> 0 | ... AD78: =IF(AD79="",$M78*$N78*2*AD$7+$P80*AD$7+$O78*$M78*1.5*2*AD$7+IF($O$10="Y",(SUMIF($CS$3:$DT$3,AD$1,$CS$8:$DT$8)-SUMIF($CS$3:$DT$3,AC$1,$CS$8:$DT$8))*($M78*$N78*2*AD$7+$P80*AD$7+$O78*$M78*1.5*2*AD$7)/(AD$7*14),0)+IF($O$11="Y",(SUMIF($CS$3:$DT$3,AD$1,$CS$8:$DT$8)*DF$11-SUMIF($CS$3:$DT$3,AC$1,$CS$8:$DT$8)*DE$11)*($M78*$N78*2*AD$7+$P80*AD$7+$O78*$M78*1.5*2*AD$7)/(AD$7*14),0),AD79) -> 0 | AE78: =SUM(S78:AD78) -> 0
A79: =A78 -> Uncheck to Hide | AG79: =IF(AE78=0,0,1) -> 0 | AH79: =IF(AG79=0,"",IF($AG$46>1,", 1 at "," at ")&"$"&ROUND(M78,2)&"/hour, working "&N78&" hours per week with"&IF(E78>0," housing","out housing"))
A80: Do not check this box | P80: =+M78*N78*R78/AE$7 -> 0 | S80: =IF(S79>0,S79-$P80*S$7,+S78-$P80*S$7) -> 0 | T80: =IF(T79>0,T79-$P80*T$7,+T78-$P80*T$7) -> 0 | U80: =IF(U79>0,U79-$P80*U$7,+U78-$P80*U$7) -> 0 | V80: =IF(V79>0,V79-$P80*V$7,+V78-$P80*V$7) -> 0 | W80: =IF(W79>0,W79-$P80*W$7,+W78-$P80*W$7) -> 0 | X80: =IF(X79>0,X79-$P80*X$7,+X78-$P80*X$7) -> 0 | Y80: =IF(Y79>0,Y79-$P80*Y$7,+Y78-$P80*Y$7) -> 0 | Z80: =IF(Z79>0,Z79-$P80*Z$7,+Z78-$P80*Z$7) -> 0 | ... AD80: =IF(AD79>0,AD79-$P80*AD$7,+AD78-$P80*AD$7) -> 0
A81: Do not check this box | S81: =+S80 -> 0 | T81: =+T80+S81 -> 0 | U81: =+U80+T81 -> 0 | V81: =+V80+U81 -> 0 | W81: =+W80+V81 -> 0 | X81: =+X80+W81 -> 0 | Y81: =+Y80+X81 -> 0 | Z81: =+Z80+Y81 -> 0 | AA81: =+AA80+Z81 -> 0 | ... AD81: =+AD80+AC81 -> 0
A82: =A79 -> Uncheck to Hide | C82: Payroll Tax | S82: =IF($E$9="CA",IF(R81<7000,$E$5*S80,($E$5-0.043)*S80),IF($E$9="IL",IF(R81<12960,$E$5*S80,($E$5-0.04125)*S80),IF($E$9="PA",IF(R81<10000,$E$5*S80,($E$5-0.071)*S80),IF($E$9="TX",IF(R81<9000,$E$5*S80,($E$5-0.0363)*S80),$E$5*S80)))) -> 0 | T82: =IF($E$9="CA",IF(S81<7000,$E$5*T80,($E$5-0.043)*T80),IF($E$9="IL",IF(S81<12960,$E$5*T80,($E$5-0.04125)*T80),IF($E$9="PA",IF(S81<10000,$E$5*T80,($E$5-0.071)*T80),IF($E$9="TX",IF(S81<9000,$E$5*T80,($E$5-0.0363)*T80),$E$5*T80)))) -> 0 | U82: =IF($E$9="CA",IF(T81<7000,$E$5*U80,($E$5-0.043)*U80),IF($E$9="IL",IF(T81<12960,$E$5*U80,($E$5-0.04125)*U80),IF($E$9="PA",IF(T81<10000,$E$5*U80,($E$5-0.071)*U80),IF($E$9="TX",IF(T81<9000,$E$5*U80,($E$5-0.0363)*U80),$E$5*U80)))) -> 0 | V82: =IF($E$9="CA",IF(U81<7000,$E$5*V80,($E$5-0.043)*V80),IF($E$9="IL",IF(U81<12960,$E$5*V80,($E$5-0.04125)*V80),IF($E$9="PA",IF(U81<10000,$E$5*V80,($E$5-0.071)*V80),IF($E$9="TX",IF(U81<9000,$E$5*V80,($E$5-0.0363)*V80),$E$5*V80)))) -> 0 | W82: =IF($E$9="CA",IF(V81<7000,$E$5*W80,($E$5-0.043)*W80),IF($E$9="IL",IF(V81<12960,$E$5*W80,($E$5-0.04125)*W80),IF($E$9="PA",IF(V81<10000,$E$5*W80,($E$5-0.071)*W80),IF($E$9="TX",IF(V81<9000,$E$5*W80,($E$5-0.0363)*W80),$E$5*W80)))) -> 0 | X82: =IF($E$9="CA",IF(W81<7000,$E$5*X80,($E$5-0.043)*X80),IF($E$9="IL",IF(W81<12960,$E$5*X80,($E$5-0.04125)*X80),IF($E$9="PA",IF(W81<10000,$E$5*X80,($E$5-0.071)*X80),IF($E$9="TX",IF(W81<9000,$E$5*X80,($E$5-0.0363)*X80),$E$5*X80)))) -> 0 | Y82: =IF($E$9="CA",IF(X81<7000,$E$5*Y80,($E$5-0.043)*Y80),IF($E$9="IL",IF(X81<12960,$E$5*Y80,($E$5-0.04125)*Y80),IF($E$9="PA",IF(X81<10000,$E$5*Y80,($E$5-0.071)*Y80),IF($E$9="TX",IF(X81<9000,$E$5*Y80,($E$5-0.0363)*Y80),$E$5*Y80)))) -> 0 | Z82: =IF($E$9="CA",IF(Y81<7000,$E$5*Z80,($E$5-0.043)*Z80),IF($E$9="IL",IF(Y81<12960,$E$5*Z80,($E$5-0.04125)*Z80),IF($E$9="PA",IF(Y81<10000,$E$5*Z80,($E$5-0.071)*Z80),IF($E$9="TX",IF(Y81<9000,$E$5*Z80,($E$5-0.0363)*Z80),$E$5*Z80)))) -> 0 | ... AD82: =IF($E$9="CA",IF(AC81<7000,$E$5*AD80,($E$5-0.043)*AD80),IF($E$9="IL",IF(AC81<12960,$E$5*AD80,($E$5-0.04125)*AD80),IF($E$9="PA",IF(AC81<10000,$E$5*AD80,($E$5-0.071)*AD80),IF($E$9="TX",IF(AC81<9000,$E$5*AD80,($E$5-0.0363)*AD80),$E$5*AD80)))) -> 0
A83: =A82 -> Uncheck to Hide | C83: Workman's Comp | S83: =IF($E$9="WA",IF(S$1<$G$6,$E$6*$N78*2*S$7+$CA$5*S80,$F$6*$N78*2*S$7+$CA$5*S80),IF($E$9="NV",IF(R81>36000,0,IF(S$1<$G$6,$E$6*S80,$F$6*S80)),IF(S$1<$G$6,$E$6*S80,$F$6*S80))) -> 0 | T83: =IF($E$9="WA",IF(T$1<$G$6,$E$6*$N78*2*T$7+$CA$5*T80,$F$6*$N78*2*T$7+$CA$5*T80),IF($E$9="NV",IF(S81>36000,0,IF(T$1<$G$6,$E$6*T80,$F$6*T80)),IF(T$1<$G$6,$E$6*T80,$F$6*T80))) -> 0 | U83: =IF($E$9="WA",IF(U$1<$G$6,$E$6*$N78*2*U$7+$CA$5*U80,$F$6*$N78*2*U$7+$CA$5*U80),IF($E$9="NV",IF(T81>36000,0,IF(U$1<$G$6,$E$6*U80,$F$6*U80)),IF(U$1<$G$6,$E$6*U80,$F$6*U80))) -> 0 | V83: =IF($E$9="WA",IF(V$1<$G$6,$E$6*$N78*2*V$7+$CA$5*V80,$F$6*$N78*2*V$7+$CA$5*V80),IF($E$9="NV",IF(U81>36000,0,IF(V$1<$G$6,$E$6*V80,$F$6*V80)),IF(V$1<$G$6,$E$6*V80,$F$6*V80))) -> 0 | W83: =IF($E$9="WA",IF(W$1<$G$6,$E$6*$N78*2*W$7+$CA$5*W80,$F$6*$N78*2*W$7+$CA$5*W80),IF($E$9="NV",IF(V81>36000,0,IF(W$1<$G$6,$E$6*W80,$F$6*W80)),IF(W$1<$G$6,$E$6*W80,$F$6*W80))) -> 0 | X83: =IF($E$9="WA",IF(X$1<$G$6,$E$6*$N78*2*X$7+$CA$5*X80,$F$6*$N78*2*X$7+$CA$5*X80),IF($E$9="NV",IF(W81>36000,0,IF(X$1<$G$6,$E$6*X80,$F$6*X80)),IF(X$1<$G$6,$E$6*X80,$F$6*X80))) -> 0 | Y83: =IF($E$9="WA",IF(Y$1<$G$6,$E$6*$N78*2*Y$7+$CA$5*Y80,$F$6*$N78*2*Y$7+$CA$5*Y80),IF($E$9="NV",IF(X81>36000,0,IF(Y$1<$G$6,$E$6*Y80,$F$6*Y80)),IF(Y$1<$G$6,$E$6*Y80,$F$6*Y80))) -> 0 | Z83: =IF($E$9="WA",IF(Z$1<$G$6,$E$6*$N78*2*Z$7+$CA$5*Z80,$F$6*$N78*2*Z$7+$CA$5*Z80),IF($E$9="NV",IF(Y81>36000,0,IF(Z$1<$G$6,$E$6*Z80,$F$6*Z80)),IF(Z$1<$G$6,$E$6*Z80,$F$6*Z80))) -> 0 | ... AD83: =IF($E$9="WA",IF(AD$1<$G$6,$E$6*$N78*2*AD$7+$CA$5*AD80,$F$6*$N78*2*AD$7+$CA$5*AD80),IF($E$9="NV",IF(AC81>36000,0,IF(AD$1<$G$6,$E$6*AD80,$F$6*AD80)),IF(AD$1<$G$6,$E$6*AD80,$F$6*AD80))) -> 0
A84: =A83 -> Uncheck to Hide | C84: 401K Match | S84: =IF(S78=0,0,$H$11/26*S$7*IF(OR($G78=0,$G78=1),1,$G78)) -> 0 | T84: =IF(T78=0,0,$H$11/26*T$7*IF(OR($G78=0,$G78=1),1,$G78)) -> 0 | U84: =IF(U78=0,0,$H$11/26*U$7*IF(OR($G78=0,$G78=1),1,$G78)) -> 0 | V84: =IF(V78=0,0,$H$11/26*V$7*IF(OR($G78=0,$G78=1),1,$G78)) -> 0 | W84: =IF(W78=0,0,$H$11/26*W$7*IF(OR($G78=0,$G78=1),1,$G78)) -> 0 | X84: =IF(X78=0,0,$H$11/26*X$7*IF(OR($G78=0,$G78=1),1,$G78)) -> 0 | Y84: =IF(Y78=0,0,$H$11/26*Y$7*IF(OR($G78=0,$G78=1),1,$G78)) -> 0 | Z84: =IF(Z78=0,0,$H$11/26*Z$7*IF(OR($G78=0,$G78=1),1,$G78)) -> 0 | ... AD84: =IF(AD78=0,0,$H$11/26*AD$7*IF(OR($G78=0,$G78=1),1,$G78)) -> 0
A85: =A83 -> Uncheck to Hide | C85: =IF($E$9="CA","",$C$269) -> HEALTH INS. & EMPL. BENEFITS | S85: =IF(OR($E$9="CA",$E$9="CO",$E$9="OR",$E$9="WA"),0,IF($G78=0,0,$G78*$E$7*S$8/2+S80*$CC$6)) -> 0 | T85: =IF(OR($E$9="CA",$E$9="CO",$E$9="OR",$E$9="WA"),0,IF($G78=0,0,$G78*$E$7*T$8/2+T80*$CC$6)) -> 0 | U85: =IF(OR($E$9="CA",$E$9="CO",$E$9="OR",$E$9="WA"),0,IF($G78=0,0,$G78*$E$7*U$8/2+U80*$CC$6)) -> 0 | V85: =IF(OR($E$9="CA",$E$9="CO",$E$9="OR",$E$9="WA"),0,IF($G78=0,0,$G78*$E$7*V$8/2+V80*$CC$6)) -> 0 | W85: =IF(OR($E$9="CA",$E$9="CO",$E$9="OR",$E$9="WA"),0,IF($G78=0,0,$G78*$E$7*W$8/2+W80*$CC$6)) -> 0 | X85: =IF(OR($E$9="CA",$E$9="CO",$E$9="OR",$E$9="WA"),0,IF($G78=0,0,$G78*$E$7*X$8/2+X80*$CC$6)) -> 0 | Y85: =IF(OR($E$9="CA",$E$9="CO",$E$9="OR",$E$9="WA"),0,IF($G78=0,0,$G78*$E$7*Y$8/2+Y80*$CC$6)) -> 0 | Z85: =IF(OR($E$9="CA",$E$9="CO",$E$9="OR",$E$9="WA"),0,IF($G78=0,0,$G78*$E$7*Z$8/2+Z80*$CC$6)) -> 0 | ... AD85: =IF(OR($E$9="CA",$E$9="CO",$E$9="OR",$E$9="WA"),0,IF($G78=0,0,$G78*$E$7*AD$8/2+AD80*$CC$6)) -> 0
A86: =IF(F86+G86+H86+M86=0,"Uncheck to Hide","") -> Uncheck to Hide | B86: =B78 -> 6330-200 LEASING SALARY | C86: Leasing Consultant 6 | I86: 15 | M86: =ROUND(K86*(1+L86),2) -> 0 | P86: =IF(SUM(S87:AD87)>0,1,0) -> 0 | Q86: =M86*N86*52 -> 0 | S86: =IF(S87="",$M86*$N86*2*S$7+$P88*S$7+$O86*$M86*1.5*2*S$7+IF($O$10="Y",(SUMIF($CS$3:$DT$3,S$1,$CS$8:$DT$8)-SUMIF($CS$3:$DT$3,R$1,$CS$8:$DT$8))*($M86*$N86*2*S$7+$P88*S$7+$O86*$M86*1.5*2*S$7)/(S$7*14),0)+IF($O$11="Y",(SUMIF($CS$3:$DT$3,S$1,$CS$8:$DT$8)*CU$11-SUMIF($CS$3:$DT$3,R$1,$CS$8:$DT$8)*CT$11)*($M86*$N86*2*S$7+$P88*S$7+$O86*$M86*1.5*2*S$7)/(S$7*14),0),S87) -> 0 | T86: =IF(T87="",$M86*$N86*2*T$7+$P88*T$7+$O86*$M86*1.5*2*T$7+IF($O$10="Y",(SUMIF($CS$3:$DT$3,T$1,$CS$8:$DT$8)-SUMIF($CS$3:$DT$3,S$1,$CS$8:$DT$8))*($M86*$N86*2*T$7+$P88*T$7+$O86*$M86*1.5*2*T$7)/(T$7*14),0)+IF($O$11="Y",(SUMIF($CS$3:$DT$3,T$1,$CS$8:$DT$8)*CV$11-SUMIF($CS$3:$DT$3,S$1,$CS$8:$DT$8)*CU$11)*($M86*$N86*2*T$7+$P88*T$7+$O86*$M86*1.5*2*T$7)/(T$7*14),0),T87) -> 0 | U86: =IF(U87="",$M86*$N86*2*U$7+$P88*U$7+$O86*$M86*1.5*2*U$7+IF($O$10="Y",(SUMIF($CS$3:$DT$3,U$1,$CS$8:$DT$8)-SUMIF($CS$3:$DT$3,T$1,$CS$8:$DT$8))*($M86*$N86*2*U$7+$P88*U$7+$O86*$M86*1.5*2*U$7)/(U$7*14),0)+IF($O$11="Y",(SUMIF($CS$3:$DT$3,U$1,$CS$8:$DT$8)*CW$11-SUMIF($CS$3:$DT$3,T$1,$CS$8:$DT$8)*CV$11)*($M86*$N86*2*U$7+$P88*U$7+$O86*$M86*1.5*2*U$7)/(U$7*14),0),U87) -> 0 | V86: =IF(V87="",$M86*$N86*2*V$7+$P88*V$7+$O86*$M86*1.5*2*V$7+IF($O$10="Y",(SUMIF($CS$3:$DT$3,V$1,$CS$8:$DT$8)-SUMIF($CS$3:$DT$3,U$1,$CS$8:$DT$8))*($M86*$N86*2*V$7+$P88*V$7+$O86*$M86*1.5*2*V$7)/(V$7*14),0)+IF($O$11="Y",(SUMIF($CS$3:$DT$3,V$1,$CS$8:$DT$8)*CX$11-SUMIF($CS$3:$DT$3,U$1,$CS$8:$DT$8)*CW$11)*($M86*$N86*2*V$7+$P88*V$7+$O86*$M86*1.5*2*V$7)/(V$7*14),0),V87) -> 0 | W86: =IF(W87="",$M86*$N86*2*W$7+$P88*W$7+$O86*$M86*1.5*2*W$7+IF($O$10="Y",(SUMIF($CS$3:$DT$3,W$1,$CS$8:$DT$8)-SUMIF($CS$3:$DT$3,V$1,$CS$8:$DT$8))*($M86*$N86*2*W$7+$P88*W$7+$O86*$M86*1.5*2*W$7)/(W$7*14),0)+IF($O$11="Y",(SUMIF($CS$3:$DT$3,W$1,$CS$8:$DT$8)*CY$11-SUMIF($CS$3:$DT$3,V$1,$CS$8:$DT$8)*CX$11)*($M86*$N86*2*W$7+$P88*W$7+$O86*$M86*1.5*2*W$7)/(W$7*14),0),W87) -> 0 | X86: =IF(X87="",$M86*$N86*2*X$7+$P88*X$7+$O86*$M86*1.5*2*X$7+IF($O$10="Y",(SUMIF($CS$3:$DT$3,X$1,$CS$8:$DT$8)-SUMIF($CS$3:$DT$3,W$1,$CS$8:$DT$8))*($M86*$N86*2*X$7+$P88*X$7+$O86*$M86*1.5*2*X$7)/(X$7*14),0)+IF($O$11="Y",(SUMIF($CS$3:$DT$3,X$1,$CS$8:$DT$8)*CZ$11-SUMIF($CS$3:$DT$3,W$1,$CS$8:$DT$8)*CY$11)*($M86*$N86*2*X$7+$P88*X$7+$O86*$M86*1.5*2*X$7)/(X$7*14),0),X87) -> 0 | Y86: =IF(Y87="",$M86*$N86*2*Y$7+$P88*Y$7+$O86*$M86*1.5*2*Y$7+IF($O$10="Y",(SUMIF($CS$3:$DT$3,Y$1,$CS$8:$DT$8)-SUMIF($CS$3:$DT$3,X$1,$CS$8:$DT$8))*($M86*$N86*2*Y$7+$P88*Y$7+$O86*$M86*1.5*2*Y$7)/(Y$7*14),0)+IF($O$11="Y",(SUMIF($CS$3:$DT$3,Y$1,$CS$8:$DT$8)*DA$11-SUMIF($CS$3:$DT$3,X$1,$CS$8:$DT$8)*CZ$11)*($M86*$N86*2*Y$7+$P88*Y$7+$O86*$M86*1.5*2*Y$7)/(Y$7*14),0),Y87) -> 0 | Z86: =IF(Z87="",$M86*$N86*2*Z$7+$P88*Z$7+$O86*$M86*1.5*2*Z$7+IF($O$10="Y",(SUMIF($CS$3:$DT$3,Z$1,$CS$8:$DT$8)-SUMIF($CS$3:$DT$3,Y$1,$CS$8:$DT$8))*($M86*$N86*2*Z$7+$P88*Z$7+$O86*$M86*1.5*2*Z$7)/(Z$7*14),0)+IF($O$11="Y",(SUMIF($CS$3:$DT$3,Z$1,$CS$8:$DT$8)*DB$11-SUMIF($CS$3:$DT$3,Y$1,$CS$8:$DT$8)*DA$11)*($M86*$N86*2*Z$7+$P88*Z$7+$O86*$M86*1.5*2*Z$7)/(Z$7*14),0),Z87) -> 0 | ... AD86: =IF(AD87="",$M86*$N86*2*AD$7+$P88*AD$7+$O86*$M86*1.5*2*AD$7+IF($O$10="Y",(SUMIF($CS$3:$DT$3,AD$1,$CS$8:$DT$8)-SUMIF($CS$3:$DT$3,AC$1,$CS$8:$DT$8))*($M86*$N86*2*AD$7+$P88*AD$7+$O86*$M86*1.5*2*AD$7)/(AD$7*14),0)+IF($O$11="Y",(SUMIF($CS$3:$DT$3,AD$1,$CS$8:$DT$8)*DF$11-SUMIF($CS$3:$DT$3,AC$1,$CS$8:$DT$8)*DE$11)*($M86*$N86*2*AD$7+$P88*AD$7+$O86*$M86*1.5*2*AD$7)/(AD$7*14),0),AD87) -> 0 | AE86: =SUM(S86:AD86) -> 0
A87: =A86 -> Uncheck to Hide | AG87: =IF(AE86=0,0,1) -> 0 | AH87: =IF(AG87=0,"",IF($AG$46>1,", 1 at "," at ")&"$"&ROUND(M86,2)&"/hour, working "&N86&" hours per week with"&IF(E86>0," housing","out housing"))
A88: Do not check this box | P88: =+M86*N86*R86/AE$7 -> 0 | S88: =IF(S87>0,S87-$P88*S$7,+S86-$P88*S$7) -> 0 | T88: =IF(T87>0,T87-$P88*T$7,+T86-$P88*T$7) -> 0 | U88: =IF(U87>0,U87-$P88*U$7,+U86-$P88*U$7) -> 0 | V88: =IF(V87>0,V87-$P88*V$7,+V86-$P88*V$7) -> 0 | W88: =IF(W87>0,W87-$P88*W$7,+W86-$P88*W$7) -> 0 | X88: =IF(X87>0,X87-$P88*X$7,+X86-$P88*X$7) -> 0 | Y88: =IF(Y87>0,Y87-$P88*Y$7,+Y86-$P88*Y$7) -> 0 | Z88: =IF(Z87>0,Z87-$P88*Z$7,+Z86-$P88*Z$7) -> 0 | ... AD88: =IF(AD87>0,AD87-$P88*AD$7,+AD86-$P88*AD$7) -> 0
A89: Do not check this box | S89: =+S88 -> 0 | T89: =+T88+S89 -> 0 | U89: =+U88+T89 -> 0 | V89: =+V88+U89 -> 0 | W89: =+W88+V89 -> 0 | X89: =+X88+W89 -> 0 | Y89: =+Y88+X89 -> 0 | Z89: =+Z88+Y89 -> 0 | AA89: =+AA88+Z89 -> 0 | ... AD89: =+AD88+AC89 -> 0
A90: =A87 -> Uncheck to Hide | C90: Payroll Tax | S90: =IF($E$9="CA",IF(R89<7000,$E$5*S88,($E$5-0.043)*S88),IF($E$9="IL",IF(R89<12960,$E$5*S88,($E$5-0.04125)*S88),IF($E$9="PA",IF(R89<10000,$E$5*S88,($E$5-0.071)*S88),IF($E$9="TX",IF(R89<9000,$E$5*S88,($E$5-0.0363)*S88),$E$5*S88)))) -> 0 | T90: =IF($E$9="CA",IF(S89<7000,$E$5*T88,($E$5-0.043)*T88),IF($E$9="IL",IF(S89<12960,$E$5*T88,($E$5-0.04125)*T88),IF($E$9="PA",IF(S89<10000,$E$5*T88,($E$5-0.071)*T88),IF($E$9="TX",IF(S89<9000,$E$5*T88,($E$5-0.0363)*T88),$E$5*T88)))) -> 0 | U90: =IF($E$9="CA",IF(T89<7000,$E$5*U88,($E$5-0.043)*U88),IF($E$9="IL",IF(T89<12960,$E$5*U88,($E$5-0.04125)*U88),IF($E$9="PA",IF(T89<10000,$E$5*U88,($E$5-0.071)*U88),IF($E$9="TX",IF(T89<9000,$E$5*U88,($E$5-0.0363)*U88),$E$5*U88)))) -> 0 | V90: =IF($E$9="CA",IF(U89<7000,$E$5*V88,($E$5-0.043)*V88),IF($E$9="IL",IF(U89<12960,$E$5*V88,($E$5-0.04125)*V88),IF($E$9="PA",IF(U89<10000,$E$5*V88,($E$5-0.071)*V88),IF($E$9="TX",IF(U89<9000,$E$5*V88,($E$5-0.0363)*V88),$E$5*V88)))) -> 0 | W90: =IF($E$9="CA",IF(V89<7000,$E$5*W88,($E$5-0.043)*W88),IF($E$9="IL",IF(V89<12960,$E$5*W88,($E$5-0.04125)*W88),IF($E$9="PA",IF(V89<10000,$E$5*W88,($E$5-0.071)*W88),IF($E$9="TX",IF(V89<9000,$E$5*W88,($E$5-0.0363)*W88),$E$5*W88)))) -> 0 | X90: =IF($E$9="CA",IF(W89<7000,$E$5*X88,($E$5-0.043)*X88),IF($E$9="IL",IF(W89<12960,$E$5*X88,($E$5-0.04125)*X88),IF($E$9="PA",IF(W89<10000,$E$5*X88,($E$5-0.071)*X88),IF($E$9="TX",IF(W89<9000,$E$5*X88,($E$5-0.0363)*X88),$E$5*X88)))) -> 0 | Y90: =IF($E$9="CA",IF(X89<7000,$E$5*Y88,($E$5-0.043)*Y88),IF($E$9="IL",IF(X89<12960,$E$5*Y88,($E$5-0.04125)*Y88),IF($E$9="PA",IF(X89<10000,$E$5*Y88,($E$5-0.071)*Y88),IF($E$9="TX",IF(X89<9000,$E$5*Y88,($E$5-0.0363)*Y88),$E$5*Y88)))) -> 0 | Z90: =IF($E$9="CA",IF(Y89<7000,$E$5*Z88,($E$5-0.043)*Z88),IF($E$9="IL",IF(Y89<12960,$E$5*Z88,($E$5-0.04125)*Z88),IF($E$9="PA",IF(Y89<10000,$E$5*Z88,($E$5-0.071)*Z88),IF($E$9="TX",IF(Y89<9000,$E$5*Z88,($E$5-0.0363)*Z88),$E$5*Z88)))) -> 0 | ... AD90: =IF($E$9="CA",IF(AC89<7000,$E$5*AD88,($E$5-0.043)*AD88),IF($E$9="IL",IF(AC89<12960,$E$5*AD88,($E$5-0.04125)*AD88),IF($E$9="PA",IF(AC89<10000,$E$5*AD88,($E$5-0.071)*AD88),IF($E$9="TX",IF(AC89<9000,$E$5*AD88,($E$5-0.0363)*AD88),$E$5*AD88)))) -> 0
A91: =A90 -> Uncheck to Hide | C91: Workman's Comp | S91: =IF($E$9="WA",IF(S$1<$G$6,$E$6*$N86*2*S$7+$CA$5*S88,$F$6*$N86*2*S$7+$CA$5*S88),IF($E$9="NV",IF(R89>36000,0,IF(S$1<$G$6,$E$6*S88,$F$6*S88)),IF(S$1<$G$6,$E$6*S88,$F$6*S88))) -> 0 | T91: =IF($E$9="WA",IF(T$1<$G$6,$E$6*$N86*2*T$7+$CA$5*T88,$F$6*$N86*2*T$7+$CA$5*T88),IF($E$9="NV",IF(S89>36000,0,IF(T$1<$G$6,$E$6*T88,$F$6*T88)),IF(T$1<$G$6,$E$6*T88,$F$6*T88))) -> 0 | U91: =IF($E$9="WA",IF(U$1<$G$6,$E$6*$N86*2*U$7+$CA$5*U88,$F$6*$N86*2*U$7+$CA$5*U88),IF($E$9="NV",IF(T89>36000,0,IF(U$1<$G$6,$E$6*U88,$F$6*U88)),IF(U$1<$G$6,$E$6*U88,$F$6*U88))) -> 0 | V91: =IF($E$9="WA",IF(V$1<$G$6,$E$6*$N86*2*V$7+$CA$5*V88,$F$6*$N86*2*V$7+$CA$5*V88),IF($E$9="NV",IF(U89>36000,0,IF(V$1<$G$6,$E$6*V88,$F$6*V88)),IF(V$1<$G$6,$E$6*V88,$F$6*V88))) -> 0 | W91: =IF($E$9="WA",IF(W$1<$G$6,$E$6*$N86*2*W$7+$CA$5*W88,$F$6*$N86*2*W$7+$CA$5*W88),IF($E$9="NV",IF(V89>36000,0,IF(W$1<$G$6,$E$6*W88,$F$6*W88)),IF(W$1<$G$6,$E$6*W88,$F$6*W88))) -> 0 | X91: =IF($E$9="WA",IF(X$1<$G$6,$E$6*$N86*2*X$7+$CA$5*X88,$F$6*$N86*2*X$7+$CA$5*X88),IF($E$9="NV",IF(W89>36000,0,IF(X$1<$G$6,$E$6*X88,$F$6*X88)),IF(X$1<$G$6,$E$6*X88,$F$6*X88))) -> 0 | Y91: =IF($E$9="WA",IF(Y$1<$G$6,$E$6*$N86*2*Y$7+$CA$5*Y88,$F$6*$N86*2*Y$7+$CA$5*Y88),IF($E$9="NV",IF(X89>36000,0,IF(Y$1<$G$6,$E$6*Y88,$F$6*Y88)),IF(Y$1<$G$6,$E$6*Y88,$F$6*Y88))) -> 0 | Z91: =IF($E$9="WA",IF(Z$1<$G$6,$E$6*$N86*2*Z$7+$CA$5*Z88,$F$6*$N86*2*Z$7+$CA$5*Z88),IF($E$9="NV",IF(Y89>36000,0,IF(Z$1<$G$6,$E$6*Z88,$F$6*Z88)),IF(Z$1<$G$6,$E$6*Z88,$F$6*Z88))) -> 0 | ... AD91: =IF($E$9="WA",IF(AD$1<$G$6,$E$6*$N86*2*AD$7+$CA$5*AD88,$F$6*$N86*2*AD$7+$CA$5*AD88),IF($E$9="NV",IF(AC89>36000,0,IF(AD$1<$G$6,$E$6*AD88,$F$6*AD88)),IF(AD$1<$G$6,$E$6*AD88,$F$6*AD88))) -> 0
A92: =A91 -> Uncheck to Hide | C92: 401K Match | S92: =IF(S86=0,0,$H$11/26*S$7*IF(OR($G86=0,$G86=1),1,$G86)) -> 0 | T92: =IF(T86=0,0,$H$11/26*T$7*IF(OR($G86=0,$G86=1),1,$G86)) -> 0 | U92: =IF(U86=0,0,$H$11/26*U$7*IF(OR($G86=0,$G86=1),1,$G86)) -> 0 | V92: =IF(V86=0,0,$H$11/26*V$7*IF(OR($G86=0,$G86=1),1,$G86)) -> 0 | W92: =IF(W86=0,0,$H$11/26*W$7*IF(OR($G86=0,$G86=1),1,$G86)) -> 0 | X92: =IF(X86=0,0,$H$11/26*X$7*IF(OR($G86=0,$G86=1),1,$G86)) -> 0 | Y92: =IF(Y86=0,0,$H$11/26*Y$7*IF(OR($G86=0,$G86=1),1,$G86)) -> 0 | Z92: =IF(Z86=0,0,$H$11/26*Z$7*IF(OR($G86=0,$G86=1),1,$G86)) -> 0 | ... AD92: =IF(AD86=0,0,$H$11/26*AD$7*IF(OR($G86=0,$G86=1),1,$G86)) -> 0
A93: =A91 -> Uncheck to Hide | C93: =IF($E$9="CA","",$C$269) -> HEALTH INS. & EMPL. BENEFITS | S93: =IF(OR($E$9="CA",$E$9="CO",$E$9="OR",$E$9="WA"),0,IF($G86=0,0,$G86*$E$7*S$8/2+S88*$CC$6)) -> 0 | T93: =IF(OR($E$9="CA",$E$9="CO",$E$9="OR",$E$9="WA"),0,IF($G86=0,0,$G86*$E$7*T$8/2+T88*$CC$6)) -> 0 | U93: =IF(OR($E$9="CA",$E$9="CO",$E$9="OR",$E$9="WA"),0,IF($G86=0,0,$G86*$E$7*U$8/2+U88*$CC$6)) -> 0 | V93: =IF(OR($E$9="CA",$E$9="CO",$E$9="OR",$E$9="WA"),0,IF($G86=0,0,$G86*$E$7*V$8/2+V88*$CC$6)) -> 0 | W93: =IF(OR($E$9="CA",$E$9="CO",$E$9="OR",$E$9="WA"),0,IF($G86=0,0,$G86*$E$7*W$8/2+W88*$CC$6)) -> 0 | X93: =IF(OR($E$9="CA",$E$9="CO",$E$9="OR",$E$9="WA"),0,IF($G86=0,0,$G86*$E$7*X$8/2+X88*$CC$6)) -> 0 | Y93: =IF(OR($E$9="CA",$E$9="CO",$E$9="OR",$E$9="WA"),0,IF($G86=0,0,$G86*$E$7*Y$8/2+Y88*$CC$6)) -> 0 | Z93: =IF(OR($E$9="CA",$E$9="CO",$E$9="OR",$E$9="WA"),0,IF($G86=0,0,$G86*$E$7*Z$8/2+Z88*$CC$6)) -> 0 | ... AD93: =IF(OR($E$9="CA",$E$9="CO",$E$9="OR",$E$9="WA"),0,IF($G86=0,0,$G86*$E$7*AD$8/2+AD88*$CC$6)) -> 0
A94: =IF(F94+G94+H94+M94=0,"Uncheck to Hide","") -> Uncheck to Hide | B94: =B86 -> 6330-200 LEASING SALARY | C94: Leasing Consultant 7 | I94: 15 | M94: =ROUND(K94*(1+L94),2) -> 0 | P94: =IF(SUM(S95:AD95)>0,1,0) -> 0 | Q94: =M94*N94*52 -> 0 | S94: =IF(S95="",$M94*$N94*2*S$7+$P96*S$7+$O94*$M94*1.5*2*S$7+IF($O$10="Y",(SUMIF($CS$3:$DT$3,S$1,$CS$8:$DT$8)-SUMIF($CS$3:$DT$3,R$1,$CS$8:$DT$8))*($M94*$N94*2*S$7+$P96*S$7+$O94*$M94*1.5*2*S$7)/(S$7*14),0)+IF($O$11="Y",(SUMIF($CS$3:$DT$3,S$1,$CS$8:$DT$8)*CU$11-SUMIF($CS$3:$DT$3,R$1,$CS$8:$DT$8)*CT$11)*($M94*$N94*2*S$7+$P96*S$7+$O94*$M94*1.5*2*S$7)/(S$7*14),0),S95) -> 0 | T94: =IF(T95="",$M94*$N94*2*T$7+$P96*T$7+$O94*$M94*1.5*2*T$7+IF($O$10="Y",(SUMIF($CS$3:$DT$3,T$1,$CS$8:$DT$8)-SUMIF($CS$3:$DT$3,S$1,$CS$8:$DT$8))*($M94*$N94*2*T$7+$P96*T$7+$O94*$M94*1.5*2*T$7)/(T$7*14),0)+IF($O$11="Y",(SUMIF($CS$3:$DT$3,T$1,$CS$8:$DT$8)*CV$11-SUMIF($CS$3:$DT$3,S$1,$CS$8:$DT$8)*CU$11)*($M94*$N94*2*T$7+$P96*T$7+$O94*$M94*1.5*2*T$7)/(T$7*14),0),T95) -> 0 | U94: =IF(U95="",$M94*$N94*2*U$7+$P96*U$7+$O94*$M94*1.5*2*U$7+IF($O$10="Y",(SUMIF($CS$3:$DT$3,U$1,$CS$8:$DT$8)-SUMIF($CS$3:$DT$3,T$1,$CS$8:$DT$8))*($M94*$N94*2*U$7+$P96*U$7+$O94*$M94*1.5*2*U$7)/(U$7*14),0)+IF($O$11="Y",(SUMIF($CS$3:$DT$3,U$1,$CS$8:$DT$8)*CW$11-SUMIF($CS$3:$DT$3,T$1,$CS$8:$DT$8)*CV$11)*($M94*$N94*2*U$7+$P96*U$7+$O94*$M94*1.5*2*U$7)/(U$7*14),0),U95) -> 0 | V94: =IF(V95="",$M94*$N94*2*V$7+$P96*V$7+$O94*$M94*1.5*2*V$7+IF($O$10="Y",(SUMIF($CS$3:$DT$3,V$1,$CS$8:$DT$8)-SUMIF($CS$3:$DT$3,U$1,$CS$8:$DT$8))*($M94*$N94*2*V$7+$P96*V$7+$O94*$M94*1.5*2*V$7)/(V$7*14),0)+IF($O$11="Y",(SUMIF($CS$3:$DT$3,V$1,$CS$8:$DT$8)*CX$11-SUMIF($CS$3:$DT$3,U$1,$CS$8:$DT$8)*CW$11)*($M94*$N94*2*V$7+$P96*V$7+$O94*$M94*1.5*2*V$7)/(V$7*14),0),V95) -> 0 | W94: =IF(W95="",$M94*$N94*2*W$7+$P96*W$7+$O94*$M94*1.5*2*W$7+IF($O$10="Y",(SUMIF($CS$3:$DT$3,W$1,$CS$8:$DT$8)-SUMIF($CS$3:$DT$3,V$1,$CS$8:$DT$8))*($M94*$N94*2*W$7+$P96*W$7+$O94*$M94*1.5*2*W$7)/(W$7*14),0)+IF($O$11="Y",(SUMIF($CS$3:$DT$3,W$1,$CS$8:$DT$8)*CY$11-SUMIF($CS$3:$DT$3,V$1,$CS$8:$DT$8)*CX$11)*($M94*$N94*2*W$7+$P96*W$7+$O94*$M94*1.5*2*W$7)/(W$7*14),0),W95) -> 0 | X94: =IF(X95="",$M94*$N94*2*X$7+$P96*X$7+$O94*$M94*1.5*2*X$7+IF($O$10="Y",(SUMIF($CS$3:$DT$3,X$1,$CS$8:$DT$8)-SUMIF($CS$3:$DT$3,W$1,$CS$8:$DT$8))*($M94*$N94*2*X$7+$P96*X$7+$O94*$M94*1.5*2*X$7)/(X$7*14),0)+IF($O$11="Y",(SUMIF($CS$3:$DT$3,X$1,$CS$8:$DT$8)*CZ$11-SUMIF($CS$3:$DT$3,W$1,$CS$8:$DT$8)*CY$11)*($M94*$N94*2*X$7+$P96*X$7+$O94*$M94*1.5*2*X$7)/(X$7*14),0),X95) -> 0 | Y94: =IF(Y95="",$M94*$N94*2*Y$7+$P96*Y$7+$O94*$M94*1.5*2*Y$7+IF($O$10="Y",(SUMIF($CS$3:$DT$3,Y$1,$CS$8:$DT$8)-SUMIF($CS$3:$DT$3,X$1,$CS$8:$DT$8))*($M94*$N94*2*Y$7+$P96*Y$7+$O94*$M94*1.5*2*Y$7)/(Y$7*14),0)+IF($O$11="Y",(SUMIF($CS$3:$DT$3,Y$1,$CS$8:$DT$8)*DA$11-SUMIF($CS$3:$DT$3,X$1,$CS$8:$DT$8)*CZ$11)*($M94*$N94*2*Y$7+$P96*Y$7+$O94*$M94*1.5*2*Y$7)/(Y$7*14),0),Y95) -> 0 | Z94: =IF(Z95="",$M94*$N94*2*Z$7+$P96*Z$7+$O94*$M94*1.5*2*Z$7+IF($O$10="Y",(SUMIF($CS$3:$DT$3,Z$1,$CS$8:$DT$8)-SUMIF($CS$3:$DT$3,Y$1,$CS$8:$DT$8))*($M94*$N94*2*Z$7+$P96*Z$7+$O94*$M94*1.5*2*Z$7)/(Z$7*14),0)+IF($O$11="Y",(SUMIF($CS$3:$DT$3,Z$1,$CS$8:$DT$8)*DB$11-SUMIF($CS$3:$DT$3,Y$1,$CS$8:$DT$8)*DA$11)*($M94*$N94*2*Z$7+$P96*Z$7+$O94*$M94*1.5*2*Z$7)/(Z$7*14),0),Z95) -> 0 | ... AD94: =IF(AD95="",$M94*$N94*2*AD$7+$P96*AD$7+$O94*$M94*1.5*2*AD$7+IF($O$10="Y",(SUMIF($CS$3:$DT$3,AD$1,$CS$8:$DT$8)-SUMIF($CS$3:$DT$3,AC$1,$CS$8:$DT$8))*($M94*$N94*2*AD$7+$P96*AD$7+$O94*$M94*1.5*2*AD$7)/(AD$7*14),0)+IF($O$11="Y",(SUMIF($CS$3:$DT$3,AD$1,$CS$8:$DT$8)*DF$11-SUMIF($CS$3:$DT$3,AC$1,$CS$8:$DT$8)*DE$11)*($M94*$N94*2*AD$7+$P96*AD$7+$O94*$M94*1.5*2*AD$7)/(AD$7*14),0),AD95) -> 0 | AE94: =SUM(S94:AD94) -> 0
A95: =A94 -> Uncheck to Hide | AG95: =IF(AE94=0,0,1) -> 0 | AH95: =IF(AG95=0,".",IF($AG$46>1,", 1 at "," at ")&"$"&ROUND(M94,2)&"/hour, working "&N94&" hours per week with"&IF(E94>0," housing.","out housing.")) -> .
A96: Do not check this box | P96: =+M94*N94*R94/AE$7 -> 0 | S96: =IF(S95>0,S95-$P96*S$7,+S94-$P96*S$7) -> 0 | T96: =IF(T95>0,T95-$P96*T$7,+T94-$P96*T$7) -> 0 | U96: =IF(U95>0,U95-$P96*U$7,+U94-$P96*U$7) -> 0 | V96: =IF(V95>0,V95-$P96*V$7,+V94-$P96*V$7) -> 0 | W96: =IF(W95>0,W95-$P96*W$7,+W94-$P96*W$7) -> 0 | X96: =IF(X95>0,X95-$P96*X$7,+X94-$P96*X$7) -> 0 | Y96: =IF(Y95>0,Y95-$P96*Y$7,+Y94-$P96*Y$7) -> 0 | Z96: =IF(Z95>0,Z95-$P96*Z$7,+Z94-$P96*Z$7) -> 0 | ... AD96: =IF(AD95>0,AD95-$P96*AD$7,+AD94-$P96*AD$7) -> 0
A97: Do not check this box | S97: =+S96 -> 0 | T97: =+T96+S97 -> 0 | U97: =+U96+T97 -> 0 | V97: =+V96+U97 -> 0 | W97: =+W96+V97 -> 0 | X97: =+X96+W97 -> 0 | Y97: =+Y96+X97 -> 0 | Z97: =+Z96+Y97 -> 0 | AA97: =+AA96+Z97 -> 0 | ... AD97: =+AD96+AC97 -> 0
A98: =A95 -> Uncheck to Hide | C98: Payroll Tax | S98: =IF($E$9="CA",IF(R97<7000,$E$5*S96,($E$5-0.043)*S96),IF($E$9="IL",IF(R97<12960,$E$5*S96,($E$5-0.04125)*S96),IF($E$9="PA",IF(R97<10000,$E$5*S96,($E$5-0.071)*S96),IF($E$9="TX",IF(R97<9000,$E$5*S96,($E$5-0.0363)*S96),$E$5*S96)))) -> 0 | T98: =IF($E$9="CA",IF(S97<7000,$E$5*T96,($E$5-0.043)*T96),IF($E$9="IL",IF(S97<12960,$E$5*T96,($E$5-0.04125)*T96),IF($E$9="PA",IF(S97<10000,$E$5*T96,($E$5-0.071)*T96),IF($E$9="TX",IF(S97<9000,$E$5*T96,($E$5-0.0363)*T96),$E$5*T96)))) -> 0 | U98: =IF($E$9="CA",IF(T97<7000,$E$5*U96,($E$5-0.043)*U96),IF($E$9="IL",IF(T97<12960,$E$5*U96,($E$5-0.04125)*U96),IF($E$9="PA",IF(T97<10000,$E$5*U96,($E$5-0.071)*U96),IF($E$9="TX",IF(T97<9000,$E$5*U96,($E$5-0.0363)*U96),$E$5*U96)))) -> 0 | V98: =IF($E$9="CA",IF(U97<7000,$E$5*V96,($E$5-0.043)*V96),IF($E$9="IL",IF(U97<12960,$E$5*V96,($E$5-0.04125)*V96),IF($E$9="PA",IF(U97<10000,$E$5*V96,($E$5-0.071)*V96),IF($E$9="TX",IF(U97<9000,$E$5*V96,($E$5-0.0363)*V96),$E$5*V96)))) -> 0 | W98: =IF($E$9="CA",IF(V97<7000,$E$5*W96,($E$5-0.043)*W96),IF($E$9="IL",IF(V97<12960,$E$5*W96,($E$5-0.04125)*W96),IF($E$9="PA",IF(V97<10000,$E$5*W96,($E$5-0.071)*W96),IF($E$9="TX",IF(V97<9000,$E$5*W96,($E$5-0.0363)*W96),$E$5*W96)))) -> 0 | X98: =IF($E$9="CA",IF(W97<7000,$E$5*X96,($E$5-0.043)*X96),IF($E$9="IL",IF(W97<12960,$E$5*X96,($E$5-0.04125)*X96),IF($E$9="PA",IF(W97<10000,$E$5*X96,($E$5-0.071)*X96),IF($E$9="TX",IF(W97<9000,$E$5*X96,($E$5-0.0363)*X96),$E$5*X96)))) -> 0 | Y98: =IF($E$9="CA",IF(X97<7000,$E$5*Y96,($E$5-0.043)*Y96),IF($E$9="IL",IF(X97<12960,$E$5*Y96,($E$5-0.04125)*Y96),IF($E$9="PA",IF(X97<10000,$E$5*Y96,($E$5-0.071)*Y96),IF($E$9="TX",IF(X97<9000,$E$5*Y96,($E$5-0.0363)*Y96),$E$5*Y96)))) -> 0 | Z98: =IF($E$9="CA",IF(Y97<7000,$E$5*Z96,($E$5-0.043)*Z96),IF($E$9="IL",IF(Y97<12960,$E$5*Z96,($E$5-0.04125)*Z96),IF($E$9="PA",IF(Y97<10000,$E$5*Z96,($E$5-0.071)*Z96),IF($E$9="TX",IF(Y97<9000,$E$5*Z96,($E$5-0.0363)*Z96),$E$5*Z96)))) -> 0 | ... AD98: =IF($E$9="CA",IF(AC97<7000,$E$5*AD96,($E$5-0.043)*AD96),IF($E$9="IL",IF(AC97<12960,$E$5*AD96,($E$5-0.04125)*AD96),IF($E$9="PA",IF(AC97<10000,$E$5*AD96,($E$5-0.071)*AD96),IF($E$9="TX",IF(AC97<9000,$E$5*AD96,($E$5-0.0363)*AD96),$E$5*AD96)))) -> 0
A99: =A98 -> Uncheck to Hide | C99: Workman's Comp | S99: =IF($E$9="WA",IF(S$1<$G$6,$E$6*$N94*2*S$7+$CA$5*S96,$F$6*$N94*2*S$7+$CA$5*S96),IF($E$9="NV",IF(R97>36000,0,IF(S$1<$G$6,$E$6*S96,$F$6*S96)),IF(S$1<$G$6,$E$6*S96,$F$6*S96))) -> 0 | T99: =IF($E$9="WA",IF(T$1<$G$6,$E$6*$N94*2*T$7+$CA$5*T96,$F$6*$N94*2*T$7+$CA$5*T96),IF($E$9="NV",IF(S97>36000,0,IF(T$1<$G$6,$E$6*T96,$F$6*T96)),IF(T$1<$G$6,$E$6*T96,$F$6*T96))) -> 0 | U99: =IF($E$9="WA",IF(U$1<$G$6,$E$6*$N94*2*U$7+$CA$5*U96,$F$6*$N94*2*U$7+$CA$5*U96),IF($E$9="NV",IF(T97>36000,0,IF(U$1<$G$6,$E$6*U96,$F$6*U96)),IF(U$1<$G$6,$E$6*U96,$F$6*U96))) -> 0 | V99: =IF($E$9="WA",IF(V$1<$G$6,$E$6*$N94*2*V$7+$CA$5*V96,$F$6*$N94*2*V$7+$CA$5*V96),IF($E$9="NV",IF(U97>36000,0,IF(V$1<$G$6,$E$6*V96,$F$6*V96)),IF(V$1<$G$6,$E$6*V96,$F$6*V96))) -> 0 | W99: =IF($E$9="WA",IF(W$1<$G$6,$E$6*$N94*2*W$7+$CA$5*W96,$F$6*$N94*2*W$7+$CA$5*W96),IF($E$9="NV",IF(V97>36000,0,IF(W$1<$G$6,$E$6*W96,$F$6*W96)),IF(W$1<$G$6,$E$6*W96,$F$6*W96))) -> 0 | X99: =IF($E$9="WA",IF(X$1<$G$6,$E$6*$N94*2*X$7+$CA$5*X96,$F$6*$N94*2*X$7+$CA$5*X96),IF($E$9="NV",IF(W97>36000,0,IF(X$1<$G$6,$E$6*X96,$F$6*X96)),IF(X$1<$G$6,$E$6*X96,$F$6*X96))) -> 0 | Y99: =IF($E$9="WA",IF(Y$1<$G$6,$E$6*$N94*2*Y$7+$CA$5*Y96,$F$6*$N94*2*Y$7+$CA$5*Y96),IF($E$9="NV",IF(X97>36000,0,IF(Y$1<$G$6,$E$6*Y96,$F$6*Y96)),IF(Y$1<$G$6,$E$6*Y96,$F$6*Y96))) -> 0 | Z99: =IF($E$9="WA",IF(Z$1<$G$6,$E$6*$N94*2*Z$7+$CA$5*Z96,$F$6*$N94*2*Z$7+$CA$5*Z96),IF($E$9="NV",IF(Y97>36000,0,IF(Z$1<$G$6,$E$6*Z96,$F$6*Z96)),IF(Z$1<$G$6,$E$6*Z96,$F$6*Z96))) -> 0 | ... AD99: =IF($E$9="WA",IF(AD$1<$G$6,$E$6*$N94*2*AD$7+$CA$5*AD96,$F$6*$N94*2*AD$7+$CA$5*AD96),IF($E$9="NV",IF(AC97>36000,0,IF(AD$1<$G$6,$E$6*AD96,$F$6*AD96)),IF(AD$1<$G$6,$E$6*AD96,$F$6*AD96))) -> 0
A100: =A99 -> Uncheck to Hide | C100: 401K Match | S100: =IF(S94=0,0,$H$11/26*S$7*IF(OR($G94=0,$G94=1),1,$G94)) -> 0 | T100: =IF(T94=0,0,$H$11/26*T$7*IF(OR($G94=0,$G94=1),1,$G94)) -> 0 | U100: =IF(U94=0,0,$H$11/26*U$7*IF(OR($G94=0,$G94=1),1,$G94)) -> 0 | V100: =IF(V94=0,0,$H$11/26*V$7*IF(OR($G94=0,$G94=1),1,$G94)) -> 0 | W100: =IF(W94=0,0,$H$11/26*W$7*IF(OR($G94=0,$G94=1),1,$G94)) -> 0 | X100: =IF(X94=0,0,$H$11/26*X$7*IF(OR($G94=0,$G94=1),1,$G94)) -> 0 | Y100: =IF(Y94=0,0,$H$11/26*Y$7*IF(OR($G94=0,$G94=1),1,$G94)) -> 0 | Z100: =IF(Z94=0,0,$H$11/26*Z$7*IF(OR($G94=0,$G94=1),1,$G94)) -> 0 | ... AD100: =IF(AD94=0,0,$H$11/26*AD$7*IF(OR($G94=0,$G94=1),1,$G94)) -> 0
...
